Workbook

Sheet NVA. EST. PROGRAMATICA 2026
A1: DG | B1: ÁREA ADMINISTRATIVA | C1: Fin | D1: FN | E1: SF | F1: PG | G1: SP | H1: Py | I1: DG | K1: D Aux | P1: Denominación de Programa | Q1: Denominación de Proyecto | R1: Descripción de Acciones | S1: Tipo de Indicador | T1: Unidad de Medida
A2: D00 | B2: SECRETARÍA DEL AYUNTAMIENTO | C2: 01 | D2: 03 | E2: 09 | F2: 02 | G2: 01 | H2: 01 | I2: D00 | K2: 155 | L2: =VLOOKUP(K2,'GACETA 3'!E2:$F$75,2,0) -> Área Jurídica | M2: =CONCATENATE(C2,D2,E2,F2,G2) -> 0103090201 | N2: =VLOOKUP(M2,GACETA!$A$1:$C$186,3,0) -> M | O2: =VLOOKUP(M2,GACETA!$A$1:$C$186,2,0) -> Revisión y emisión de la reglamentación municipal | P2: Reglamentación municipal | Q2: Revisión y emisión de la reglamentación municipal | R2: Reglamentos y disposiciones de observancia general en el municipio publicadas | S2: Gestión | T2: Gaceta
C3: 01 | D3: 03 | E3: 09 | F3: 02 | G3: 01 | H3: 01 | I3: D00 | K3: 155 | L3: =VLOOKUP(K3,'GACETA 3'!E3:$F$75,2,0) -> Área Jurídica | M3: =CONCATENATE(C3,D3,E3,F3,G3) -> 0103090201 | N3: =VLOOKUP(M3,GACETA!$A$1:$C$186,3,0) -> M | O3: =VLOOKUP(M3,GACETA!$A$1:$C$186,2,0) -> Revisión y emisión de la reglamentación municipal | R3: Capacitaciones en materia reglamentaria otorgadas | S3: Gestión | T3: Capacitación
C4: 01 | D4: 03 | E4: 09 | F4: 02 | G4: 01 | H4: 01 | I4: D00 | K4: 155 | L4: =VLOOKUP(K4,'GACETA 3'!E4:$F$75,2,0) -> Área Jurídica | M4: =CONCATENATE(C4,D4,E4,F4,G4) -> 0103090201 | N4: =VLOOKUP(M4,GACETA!$A$1:$C$186,3,0) -> M | O4: =VLOOKUP(M4,GACETA!$A$1:$C$186,2,0) -> Revisión y emisión de la reglamentación municipal | R4: Revisión de propuestas viables de modificación a Leyes, decretos y reglamentos municipales | S4: Gestión | T4: Propuesta
C5: 01 | D5: 03 | E5: 09 | F5: 02 | G5: 01 | H5: 01 | I5: D00 | K5: 155 | L5: =VLOOKUP(K5,'GACETA 3'!E5:$F$75,2,0) -> Área Jurídica | M5: =CONCATENATE(C5,D5,E5,F5,G5) -> 0103090201 | N5: =VLOOKUP(M5,GACETA!$A$1:$C$186,3,0) -> M | O5: =VLOOKUP(M5,GACETA!$A$1:$C$186,2,0) -> Revisión y emisión de la reglamentación municipal | R5: Realización de sesiones de cabildo | S5: Gestión | T5: Sesión
C6: 01 | D6: 05 | E6: 02 | F6: 06 | G6: 06 | I6: D00 | K6: 114 | L6: =VLOOKUP(K6,'GACETA 3'!E6:$F$75,2,0) -> Control Patrimonial | M6: =CONCATENATE(C6,D6,E6,F6,G6) -> 0105020606 | N6: =VLOOKUP(M6,GACETA!$A$1:$C$186,3,0) -> M | O6: =VLOOKUP(M6,GACETA!$A$1:$C$186,2,0) -> Control del patrimonio y normatividad | P6: Consolidación de la administración pública de resultados | Q6: Control del patrimonio y normatividad | R6: Realizar los levantamientos fisicos de los bienes muebles e inmuebles. | S6: Gestión | T6: Bien
C7: 01 | D7: 05 | E7: 02 | F7: 06 | G7: 06 | I7: D00 | K7: 114 | L7: =VLOOKUP(K7,'GACETA 3'!E7:$F$75,2,0) -> Control Patrimonial | M7: =CONCATENATE(C7,D7,E7,F7,G7) -> 0105020606 | N7: =VLOOKUP(M7,GACETA!$A$1:$C$186,3,0) -> M | O7: =VLOOKUP(M7,GACETA!$A$1:$C$186,2,0) -> Control del patrimonio y normatividad | R7: Actualizar el inventario mediante revisiones fisicas por areas de trabajo de la Administracion Publica Municipal. | S7: Gestión | T7: Revision fisica
C8: 01 | D8: 05 | E8: 02 | F8: 06 | G8: 06 | I8: D00 | K8: 114 | L8: =VLOOKUP(K8,'GACETA 3'!E8:$F$75,2,0) -> Control Patrimonial | M8: =CONCATENATE(C8,D8,E8,F8,G8) -> 0105020606 | N8: =VLOOKUP(M8,GACETA!$A$1:$C$186,3,0) -> M | O8: =VLOOKUP(M8,GACETA!$A$1:$C$186,2,0) -> Control del patrimonio y normatividad | R8: Actualización de registros de bienes inmuebles propiedad municipal | S8: Gestión | T8: Registros actualizados
C9: 01 | D9: 03 | E9: 09 | F9: 03 | G9: 01 | I9: D00 | K9: 108 | L9: =VLOOKUP(K9,'GACETA 3'!$E$9:$F$75,2,0) -> Juzgados Cívicos | M9: =CONCATENATE(C9,D9,E9,F9,G9) -> 0103090301 | N9: =VLOOKUP(M9,GACETA!$A$1:$C$186,3,0) -> L | O9: =VLOOKUP(M9,GACETA!$A$1:$C$186,2,0) -> Mediación, conciliación y función calificadora municipal | P9: Justicia Cívica Municipal | Q9: Mediación, conciliación y función calificadora municipal | R9: Garantizar la paz social, convivencia familiar y vecinal a través de medios alternativos de solucion de controversias. | S9: Gestión | T9: Mediacion
C10: 01 | D10: 03 | E10: 09 | F10: 03 | G10: 01 | I10: D00 | K10: 108 | L10: =VLOOKUP(K10,'GACETA 3'!$E$9:$F$75,2,0) -> Juzgados Cívicos | M10: =CONCATENATE(C10,D10,E10,F10,G10) -> 0103090301 | N10: =VLOOKUP(M10,GACETA!$A$1:$C$186,3,0) -> L | O10: =VLOOKUP(M10,GACETA!$A$1:$C$186,2,0) -> Mediación, conciliación y función calificadora municipal | R10: Citar a las partes en conflicto con la finalidad de dirimir sus diferencias a través del dialogo y medios alternativos de solución | S10: Gestión | T10: Citatorio
C11: 01 | D11: 03 | E11: 09 | F11: 03 | G11: 01 | I11: D00 | K11: 108 | L11: =VLOOKUP(K11,'GACETA 3'!$E$9:$F$75,2,0) -> Juzgados Cívicos | M11: =CONCATENATE(C11,D11,E11,F11,G11) -> 0103090301 | N11: =VLOOKUP(M11,GACETA!$A$1:$C$186,3,0) -> L | O11: =VLOOKUP(M11,GACETA!$A$1:$C$186,2,0) -> Mediación, conciliación y función calificadora municipal | R11: Dar cumplimiento a los ordenamientos legales a través de la aplicación de sanciones por infracciones | S11: Gestión | T11: Sanción
C12: 01 | D12: 03 | E12: 09 | F12: 03 | G12: 01 | I12: D00 | K12: 108 | L12: =VLOOKUP(K12,'GACETA 3'!$E$9:$F$75,2,0) -> Juzgados Cívicos | M12: =CONCATENATE(C12,D12,E12,F12,G12) -> 0103090301 | N12: =VLOOKUP(M12,GACETA!$A$1:$C$186,3,0) -> L | O12: =VLOOKUP(M12,GACETA!$A$1:$C$186,2,0) -> Mediación, conciliación y función calificadora municipal | R12: Capacitaciones en tematicas relacionadas a la Justicia Civica | S12: Gestión | T12: Capacitación
C13: 01 | D13: 03 | E13: 09 | F13: 03 | G13: 01 | I13: D00 | K13: 108 | L13: =VLOOKUP(K13,'GACETA 3'!$E$9:$F$75,2,0) -> Juzgados Cívicos | M13: =CONCATENATE(C13,D13,E13,F13,G13) -> 0103090301 | N13: =VLOOKUP(M13,GACETA!$A$1:$C$186,3,0) -> L | O13: =VLOOKUP(M13,GACETA!$A$1:$C$186,2,0) -> Mediación, conciliación y función calificadora municipal | R13: Difusión de la cultura civica y cultura de la legalidad en medios de comunicación | S13: Gestión | T13: Post
C14: 01 | D14: 03 | E14: 09 | F14: 03 | G14: 01 | I14: D00 | K14: 108 | L14: =VLOOKUP(K14,'GACETA 3'!$E$9:$F$75,2,0) -> Juzgados Cívicos | M14: =CONCATENATE(C14,D14,E14,F14,G14) -> 0103090301 | N14: =VLOOKUP(M14,GACETA!$A$1:$C$186,3,0) -> L | O14: =VLOOKUP(M14,GACETA!$A$1:$C$186,2,0) -> Mediación, conciliación y función calificadora municipal | R14: Informes de Resultados de las Acciones del Juzgado Cívico | S14: Gestión | T14: Informe
C15: 01 | D15: 03 | E15: 09 | F15: 03 | G15: 01 | I15: D00 | K15: 108 | L15: =VLOOKUP(K15,'GACETA 3'!$E$9:$F$75,2,0) -> Juzgados Cívicos | M15: =CONCATENATE(C15,D15,E15,F15,G15) -> 0103090301 | N15: =VLOOKUP(M15,GACETA!$A$1:$C$186,3,0) -> L | O15: =VLOOKUP(M15,GACETA!$A$1:$C$186,2,0) -> Mediación, conciliación y función calificadora municipal | R15: Jornadas de Trabajo en favor de la comunidad | S15: Gestión | T15: Jornada
C16: 01 | D16: 03 | E16: 09 | F16: 03 | G16: 01 | I16: D00 | K16: 108 | L16: =VLOOKUP(K16,'GACETA 3'!$E$9:$F$75,2,0) -> Juzgados Cívicos | M16: =CONCATENATE(C16,D16,E16,F16,G16) -> 0103090301 | N16: =VLOOKUP(M16,GACETA!$A$1:$C$186,3,0) -> L | O16: =VLOOKUP(M16,GACETA!$A$1:$C$186,2,0) -> Mediación, conciliación y función calificadora municipal | R16: Proporcionar asesorias psicologicas y preventivas escolares, enfocado a pdres y adolecentes | S16: Gestión | T16: Asesorías
C17: 01 | D17: 03 | E17: 09 | F17: 03 | G17: 01 | I17: D00 | K17: 108 | L17: =VLOOKUP(K17,'GACETA 3'!$E$9:$F$75,2,0) -> Juzgados Cívicos | M17: =CONCATENATE(C17,D17,E17,F17,G17) -> 0103090301 | N17: =VLOOKUP(M17,GACETA!$A$1:$C$186,3,0) -> L | O17: =VLOOKUP(M17,GACETA!$A$1:$C$186,2,0) -> Mediación, conciliación y función calificadora municipal | R17: Realizar talleres para jovenes menores infractores para su readapatcion | S17: Gestión | T17: Taller
C18: 01 | D18: 08 | E18: 01 | F18: 01 | G18: 02 | I18: D00 | K18: 109 | L18: =VLOOKUP(K18,'GACETA 3'!$E$9:$F$75,2,0) -> Registro Civil | M18: =CONCATENATE(C18,D18,E18,F18,G18) -> 0108010102 | N18: =VLOOKUP(M18,GACETA!$A$1:$C$186,3,0) -> E | O18: =VLOOKUP(M18,GACETA!$A$1:$C$186,2,0) -> Actualización y operación del registro civil | P18: Protección Jurídica de las Personas | Q18: Actualizacion y operación del Registro Civil | R18: Emitir copias certificadas de actas en las Oficialías del registro civil aporvechando el uso de las tecnologías | S18: Gestión | T18: Copia
C19: 01 | D19: 08 | E19: 01 | F19: 01 | G19: 02 | I19: D00 | K19: 109 | L19: =VLOOKUP(K19,'GACETA 3'!$E$9:$F$75,2,0) -> Registro Civil | M19: =CONCATENATE(C19,D19,E19,F19,G19) -> 0108010102 | N19: =VLOOKUP(M19,GACETA!$A$1:$C$186,3,0) -> E | O19: =VLOOKUP(M19,GACETA!$A$1:$C$186,2,0) -> Actualización y operación del registro civil | R19: Proporcionar las constancias de no registro de una forma más ágil a los solicitantes | S19: Gestión | T19: Constancia
C20: 01 | D20: 08 | E20: 01 | F20: 01 | G20: 02 | I20: D00 | K20: 109 | L20: =VLOOKUP(K20,'GACETA 3'!$E$9:$F$75,2,0) -> Registro Civil | M20: =CONCATENATE(C20,D20,E20,F20,G20) -> 0108010102 | N20: =VLOOKUP(M20,GACETA!$A$1:$C$186,3,0) -> E | O20: =VLOOKUP(M20,GACETA!$A$1:$C$186,2,0) -> Actualización y operación del registro civil | R20: Supervisiones a las oficialías del Registro Civil | S20: Gestión | T20: Supervisión
C21: 01 | D21: 08 | E21: 01 | F21: 01 | G21: 02 | I21: D00 | K21: 109 | L21: =VLOOKUP(K21,'GACETA 3'!$E$9:$F$75,2,0) -> Registro Civil | M21: =CONCATENATE(C21,D21,E21,F21,G21) -> 0108010102 | N21: =VLOOKUP(M21,GACETA!$A$1:$C$186,3,0) -> E | O21: =VLOOKUP(M21,GACETA!$A$1:$C$186,2,0) -> Actualización y operación del registro civil | R21: Evaluar el número de parejas que regularizan su estado civil mediante campañas de matrimonios masivos | S21: Gestión | T21: Campaña
C22: 01 | D22: 08 | E22: 01 | F22: 01 | G22: 02 | I22: D00 | K22: 109 | L22: =VLOOKUP(K22,'GACETA 3'!$E$9:$F$75,2,0) -> Registro Civil | M22: =CONCATENATE(C22,D22,E22,F22,G22) -> 0108010102 | N22: =VLOOKUP(M22,GACETA!$A$1:$C$186,3,0) -> E | O22: =VLOOKUP(M22,GACETA!$A$1:$C$186,2,0) -> Actualización y operación del registro civil | R22: Incrementar el número de personas que regularicen su estatus jurídico y personalidad, mediante campañas de registros extemporáneos | S22: Gestión | T22: Registro
C23: 01 | D23: 08 | E23: 01 | F23: 01 | G23: 02 | I23: D00 | K23: 109 | L23: =VLOOKUP(K23,'GACETA 3'!$E$9:$F$75,2,0) -> Registro Civil | M23: =CONCATENATE(C23,D23,E23,F23,G23) -> 0108010102 | N23: =VLOOKUP(M23,GACETA!$A$1:$C$186,3,0) -> E | O23: =VLOOKUP(M23,GACETA!$A$1:$C$186,2,0) -> Actualización y operación del registro civil | R23: Jornadas ciudadanas (matrimonios, registro de nacimientos, expedición de copias, reclusorios) | S23: Gestión | T23: Jornada
A24: B01 | B24: Sindicatura I | C24: 02 | D24: 02 | E24: 02 | F24: 01 | G24: 02 | I24: B01 | K24: 110 | L24: =VLOOKUP(K24,'GACETA 3'!$E$9:$F$75,2,0) -> Acción Cívica | M24: =CONCATENATE(C24,D24,E24,F24,G24) -> 0202020102 | N24: =VLOOKUP(M24,GACETA!$A$1:$C$186,3,0) -> M | O24: =VLOOKUP(M24,GACETA!$A$1:$C$186,2,0) -> Apoyo Solidario | P24: Desarrollo comunitario | Q24: Apoyo solidario | R24: Realizar acciones, obras y apoyos en comunidades por medio de atención a la ciudadanía | S24: Gestión | T24: Solicitudes
C25: 02 | D25: 02 | E25: 02 | F25: 01 | G25: 02 | I25: B02 | K25: 110 | L25: =VLOOKUP(K25,'GACETA 3'!$E$9:$F$75,2,0) -> Acción Cívica | M25: =CONCATENATE(C25,D25,E25,F25,G25) -> 0202020102 | N25: =VLOOKUP(M25,GACETA!$A$1:$C$186,3,0) -> M | O25: =VLOOKUP(M25,GACETA!$A$1:$C$186,2,0) -> Apoyo Solidario | R25: Llevar acabo Sesiones de cabildo para abordar temas en benificio de la poblacion | S25: Gestión | T25: Asistencia
C26: 02 | D26: 02 | E26: 02 | F26: 01 | G26: 02 | I26: B01 | K26: 110 | L26: =VLOOKUP(K26,'GACETA 3'!$E$9:$F$75,2,0) -> Acción Cívica | M26: =CONCATENATE(C26,D26,E26,F26,G26) -> 0202020102 | N26: =VLOOKUP(M26,GACETA!$A$1:$C$186,3,0) -> M | O26: =VLOOKUP(M26,GACETA!$A$1:$C$186,2,0) -> Apoyo Solidario | R26: Realizar sesiones coadyuvando con las áreas administrativas municipales en encomineda establecida bajo comité | S26: Gestión | T26: Sesiones
A27: B02 | B27: Sindicatura II | C27: 02 | D27: 02 | E27: 02 | F27: 01 | G27: 02 | I27: B02 | K27: 110 | L27: =VLOOKUP(K27,'GACETA 3'!$E$9:$F$75,2,0) -> Acción Cívica | M27: =CONCATENATE(C27,D27,E27,F27,G27) -> 0202020102 | N27: =VLOOKUP(M27,GACETA!$A$1:$C$186,3,0) -> M | O27: =VLOOKUP(M27,GACETA!$A$1:$C$186,2,0) -> Apoyo Solidario | P27: Desarrollo comunitario | Q27: Apoyo solidario | R27: Realizar acciones, obras y apoyos en comunidades por medio de atención a la ciudadanía | S27: Gestión | T27: Solicitudes
C28: 02 | D28: 02 | E28: 02 | F28: 01 | G28: 02 | I28: B02 | K28: 110 | L28: =VLOOKUP(K28,'GACETA 3'!$E$9:$F$75,2,0) -> Acción Cívica | M28: =CONCATENATE(C28,D28,E28,F28,G28) -> 0202020102 | N28: =VLOOKUP(M28,GACETA!$A$1:$C$186,3,0) -> M | O28: =VLOOKUP(M28,GACETA!$A$1:$C$186,2,0) -> Apoyo Solidario | R28: Llevar acabo Sesiones de cabildo para abordar temas en benificio de la poblacion | S28: Gestión | T28: Asistencia
C29: 02 | D29: 02 | E29: 02 | F29: 01 | G29: 02 | I29: B02 | K29: 110 | L29: =VLOOKUP(K29,'GACETA 3'!$E$9:$F$75,2,0) -> Acción Cívica | M29: =CONCATENATE(C29,D29,E29,F29,G29) -> 0202020102 | N29: =VLOOKUP(M29,GACETA!$A$1:$C$186,3,0) -> M | O29: =VLOOKUP(M29,GACETA!$A$1:$C$186,2,0) -> Apoyo Solidario | R29: Realizar sesiones coadyuvando con las áreas administrativas municipales en encomineda establecida bajo comité | S29: Gestión | T29: Sesiones
A30: C01 | B30: REGIDURÍA I | C30: 02 | D30: 02 | E30: 02 | F30: 01 | G30: 02 | I30: C01 | K30: 110 | L30: =VLOOKUP(K30,'GACETA 3'!$E$9:$F$75,2,0) -> Acción Cívica | M30: =CONCATENATE(C30,D30,E30,F30,G30) -> 0202020102 | N30: =VLOOKUP(M30,GACETA!$A$1:$C$186,3,0) -> M | O30: =VLOOKUP(M30,GACETA!$A$1:$C$186,2,0) -> Apoyo Solidario | P30: Desarrollo comunitario | Q30: Apoyo solidario | R30: Realizar acciones, obras y apoyos en comunidades por medio de atención a la ciudadanía | S30: Gestión | T30: Solicitudes
C31: 02 | D31: 02 | E31: 02 | F31: 01 | G31: 02 | I31: B02 | K31: 110 | L31: =VLOOKUP(K31,'GACETA 3'!$E$9:$F$75,2,0) -> Acción Cívica | M31: =CONCATENATE(C31,D31,E31,F31,G31) -> 0202020102 | N31: =VLOOKUP(M31,GACETA!$A$1:$C$186,3,0) -> M | O31: =VLOOKUP(M31,GACETA!$A$1:$C$186,2,0) -> Apoyo Solidario | R31: Llevar acabo Sesiones de cabildo para abordar temas en benificio de la poblacion | S31: Gestión | T31: Asistencia
C32: 02 | D32: 02 | E32: 02 | F32: 01 | G32: 02 | I32: C01 | K32: 110 | L32: =VLOOKUP(K32,'GACETA 3'!$E$9:$F$75,2,0) -> Acción Cívica | M32: =CONCATENATE(C32,D32,E32,F32,G32) -> 0202020102 | N32: =VLOOKUP(M32,GACETA!$A$1:$C$186,3,0) -> M | O32: =VLOOKUP(M32,GACETA!$A$1:$C$186,2,0) -> Apoyo Solidario | R32: Realizar sesiones coadyuvando con las áreas administrativas municipales en encomineda establecida bajo comité | S32: Gestión | T32: Sesiones
A33: C02 | B33: REGIDURÍA II | C33: 02 | D33: 02 | E33: 02 | F33: 01 | G33: 02 | I33: C02 | K33: 110 | L33: =VLOOKUP(K33,'GACETA 3'!$E$9:$F$75,2,0) -> Acción Cívica | M33: =CONCATENATE(C33,D33,E33,F33,G33) -> 0202020102 | N33: =VLOOKUP(M33,GACETA!$A$1:$C$186,3,0) -> M | O33: =VLOOKUP(M33,GACETA!$A$1:$C$186,2,0) -> Apoyo Solidario | P33: Desarrollo comunitario | Q33: Apoyo solidario | R33: Realizar acciones, obras y apoyos en comunidades por medio de atención a la ciudadanía | S33: Gestión | T33: Solicitudes
C34: 02 | D34: 02 | E34: 02 | F34: 01 | G34: 02 | I34: B02 | K34: 110 | L34: =VLOOKUP(K34,'GACETA 3'!$E$9:$F$75,2,0) -> Acción Cívica | M34: =CONCATENATE(C34,D34,E34,F34,G34) -> 0202020102 | N34: =VLOOKUP(M34,GACETA!$A$1:$C$186,3,0) -> M | O34: =VLOOKUP(M34,GACETA!$A$1:$C$186,2,0) -> Apoyo Solidario | R34: Llevar acabo Sesiones de cabildo para abordar temas en benificio de la poblacion | S34: Gestión | T34: Asistencia
C35: 02 | D35: 02 | E35: 02 | F35: 01 | G35: 02 | I35: C02 | K35: 110 | L35: =VLOOKUP(K35,'GACETA 3'!$E$9:$F$75,2,0) -> Acción Cívica | M35: =CONCATENATE(C35,D35,E35,F35,G35) -> 0202020102 | N35: =VLOOKUP(M35,GACETA!$A$1:$C$186,3,0) -> M | O35: =VLOOKUP(M35,GACETA!$A$1:$C$186,2,0) -> Apoyo Solidario | R35: Realizar sesiones coadyuvando con las áreas administrativas municipales en encomineda establecida bajo comité | S35: Gestión | T35: Sesiones
A36: C03 | B36: REGIDURÍA III | C36: 02 | D36: 02 | E36: 02 | F36: 01 | G36: 02 | I36: C03 | K36: 110 | L36: =VLOOKUP(K36,'GACETA 3'!$E$9:$F$75,2,0) -> Acción Cívica | M36: =CONCATENATE(C36,D36,E36,F36,G36) -> 0202020102 | N36: =VLOOKUP(M36,GACETA!$A$1:$C$186,3,0) -> M | O36: =VLOOKUP(M36,GACETA!$A$1:$C$186,2,0) -> Apoyo Solidario | P36: Desarrollo comunitario | Q36: Apoyo solidario | R36: Realizar acciones, obras y apoyos en comunidades por medio de atención a la ciudadanía | S36: Gestión | T36: Solicitudes
C37: 02 | D37: 02 | E37: 02 | F37: 01 | G37: 02 | I37: B02 | K37: 110 | L37: =VLOOKUP(K37,'GACETA 3'!$E$9:$F$75,2,0) -> Acción Cívica | M37: =CONCATENATE(C37,D37,E37,F37,G37) -> 0202020102 | N37: =VLOOKUP(M37,GACETA!$A$1:$C$186,3,0) -> M | O37: =VLOOKUP(M37,GACETA!$A$1:$C$186,2,0) -> Apoyo Solidario | R37: Llevar acabo Sesiones de cabildo para abordar temas en benificio de la poblacion | S37: Gestión | T37: Asistencia
C38: 02 | D38: 02 | E38: 02 | F38: 01 | G38: 02 | I38: C03 | K38: 110 | L38: =VLOOKUP(K38,'GACETA 3'!$E$9:$F$75,2,0) -> Acción Cívica | M38: =CONCATENATE(C38,D38,E38,F38,G38) -> 0202020102 | N38: =VLOOKUP(M38,GACETA!$A$1:$C$186,3,0) -> M | O38: =VLOOKUP(M38,GACETA!$A$1:$C$186,2,0) -> Apoyo Solidario | R38: Realizar sesiones coadyuvando con las áreas administrativas municipales en encomineda establecida bajo comité | S38: Gestión | T38: Sesiones
A39: C04 | B39: REGIDURÍA IV | C39: 02 | D39: 02 | E39: 02 | F39: 01 | G39: 02 | I39: C04 | K39: 110 | L39: =VLOOKUP(K39,'GACETA 3'!$E$9:$F$75,2,0) -> Acción Cívica | M39: =CONCATENATE(C39,D39,E39,F39,G39) -> 0202020102 | N39: =VLOOKUP(M39,GACETA!$A$1:$C$186,3,0) -> M | O39: =VLOOKUP(M39,GACETA!$A$1:$C$186,2,0) -> Apoyo Solidario | P39: Desarrollo comunitario | Q39: Apoyo solidario | R39: Realizar acciones, obras y apoyos en comunidades por medio de atención a la ciudadanía | S39: Gestión | T39: Solicitudes
C40: 02 | D40: 02 | E40: 02 | F40: 01 | G40: 02 | I40: B02 | K40: 110 | L40: =VLOOKUP(K40,'GACETA 3'!$E$9:$F$75,2,0) -> Acción Cívica | M40: =CONCATENATE(C40,D40,E40,F40,G40) -> 0202020102 | N40: =VLOOKUP(M40,GACETA!$A$1:$C$186,3,0) -> M | O40: =VLOOKUP(M40,GACETA!$A$1:$C$186,2,0) -> Apoyo Solidario | R40: Llevar acabo Sesiones de cabildo para abordar temas en benificio de la poblacion | S40: Gestión | T40: Asistencia
C41: 02 | D41: 02 | E41: 02 | F41: 01 | G41: 02 | I41: C04 | K41: 110 | L41: =VLOOKUP(K41,'GACETA 3'!$E$9:$F$75,2,0) -> Acción Cívica | M41: =CONCATENATE(C41,D41,E41,F41,G41) -> 0202020102 | N41: =VLOOKUP(M41,GACETA!$A$1:$C$186,3,0) -> M | O41: =VLOOKUP(M41,GACETA!$A$1:$C$186,2,0) -> Apoyo Solidario | R41: Realizar sesiones coadyuvando con las áreas administrativas municipales en encomineda establecida bajo comité | S41: Gestión | T41: Sesiones
A42: C05 | B42: REGIDURÍA V | C42: 02 | D42: 02 | E42: 02 | F42: 01 | G42: 02 | I42: C05 | K42: 110 | L42: =VLOOKUP(K42,'GACETA 3'!$E$9:$F$75,2,0) -> Acción Cívica | M42: =CONCATENATE(C42,D42,E42,F42,G42) -> 0202020102 | N42: =VLOOKUP(M42,GACETA!$A$1:$C$186,3,0) -> M | O42: =VLOOKUP(M42,GACETA!$A$1:$C$186,2,0) -> Apoyo Solidario | P42: Desarrollo comunitario | Q42: Apoyo solidario | R42: Realizar acciones, obras y apoyos en comunidades por medio de atención a la ciudadanía | S42: Gestión | T42: Solicitudes
C43: 02 | D43: 02 | E43: 02 | F43: 01 | G43: 02 | I43: B02 | K43: 110 | L43: =VLOOKUP(K43,'GACETA 3'!$E$9:$F$75,2,0) -> Acción Cívica | M43: =CONCATENATE(C43,D43,E43,F43,G43) -> 0202020102 | N43: =VLOOKUP(M43,GACETA!$A$1:$C$186,3,0) -> M | O43: =VLOOKUP(M43,GACETA!$A$1:$C$186,2,0) -> Apoyo Solidario | R43: Llevar acabo Sesiones de cabildo para abordar temas en benificio de la poblacion | S43: Gestión | T43: Asistencia
C44: 02 | D44: 02 | E44: 02 | F44: 01 | G44: 02 | I44: C05 | K44: 110 | L44: =VLOOKUP(K44,'GACETA 3'!$E$9:$F$75,2,0) -> Acción Cívica | M44: =CONCATENATE(C44,D44,E44,F44,G44) -> 0202020102 | N44: =VLOOKUP(M44,GACETA!$A$1:$C$186,3,0) -> M | O44: =VLOOKUP(M44,GACETA!$A$1:$C$186,2,0) -> Apoyo Solidario | R44: Realizar sesiones coadyuvando con las áreas administrativas municipales en encomineda establecida bajo comité | S44: Gestión | T44: Sesiones
A45: C06 | B45: REGIDURÍA VI | C45: 02 | D45: 02 | E45: 02 | F45: 01 | G45: 02 | I45: C06 | K45: 110 | L45: =VLOOKUP(K45,'GACETA 3'!$E$9:$F$75,2,0) -> Acción Cívica | M45: =CONCATENATE(C45,D45,E45,F45,G45) -> 0202020102 | N45: =VLOOKUP(M45,GACETA!$A$1:$C$186,3,0) -> M | O45: =VLOOKUP(M45,GACETA!$A$1:$C$186,2,0) -> Apoyo Solidario | P45: Desarrollo comunitario | Q45: Apoyo solidario | R45: Realizar acciones, obras y apoyos en comunidades por medio de atención a la ciudadanía | S45: Gestión | T45: Solicitudes
C46: 02 | D46: 02 | E46: 02 | F46: 01 | G46: 02 | I46: B02 | K46: 110 | L46: =VLOOKUP(K46,'GACETA 3'!$E$9:$F$75,2,0) -> Acción Cívica | M46: =CONCATENATE(C46,D46,E46,F46,G46) -> 0202020102 | N46: =VLOOKUP(M46,GACETA!$A$1:$C$186,3,0) -> M | O46: =VLOOKUP(M46,GACETA!$A$1:$C$186,2,0) -> Apoyo Solidario | R46: Llevar acabo Sesiones de cabildo para abordar temas en benificio de la poblacion | S46: Gestión | T46: Asistencia
C47: 02 | D47: 02 | E47: 02 | F47: 01 | G47: 02 | I47: C06 | K47: 110 | L47: =VLOOKUP(K47,'GACETA 3'!$E$9:$F$75,2,0) -> Acción Cívica | M47: =CONCATENATE(C47,D47,E47,F47,G47) -> 0202020102 | N47: =VLOOKUP(M47,GACETA!$A$1:$C$186,3,0) -> M | O47: =VLOOKUP(M47,GACETA!$A$1:$C$186,2,0) -> Apoyo Solidario | R47: Realizar sesiones coadyuvando con las áreas administrativas municipales en encomineda establecida bajo comité | S47: Gestión | T47: Sesiones
A48: C07 | B48: REGIDURÍA VII | C48: 02 | D48: 02 | E48: 02 | F48: 01 | G48: 02 | I48: C07 | K48: 110 | L48: =VLOOKUP(K48,'GACETA 3'!$E$9:$F$75,2,0) -> Acción Cívica | M48: =CONCATENATE(C48,D48,E48,F48,G48) -> 0202020102 | N48: =VLOOKUP(M48,GACETA!$A$1:$C$186,3,0) -> M | O48: =VLOOKUP(M48,GACETA!$A$1:$C$186,2,0) -> Apoyo Solidario | P48: Desarrollo comunitario | Q48: Apoyo solidario | R48: Realizar acciones, obras y apoyos en comunidades por medio de atención a la ciudadanía | S48: Gestión | T48: Solicitudes
C49: 02 | D49: 02 | E49: 02 | F49: 01 | G49: 02 | I49: B02 | K49: 110 | L49: =VLOOKUP(K49,'GACETA 3'!$E$9:$F$75,2,0) -> Acción Cívica | M49: =CONCATENATE(C49,D49,E49,F49,G49) -> 0202020102 | N49: =VLOOKUP(M49,GACETA!$A$1:$C$186,3,0) -> M | O49: =VLOOKUP(M49,GACETA!$A$1:$C$186,2,0) -> Apoyo Solidario | R49: Llevar acabo Sesiones de cabildo para abordar temas en benificio de la poblacion | S49: Gestión | T49: Asistencia
C50: 02 | D50: 02 | E50: 02 | F50: 01 | G50: 02 | I50: C07 | K50: 110 | L50: =VLOOKUP(K50,'GACETA 3'!$E$9:$F$75,2,0) -> Acción Cívica | M50: =CONCATENATE(C50,D50,E50,F50,G50) -> 0202020102 | N50: =VLOOKUP(M50,GACETA!$A$1:$C$186,3,0) -> M | O50: =VLOOKUP(M50,GACETA!$A$1:$C$186,2,0) -> Apoyo Solidario | R50: Realizar sesiones coadyuvando con las áreas administrativas municipales en encomineda establecida bajo comité | S50: Gestión | T50: Sesiones
A51: C08 | B51: REGIDURÍA VIII | C51: 02 | D51: 02 | E51: 02 | F51: 01 | G51: 02 | I51: C08 | K51: 110 | L51: =VLOOKUP(K51,'GACETA 3'!$E$9:$F$75,2,0) -> Acción Cívica | M51: =CONCATENATE(C51,D51,E51,F51,G51) -> 0202020102 | N51: =VLOOKUP(M51,GACETA!$A$1:$C$186,3,0) -> M | O51: =VLOOKUP(M51,GACETA!$A$1:$C$186,2,0) -> Apoyo Solidario | P51: Desarrollo comunitario | Q51: Apoyo solidario | R51: Realizar acciones, obras y apoyos en comunidades por medio de atención a la ciudadanía | S51: Gestión | T51: Solicitudes
C52: 02 | D52: 02 | E52: 02 | F52: 01 | G52: 02 | I52: B02 | K52: 110 | L52: =VLOOKUP(K52,'GACETA 3'!$E$9:$F$75,2,0) -> Acción Cívica | M52: =CONCATENATE(C52,D52,E52,F52,G52) -> 0202020102 | N52: =VLOOKUP(M52,GACETA!$A$1:$C$186,3,0) -> M | O52: =VLOOKUP(M52,GACETA!$A$1:$C$186,2,0) -> Apoyo Solidario | R52: Llevar acabo Sesiones de cabildo para abordar temas en benificio de la poblacion | S52: Gestión | T52: Asistencia
C53: 02 | D53: 02 | E53: 02 | F53: 01 | G53: 02 | I53: C08 | K53: 110 | L53: =VLOOKUP(K53,'GACETA 3'!$E$9:$F$75,2,0) -> Acción Cívica | M53: =CONCATENATE(C53,D53,E53,F53,G53) -> 0202020102 | N53: =VLOOKUP(M53,GACETA!$A$1:$C$186,3,0) -> M | O53: =VLOOKUP(M53,GACETA!$A$1:$C$186,2,0) -> Apoyo Solidario | R53: Realizar sesiones coadyuvando con las áreas administrativas municipales en encomineda establecida bajo comité | S53: Gestión | T53: Sesiones
A54: C09 | B54: REGIDURÍA IX | C54: 02 | D54: 02 | E54: 02 | F54: 01 | G54: 02 | I54: C09 | K54: 110 | L54: =VLOOKUP(K54,'GACETA 3'!$E$9:$F$75,2,0) -> Acción Cívica | M54: =CONCATENATE(C54,D54,E54,F54,G54) -> 0202020102 | N54: =VLOOKUP(M54,GACETA!$A$1:$C$186,3,0) -> M | O54: =VLOOKUP(M54,GACETA!$A$1:$C$186,2,0) -> Apoyo Solidario | P54: Desarrollo comunitario | Q54: Apoyo solidario | R54: Realizar acciones, obras y apoyos en comunidades por medio de atención a la ciudadanía | S54: Gestión | T54: Solicitudes
C55: 02 | D55: 02 | E55: 02 | F55: 01 | G55: 02 | I55: C09 | K55: 110 | L55: =VLOOKUP(K55,'GACETA 3'!$E$9:$F$75,2,0) -> Acción Cívica | M55: =CONCATENATE(C55,D55,E55,F55,G55) -> 0202020102 | N55: =VLOOKUP(M55,GACETA!$A$1:$C$186,3,0) -> M | O55: =VLOOKUP(M55,GACETA!$A$1:$C$186,2,0) -> Apoyo Solidario | R55: Llevar acabo Sesiones de cabildo para abordar temas en benificio de la poblacion | S55: Gestión | T55: Asistencia
C56: 02 | D56: 02 | E56: 02 | F56: 01 | G56: 02 | I56: C09 | K56: 110 | L56: =VLOOKUP(K56,'GACETA 3'!$E$9:$F$75,2,0) -> Acción Cívica | M56: =CONCATENATE(C56,D56,E56,F56,G56) -> 0202020102 | N56: =VLOOKUP(M56,GACETA!$A$1:$C$186,3,0) -> M | O56: =VLOOKUP(M56,GACETA!$A$1:$C$186,2,0) -> Apoyo Solidario | R56: Realizar sesiones coadyuvando con las áreas administrativas municipales en encomineda establecida bajo comité | S56: Gestión | T56: Sesiones
A57: C10 | B57: REGIDURÍA X | C57: 02 | D57: 02 | E57: 02 | F57: 01 | G57: 02 | I57: C10 | K57: 110 | L57: =VLOOKUP(K57,'GACETA 3'!$E$9:$F$75,2,0) -> Acción Cívica | M57: =CONCATENATE(C57,D57,E57,F57,G57) -> 0202020102 | N57: =VLOOKUP(M57,GACETA!$A$1:$C$186,3,0) -> M | O57: =VLOOKUP(M57,GACETA!$A$1:$C$186,2,0) -> Apoyo Solidario | P57: Desarrollo comunitario | Q57: Apoyo solidario | R57: Realizar acciones, obras y apoyos en comunidades por medio de atención a la ciudadanía | S57: Gestión | T57: Solicitudes
C58: 02 | D58: 02 | E58: 02 | F58: 01 | G58: 02 | I58: C09 | K58: 110 | L58: =VLOOKUP(K58,'GACETA 3'!$E$9:$F$75,2,0) -> Acción Cívica | M58: =CONCATENATE(C58,D58,E58,F58,G58) -> 0202020102 | N58: =VLOOKUP(M58,GACETA!$A$1:$C$186,3,0) -> M | O58: =VLOOKUP(M58,GACETA!$A$1:$C$186,2,0) -> Apoyo Solidario | R58: Llevar acabo Sesiones de cabildo para abordar temas en benificio de la poblacion | S58: Gestión | T58: Asistencia
C59: 02 | D59: 02 | E59: 02 | F59: 01 | G59: 02 | I59: C10 | K59: 110 | L59: =VLOOKUP(K59,'GACETA 3'!$E$9:$F$75,2,0) -> Acción Cívica | M59: =CONCATENATE(C59,D59,E59,F59,G59) -> 0202020102 | N59: =VLOOKUP(M59,GACETA!$A$1:$C$186,3,0) -> M | O59: =VLOOKUP(M59,GACETA!$A$1:$C$186,2,0) -> Apoyo Solidario | R59: Realizar sesiones coadyuvando con las áreas administrativas municipales en encomineda establecida bajo comité | S59: Gestión | T59: Sesiones
A60: C11 | B60: REGIDURÍA XI | C60: 02 | D60: 02 | E60: 02 | F60: 01 | G60: 02 | I60: C11 | K60: 110 | L60: =VLOOKUP(K60,'GACETA 3'!$E$9:$F$75,2,0) -> Acción Cívica | M60: =CONCATENATE(C60,D60,E60,F60,G60) -> 0202020102 | N60: =VLOOKUP(M60,GACETA!$A$1:$C$186,3,0) -> M | O60: =VLOOKUP(M60,GACETA!$A$1:$C$186,2,0) -> Apoyo Solidario | P60: Desarrollo comunitario | Q60: Apoyo solidario | R60: Realizar acciones, obras y apoyos en comunidades por medio de atención a la ciudadanía | S60: Gestión | T60: Solicitudes
C61: 02 | D61: 02 | E61: 02 | F61: 01 | G61: 02 | I61: C09 | K61: 110 | L61: =VLOOKUP(K61,'GACETA 3'!$E$9:$F$75,2,0) -> Acción Cívica | M61: =CONCATENATE(C61,D61,E61,F61,G61) -> 0202020102 | N61: =VLOOKUP(M61,GACETA!$A$1:$C$186,3,0) -> M | O61: =VLOOKUP(M61,GACETA!$A$1:$C$186,2,0) -> Apoyo Solidario | R61: Llevar acabo Sesiones de cabildo para abordar temas en benificio de la poblacion | S61: Gestión | T61: Asistencia
C62: 02 | D62: 02 | E62: 02 | F62: 01 | G62: 02 | I62: C11 | K62: 110 | L62: =VLOOKUP(K62,'GACETA 3'!$E$9:$F$75,2,0) -> Acción Cívica | M62: =CONCATENATE(C62,D62,E62,F62,G62) -> 0202020102 | N62: =VLOOKUP(M62,GACETA!$A$1:$C$186,3,0) -> M | O62: =VLOOKUP(M62,GACETA!$A$1:$C$186,2,0) -> Apoyo Solidario | R62: Realizar sesiones coadyuvando con las áreas administrativas municipales en encomineda establecida bajo comité | S62: Gestión | T62: Sesiones
A63: C12 | B63: REGIDURÍA XII | C63: 02 | D63: 02 | E63: 02 | F63: 01 | G63: 02 | I63: C12 | K63: 110 | L63: =VLOOKUP(K63,'GACETA 3'!$E$9:$F$75,2,0) -> Acción Cívica | M63: =CONCATENATE(C63,D63,E63,F63,G63) -> 0202020102 | N63: =VLOOKUP(M63,GACETA!$A$1:$C$186,3,0) -> M | O63: =VLOOKUP(M63,GACETA!$A$1:$C$186,2,0) -> Apoyo Solidario | P63: Desarrollo comunitario | Q63: Apoyo solidario | R63: Realizar acciones, obras y apoyos en comunidades por medio de atención a la ciudadanía | S63: Gestión | T63: Solicitudes
C64: 02 | D64: 02 | E64: 02 | F64: 01 | G64: 02 | I64: C09 | K64: 110 | L64: =VLOOKUP(K64,'GACETA 3'!$E$9:$F$75,2,0) -> Acción Cívica | M64: =CONCATENATE(C64,D64,E64,F64,G64) -> 0202020102 | N64: =VLOOKUP(M64,GACETA!$A$1:$C$186,3,0) -> M | O64: =VLOOKUP(M64,GACETA!$A$1:$C$186,2,0) -> Apoyo Solidario | R64: Llevar acabo Sesiones de cabildo para abordar temas en benificio de la poblacion | S64: Gestión | T64: Asistencia
C65: 02 | D65: 02 | E65: 02 | F65: 01 | G65: 02 | I65: C12 | K65: 110 | L65: =VLOOKUP(K65,'GACETA 3'!$E$9:$F$75,2,0) -> Acción Cívica | M65: =CONCATENATE(C65,D65,E65,F65,G65) -> 0202020102 | N65: =VLOOKUP(M65,GACETA!$A$1:$C$186,3,0) -> M | O65: =VLOOKUP(M65,GACETA!$A$1:$C$186,2,0) -> Apoyo Solidario | R65: Realizar sesiones coadyuvando con las áreas administrativas municipales en encomineda establecida bajo comité | S65: Gestión | T65: Sesiones
A66: L00 | B66: TESORERÍA MUNICIPAL | C66: 01 | D66: 05 | E66: 02 | F66: 02 | G66: 01 | I66: L00 | K66: 115 | L66: =VLOOKUP(K66,'GACETA 3'!$E$9:$F$75,2,0) -> Ingresos | M66: =CONCATENATE(C66,D66,E66,F66,G66) -> 0105020201 | N66: =VLOOKUP(M66,GACETA!$A$1:$C$186,3,0) -> E | O66: =VLOOKUP(M66,GACETA!$A$1:$C$186,2,0) -> Captación y recaudación de ingresos | P66: Fortalecimiento de los ingresos | Q66: Captación y recaudación de ingresos | R66: Difundir de forma masiva los apoyos, subsidios fiscales y exhortación al pago predial puntual | S66: Gestión | T66: Campaña
C67: 01 | D67: 05 | E67: 02 | F67: 02 | G67: 01 | I67: L00 | K67: 115 | L67: =VLOOKUP(K67,'GACETA 3'!$E$9:$F$75,2,0) -> Ingresos | M67: =CONCATENATE(C67,D67,E67,F67,G67) -> 0105020201 | N67: =VLOOKUP(M67,GACETA!$A$1:$C$186,3,0) -> E | O67: =VLOOKUP(M67,GACETA!$A$1:$C$186,2,0) -> Captación y recaudación de ingresos | R67: Actualizar el Padrón de cobro de impuesto predial | S67: Gestión | T67: Contribuyente
C68: 01 | D68: 05 | E68: 02 | F68: 02 | G68: 01 | I68: L00 | K68: 115 | L68: =VLOOKUP(K68,'GACETA 3'!$E$9:$F$75,2,0) -> Ingresos | M68: =CONCATENATE(C68,D68,E68,F68,G68) -> 0105020201 | N68: =VLOOKUP(M68,GACETA!$A$1:$C$186,3,0) -> E | O68: =VLOOKUP(M68,GACETA!$A$1:$C$186,2,0) -> Captación y recaudación de ingresos | R68: Actualizar y cobrar de Impuesto Predial por concepto de Diferencia de Construcción No Declaradas. | S68: Gestión | T68: Expediente
C69: 01 | D69: 05 | E69: 02 | F69: 02 | G69: 01 | I69: L00 | K69: 115 | L69: =VLOOKUP(K69,'GACETA 3'!$E$9:$F$75,2,0) -> Ingresos | M69: =CONCATENATE(C69,D69,E69,F69,G69) -> 0105020201 | N69: =VLOOKUP(M69,GACETA!$A$1:$C$186,3,0) -> E | O69: =VLOOKUP(M69,GACETA!$A$1:$C$186,2,0) -> Captación y recaudación de ingresos | R69: Generar la Emisión, Pago y Entrega de Certificaciones de No Adeudo de Impuesto Predial y Aportación de Mejoras | S69: Gestión | T69: Expediente
C70: 01 | D70: 05 | E70: 02 | F70: 02 | G70: 01 | I70: L00 | K70: 115 | L70: =VLOOKUP(K70,'GACETA 3'!$E$9:$F$75,2,0) -> Ingresos | M70: =CONCATENATE(C70,D70,E70,F70,G70) -> 0105020201 | N70: =VLOOKUP(M70,GACETA!$A$1:$C$186,3,0) -> E | O70: =VLOOKUP(M70,GACETA!$A$1:$C$186,2,0) -> Captación y recaudación de ingresos | R70: Generar Convenios de Pago | S70: Gestión | T70: Contribuyente
C71: 01 | D71: 05 | E71: 02 | F71: 02 | G71: 01 | I71: L00 | K71: 115 | L71: =VLOOKUP(K71,'GACETA 3'!$E$9:$F$75,2,0) -> Ingresos | M71: =CONCATENATE(C71,D71,E71,F71,G71) -> 0105020201 | N71: =VLOOKUP(M71,GACETA!$A$1:$C$186,3,0) -> E | O71: =VLOOKUP(M71,GACETA!$A$1:$C$186,2,0) -> Captación y recaudación de ingresos | R71: Verificar Notificaciones de oficios Divesas | S71: Gestión | T71: Contribuyente
C72: 01 | D72: 05 | E72: 02 | F72: 02 | G72: 01 | I72: L00 | K72: 115 | L72: =VLOOKUP(K72,'GACETA 3'!$E$9:$F$75,2,0) -> Ingresos | M72: =CONCATENATE(C72,D72,E72,F72,G72) -> 0105020201 | N72: =VLOOKUP(M72,GACETA!$A$1:$C$186,3,0) -> E | O72: =VLOOKUP(M72,GACETA!$A$1:$C$186,2,0) -> Captación y recaudación de ingresos | R72: Determinar los Créditos Fiscales para contribuyentes morosos, omisos y remisos (Contribuciones, Derechos y Aprovechamientos) | S72: Gestión | T72: Contribuyente
C73: 01 | D73: 05 | E73: 02 | F73: 02 | G73: 01 | I73: L00 | K73: 115 | L73: =VLOOKUP(K73,'GACETA 3'!$E$9:$F$75,2,0) -> Ingresos | M73: =CONCATENATE(C73,D73,E73,F73,G73) -> 0105020201 | N73: =VLOOKUP(M73,GACETA!$A$1:$C$186,3,0) -> E | O73: =VLOOKUP(M73,GACETA!$A$1:$C$186,2,0) -> Captación y recaudación de ingresos | R73: Recuperar los créditos fiscales | S73: Gestión | T73: Contribuyente
C74: 01 | D74: 05 | E74: 02 | F74: 02 | G74: 01 | I74: L00 | K74: 115 | L74: =VLOOKUP(K74,'GACETA 3'!$E$9:$F$75,2,0) -> Ingresos | M74: =CONCATENATE(C74,D74,E74,F74,G74) -> 0105020201 | N74: =VLOOKUP(M74,GACETA!$A$1:$C$186,3,0) -> E | O74: =VLOOKUP(M74,GACETA!$A$1:$C$186,2,0) -> Captación y recaudación de ingresos | R74: Emitir y entregar de cartas invitación para pagos pendientes (Predial) | S74: Gestión | T74: Contribuyente
C75: 01 | D75: 05 | E75: 02 | F75: 02 | G75: 01 | I75: L00 | K75: 115 | L75: =VLOOKUP(K75,'GACETA 3'!$E$9:$F$75,2,0) -> Ingresos | M75: =CONCATENATE(C75,D75,E75,F75,G75) -> 0105020201 | N75: =VLOOKUP(M75,GACETA!$A$1:$C$186,3,0) -> E | O75: =VLOOKUP(M75,GACETA!$A$1:$C$186,2,0) -> Captación y recaudación de ingresos | R75: Notificar para el Pago de contribuyentes morosos | S75: Gestión | T75: Visita
C76: 01 | D76: 05 | E76: 02 | F76: 02 | G76: 01 | I76: L00 | K76: 115 | L76: =VLOOKUP(K76,'GACETA 3'!$E$9:$F$75,2,0) -> Ingresos | M76: =CONCATENATE(C76,D76,E76,F76,G76) -> 0105020201 | N76: =VLOOKUP(M76,GACETA!$A$1:$C$186,3,0) -> E | O76: =VLOOKUP(M76,GACETA!$A$1:$C$186,2,0) -> Captación y recaudación de ingresos | R76: Visitar las cajas móviles en las comunidades para la recaudación del impuesto predial | S76: Gestión | T76: Contribuyente
C77: 01 | D77: 05 | E77: 02 | F77: 02 | G77: 01 | I77: L00 | K77: 115 | L77: =VLOOKUP(K77,'GACETA 3'!$E$9:$F$75,2,0) -> Ingresos | M77: =CONCATENATE(C77,D77,E77,F77,G77) -> 0105020201 | N77: =VLOOKUP(M77,GACETA!$A$1:$C$186,3,0) -> E | O77: =VLOOKUP(M77,GACETA!$A$1:$C$186,2,0) -> Captación y recaudación de ingresos | R77: Generar el Traslado de Dominio Autorizado | S77: Gestión | T77: Traslado de dominio
C78: 01 | D78: 05 | E78: 02 | F78: 02 | G78: 01 | I78: L00 | K78: 115 | L78: =VLOOKUP(K78,'GACETA 3'!$E$9:$F$75,2,0) -> Ingresos | M78: =CONCATENATE(C78,D78,E78,F78,G78) -> 0105020201 | N78: =VLOOKUP(M78,GACETA!$A$1:$C$186,3,0) -> E | O78: =VLOOKUP(M78,GACETA!$A$1:$C$186,2,0) -> Captación y recaudación de ingresos | R78: Emitir la Certificación de Traslado de Dominio | S78: Gestión | T78: Documento
C79: 01 | D79: 05 | E79: 02 | F79: 02 | G79: 09 | I79: L00 | K79: 115 | L79: =VLOOKUP(K79,'GACETA 3'!$E$9:$F$75,2,0) -> Ingresos | M79: =CONCATENATE(C79,D79,E79,F79,G79) -> 0105020209 | N79: =VLOOKUP(M79,GACETA!$A$1:$C$186,3,0) -> E | O79: =VLOOKUP(M79,GACETA!$A$1:$C$186,2,0) -> Registro y control de caja y tesorería | Q79: Registro y control de caja y tesorería | R79: Llevar el control y registro de cajas, mediante el reporte del total de operaciones, inspeccionando el buen manejo de éstas | S79: Gestión | T79: Operaciones
C80: 01 | D80: 05 | E80: 02 | F80: 03 | G80: 04 | I80: L00 | K80: 119 | L80: =VLOOKUP(K80,'GACETA 3'!$E$9:$F$75,2,0) -> Contabilidad | M80: =CONCATENATE(C80,D80,E80,F80,G80) -> 0105020304 | N80: =VLOOKUP(M80,GACETA!$A$1:$C$186,3,0) -> K | O80: =VLOOKUP(M80,GACETA!$A$1:$C$186,2,0) -> Asignación, registro, seguimiento y control de la inversión pública municipal | P80: Administración del programa de inversión pública | Q80: Asignación, registro, seguimiento y control de la inversión pública municipal | R80: Revisión de los Expedientes de Obras Publicas (estimaciones) | S80: Gestión | T80: Ministración
C81: 01 | D81: 05 | E81: 02 | F81: 03 | G81: 04 | I81: L00 | K81: 119 | L81: =VLOOKUP(K81,'GACETA 3'!$E$9:$F$75,2,0) -> Contabilidad | M81: =CONCATENATE(C81,D81,E81,F81,G81) -> 0105020304 | N81: =VLOOKUP(M81,GACETA!$A$1:$C$186,3,0) -> K | O81: =VLOOKUP(M81,GACETA!$A$1:$C$186,2,0) -> Asignación, registro, seguimiento y control de la inversión pública municipal | R81: Actualización del Sistema de Recursos Federales Transferidos | S81: Gestión | T81: Reporte
C82: 01 | D82: 05 | E82: 02 | F82: 03 | G82: 04 | I82: L00 | K82: 119 | L82: =VLOOKUP(K82,'GACETA 3'!$E$9:$F$75,2,0) -> Contabilidad | M82: =CONCATENATE(C82,D82,E82,F82,G82) -> 0105020304 | N82: =VLOOKUP(M82,GACETA!$A$1:$C$186,3,0) -> K | O82: =VLOOKUP(M82,GACETA!$A$1:$C$186,2,0) -> Asignación, registro, seguimiento y control de la inversión pública municipal | R82: Seguimiento a las Aportaciones Federales | S82: Gestión | T82: Gestión
C83: 01 | D83: 05 | E83: 02 | F83: 03 | G83: 04 | I83: L00 | K83: 119 | L83: =VLOOKUP(K83,'GACETA 3'!$E$9:$F$75,2,0) -> Contabilidad | M83: =CONCATENATE(C83,D83,E83,F83,G83) -> 0105020304 | N83: =VLOOKUP(M83,GACETA!$A$1:$C$186,3,0) -> K | O83: =VLOOKUP(M83,GACETA!$A$1:$C$186,2,0) -> Asignación, registro, seguimiento y control de la inversión pública municipal | R83: Actualización del Sistema de Avance Mensual (SIAVAMEN) | S83: Gestión | T83: Actualización
C84: 01 | D84: 05 | E84: 02 | F84: 05 | G84: 08 | I84: L00 | K84: 119 | L84: =VLOOKUP(K84,'GACETA 3'!$E$9:$F$75,2,0) -> Contabilidad | M84: =CONCATENATE(C84,D84,E84,F84,G84) -> 0105020508 | N84: =VLOOKUP(M84,GACETA!$A$1:$C$186,3,0) -> P | O84: =VLOOKUP(M84,GACETA!$A$1:$C$186,2,0) -> Planeación y evaluación para el desarrollo municipal | P84: Planeación y presupuesto basado en resultados | Q84: Planeación y evaluación para el desarrollo municipal | R84: Seguimiento a los resultados y ejecución de los recursos con los que dispone el municipio. | S84: Gestión | T84: Seguimiento
C85: 01 | D85: 05 | E85: 02 | F85: 05 | G85: 10 | I85: L00 | K85: 117 | L85: =VLOOKUP(K85,'GACETA 3'!$E$9:$F$75,2,0) -> Presupuesto | M85: =CONCATENATE(C85,D85,E85,F85,G85) -> 0105020510 | N85: =VLOOKUP(M85,GACETA!$A$1:$C$186,3,0) -> O | O85: =VLOOKUP(M85,GACETA!$A$1:$C$186,2,0) -> Integración, seguimiento y control presupuestal del ayuntamiento | Q85: Integración, seguimiento y control presupuestal del ayuntamiento | R85: Mejorar el control del presupuesto, mediante la emisión de reportes | S85: Gestión | T85: Reporte
C86: 01 | D86: 05 | E86: 02 | F86: 05 | G86: 10 | I86: L00 | K86: 117 | L86: =VLOOKUP(K86,'GACETA 3'!$E$9:$F$75,2,0) -> Presupuesto | M86: =CONCATENATE(C86,D86,E86,F86,G86) -> 0105020510 | N86: =VLOOKUP(M86,GACETA!$A$1:$C$186,3,0) -> O | O86: =VLOOKUP(M86,GACETA!$A$1:$C$186,2,0) -> Integración, seguimiento y control presupuestal del ayuntamiento | R86: Asesorar a las diversas áreas en materia presupuestal | S86: Gestión | T86: Asesoría
C87: 01 | D87: 05 | E87: 02 | F87: 05 | G87: 10 | I87: L00 | K87: 117 | L87: =VLOOKUP(K87,'GACETA 3'!$E$9:$F$75,2,0) -> Presupuesto | M87: =CONCATENATE(C87,D87,E87,F87,G87) -> 0105020510 | N87: =VLOOKUP(M87,GACETA!$A$1:$C$186,3,0) -> O | O87: =VLOOKUP(M87,GACETA!$A$1:$C$186,2,0) -> Integración, seguimiento y control presupuestal del ayuntamiento | R87: Integración del presupuesto de ingresos y egresos definitivo para el ejercicio fiscal 2024 | S87: Estratégico | T87: Paquete presupuestal
C88: 01 | D88: 05 | E88: 02 | F88: 05 | G88: 10 | I88: L00 | K88: 117 | L88: =VLOOKUP(K88,'GACETA 3'!$E$9:$F$75,2,0) -> Presupuesto | M88: =CONCATENATE(C88,D88,E88,F88,G88) -> 0105020510 | N88: =VLOOKUP(M88,GACETA!$A$1:$C$186,3,0) -> O | O88: =VLOOKUP(M88,GACETA!$A$1:$C$186,2,0) -> Integración, seguimiento y control presupuestal del ayuntamiento | R88: Integración del anteproyecto de presupuesto de ingresos y egresos para el ejercicio fiscal 2025 | S88: Estratégico | T88: Paquete presupuestal
C89: 01 | D89: 05 | E89: 02 | F89: 05 | G89: 11 | I89: L00 | K89: 116 | L89: =VLOOKUP(K89,'GACETA 3'!$E$9:$F$75,2,0) -> Egresos | M89: =CONCATENATE(C89,D89,E89,F89,G89) -> 0105020511 | N89: =VLOOKUP(M89,GACETA!$A$1:$C$186,3,0) -> O | O89: =VLOOKUP(M89,GACETA!$A$1:$C$186,2,0) -> Registro, control contable-presupuestal y cuenta de la hacienda pública municipal | Q89: Registro, control contable-presupuestal y cuenta de la hacienda pública municipal | R89: Reportes trimestrales enviados al OSFEM | S89: Estratégico | T89: Informe
C90: 01 | D90: 05 | E90: 02 | F90: 05 | G90: 11 | I90: L00 | K90: 116 | L90: =VLOOKUP(K90,'GACETA 3'!$E$9:$F$75,2,0) -> Egresos | M90: =CONCATENATE(C90,D90,E90,F90,G90) -> 0105020511 | N90: =VLOOKUP(M90,GACETA!$A$1:$C$186,3,0) -> O | O90: =VLOOKUP(M90,GACETA!$A$1:$C$186,2,0) -> Registro, control contable-presupuestal y cuenta de la hacienda pública municipal | R90: Envió de la cuenta pública OSFEM | S90: Estratégico | T90: Cuenta pública
C91: 01 | D91: 05 | E91: 02 | F91: 05 | G91: 11 | I91: L00 | K91: 116 | L91: =VLOOKUP(K91,'GACETA 3'!$E$9:$F$75,2,0) -> Egresos | M91: =CONCATENATE(C91,D91,E91,F91,G91) -> 0105020511 | N91: =VLOOKUP(M91,GACETA!$A$1:$C$186,3,0) -> O | O91: =VLOOKUP(M91,GACETA!$A$1:$C$186,2,0) -> Registro, control contable-presupuestal y cuenta de la hacienda pública municipal | R91: Reportes y reactivos enviados al SEVAC | S91: Gestión | T91: Reporte
C92: 01 | D92: 05 | E92: 02 | F92: 05 | G92: 11 | I92: L00 | K92: 116 | L92: =VLOOKUP(K92,'GACETA 3'!$E$9:$F$75,2,0) -> Egresos | M92: =CONCATENATE(C92,D92,E92,F92,G92) -> 0105020511 | N92: =VLOOKUP(M92,GACETA!$A$1:$C$186,3,0) -> O | O92: =VLOOKUP(M92,GACETA!$A$1:$C$186,2,0) -> Registro, control contable-presupuestal y cuenta de la hacienda pública municipal | R92: Reportes CONAC | S92: Gestión | T92: Reporte
C93: 01 | D93: 05 | E93: 02 | F93: 05 | G93: 11 | I93: L00 | K93: 116 | L93: =VLOOKUP(K93,'GACETA 3'!$E$9:$F$75,2,0) -> Egresos | M93: =CONCATENATE(C93,D93,E93,F93,G93) -> 0105020511 | N93: =VLOOKUP(M93,GACETA!$A$1:$C$186,3,0) -> O | O93: =VLOOKUP(M93,GACETA!$A$1:$C$186,2,0) -> Registro, control contable-presupuestal y cuenta de la hacienda pública municipal | R93: Dispersión nomina | S93: Gestión | T93: Dispersión
C94: 04 | D94: 01 | E94: 01 | F94: 01 | G94: 04 | I94: L00 | K94: 116 | L94: =VLOOKUP(K94,'GACETA 3'!$E$9:$F$75,2,0) -> Egresos | M94: =CONCATENATE(C94,D94,E94,F94,G94) -> 0401010104 | N94: =VLOOKUP(M94,GACETA!$A$1:$C$186,3,0) -> D | O94: =VLOOKUP(M94,GACETA!$A$1:$C$186,2,0) -> Amortización de la deuda (capital) | P94: Deuda pública | Q94: Amortización de la deuda (Capital) | R94: Pago a capital de financiamiento | S94: Gestión | T94: Pago
C95: 04 | D95: 01 | E95: 01 | F95: 01 | G95: 05 | I95: L00 | K95: 116 | L95: =VLOOKUP(K95,'GACETA 3'!$E$9:$F$75,2,0) -> Egresos | M95: =CONCATENATE(C95,D95,E95,F95,G95) -> 0401010105 | N95: =VLOOKUP(M95,GACETA!$A$1:$C$186,3,0) -> D | O95: =VLOOKUP(M95,GACETA!$A$1:$C$186,2,0) -> Costo financiero de la deuda (intereses) | Q95: Costo financiero de la deuda (Intereses) | R95: Pago a Intereses de Financiamiento | S95: Gestión | T95: Pago
C96: 04 | D96: 02 | E96: 01 | F96: 01 | G96: 03 | I96: L00 | K96: 115 | L96: =VLOOKUP(K96,'GACETA 3'!$E$9:$F$75,2,0) -> Ingresos | M96: =CONCATENATE(C96,D96,E96,F96,G96) -> 0402010103 | N96: =VLOOKUP(M96,GACETA!$A$1:$C$186,3,0) -> C | O96: =VLOOKUP(M96,GACETA!$A$1:$C$186,2,0) -> Convenios de coordinación | P96: Transferencias | Q96: Convenios de Coordinación | R96: Seguimiento a convenio en términos de la Ley de Coordinación Fiscal | S96: Gestión | T96: Seguimiento a convenio
C97: 04 | D97: 02 | E97: 01 | F97: 01 | G97: 04 | I97: L00 | K97: 116 | L97: =VLOOKUP(K97,'GACETA 3'!$E$9:$F$75,2,0) -> Egresos | M97: =CONCATENATE(C97,D97,E97,F97,G97) -> 0402010104 | N97: =VLOOKUP(M97,GACETA!$A$1:$C$186,3,0) -> O | O97: =VLOOKUP(M97,GACETA!$A$1:$C$186,2,0) -> Transferencias del ayuntamiento a organismos municipales | Q97: Transferencias del ayuntamiento a organismos municipales | R97: Transferencia a Organismos Descentralizados | S97: Gestión | T97: Transferencia
C98: 04 | D98: 04 | E98: 01 | F98: 01 | G98: 01 | I98: L00 | K98: 116 | L98: =VLOOKUP(K98,'GACETA 3'!$E$9:$F$75,2,0) -> Egresos | M98: =CONCATENATE(C98,D98,E98,F98,G98) -> 0404010101 | N98: =VLOOKUP(M98,GACETA!$A$1:$C$186,3,0) -> #N/A | O98: =VLOOKUP(M98,GACETA!$A$1:$C$186,2,0) -> #N/A | P98: Previsiones para el pago de adeudos de ejercicios fiscales anteriores | Q98: Pasivos derivados de erogaciones devengadas y pendientes de ejercicios anteriores | R98: Pago de las ADEFAS del ejercicio | S98: Gestión | T98: Pago
C99: 01 | D99: 03 | E99: 05 | F99: 01 | G99: 04 | I99: L00 | K99: 155 | L99: =VLOOKUP(K99,'GACETA 3'!$E$9:$F$75,2,0) -> Área Jurídica | M99: =CONCATENATE(C99,D99,E99,F99,G99) -> 0103050104 | N99: =VLOOKUP(M99,GACETA!$A$1:$C$186,3,0) -> L | O99: =VLOOKUP(M99,GACETA!$A$1:$C$186,2,0) -> Asesoría jurídica al ayuntamiento | P99: Asistencia Jurídica al Ejecutivo | Q99: Asesoría Jurídica al Ayuntamiento | R99: Dar cumplimiento a lo ordenado en las sentencias emitidas por los tribunales | S99: Gestión | T99: Pago
C100: 01 | D100: 03 | E100: 05 | F100: 01 | G100: 04 | I100: L00 | K100: 155 | L100: =VLOOKUP(K100,'GACETA 3'!$E$9:$F$75,2,0) -> Área Jurídica | M100: =CONCATENATE(C100,D100,E100,F100,G100) -> 0103050104 | N100: =VLOOKUP(M100,GACETA!$A$1:$C$186,3,0) -> L | O100: =VLOOKUP(M100,GACETA!$A$1:$C$186,2,0) -> Asesoría jurídica al ayuntamiento | R100: Contestación de demandas | S100: Gestión | T100: Demanda
...

Sheet Hoja2
A2: D00 | B2: SECRETARÍA DEL AYUNTAMIENTO | C2: 155 | D2: Área Jurídica | E2: 0103090201 | F2: =VLOOKUP(E2,GACETA!$A$1:$C$186,3,0) -> M | G2: Revisión y emisión de la reglamentación municipal | I2: Reglamentos y disposiciones de observancia general en el municipio publicadas
A3: D00 | B3: SECRETARÍA DEL AYUNTAMIENTO | C3: 155 | D3: Área Jurídica | E3: 0103090201 | F3: =VLOOKUP(E3,GACETA!$A$1:$C$186,3,0) -> M | G3: Revisión y emisión de la reglamentación municipal | I3: Capacitaciones en materia reglamentaria otorgadas
A4: D00 | B4: SECRETARÍA DEL AYUNTAMIENTO | C4: 155 | D4: Área Jurídica | E4: 0103090201 | F4: =VLOOKUP(E4,GACETA!$A$1:$C$186,3,0) -> M | G4: Revisión y emisión de la reglamentación municipal | I4: Revisión de propuestas viables de modificación a Leyes, decretos y reglamentos municipales
A5: D00 | B5: SECRETARÍA DEL AYUNTAMIENTO | C5: 155 | D5: Área Jurídica | E5: 0103090201 | F5: =VLOOKUP(E5,GACETA!$A$1:$C$186,3,0) -> M | G5: Revisión y emisión de la reglamentación municipal | I5: Realización de sesiones de cabildo
A6: D00 | B6: SECRETARÍA DEL AYUNTAMIENTO | C6: 114 | D6: Control Patrimonial | E6: 0105020606 | F6: =VLOOKUP(E6,GACETA!$A$1:$C$186,3,0) -> M | G6: Control del patrimonio y normatividad | H6: =CONCATENATE(A6," ",C6," ",E6," ",F6) -> D00 114 0105020606 M | I6: Realizar los levantamientos fisicos de los bienes muebles e inmuebles.
A7: D00 | B7: SECRETARÍA DEL AYUNTAMIENTO | C7: 114 | D7: Control Patrimonial | E7: 0105020606 | F7: =VLOOKUP(E7,GACETA!$A$1:$C$186,3,0) -> M | G7: Control del patrimonio y normatividad | H7: =CONCATENATE(A7," ",C7," ",E7," ",F7) -> D00 114 0105020606 M | I7: Actualizar el inventario mediante revisiones fisicas por areas de trabajo de la Administracion Publica Municipal.
A8: D00 | B8: SECRETARÍA DEL AYUNTAMIENTO | C8: 114 | D8: Control Patrimonial | E8: 0105020606 | F8: =VLOOKUP(E8,GACETA!$A$1:$C$186,3,0) -> M | G8: Control del patrimonio y normatividad | H8: =CONCATENATE(A8," ",C8," ",E8," ",F8) -> D00 114 0105020606 M | I8: Actualización de registros de bienes inmuebles propiedad municipal
A9: D00 | B9: SECRETARÍA DEL AYUNTAMIENTO | C9: 108 | D9: Juzgados Cívicos | E9: 0103090301 | F9: =VLOOKUP(E9,GACETA!$A$1:$C$186,3,0) -> L | G9: Mediación, conciliación y función calificadora municipal | H9: =CONCATENATE(A9," ",C9," ",E9," ",F9) -> D00 108 0103090301 L | I9: Garantizar la paz social, convivencia familiar y vecinal a través de medios alternativos de solucion de controversias.
A10: D00 | B10: SECRETARÍA DEL AYUNTAMIENTO | C10: 108 | D10: Juzgados Cívicos | E10: 0103090301 | F10: =VLOOKUP(E10,GACETA!$A$1:$C$186,3,0) -> L | G10: Mediación, conciliación y función calificadora municipal | H10: =CONCATENATE(A10," ",C10," ",E10," ",F10) -> D00 108 0103090301 L | I10: Citar a las partes en conflicto con la finalidad de dirimir sus diferencias a través del dialogo y medios alternativos de solución
A11: D00 | B11: SECRETARÍA DEL AYUNTAMIENTO | C11: 108 | D11: Juzgados Cívicos | E11: 0103090301 | F11: =VLOOKUP(E11,GACETA!$A$1:$C$186,3,0) -> L | G11: Mediación, conciliación y función calificadora municipal | H11: =CONCATENATE(A11," ",C11," ",E11," ",F11) -> D00 108 0103090301 L | I11: Dar cumplimiento a los ordenamientos legales a través de la aplicación de sanciones por infracciones
A12: D00 | B12: SECRETARÍA DEL AYUNTAMIENTO | C12: 108 | D12: Juzgados Cívicos | E12: 0103090301 | F12: =VLOOKUP(E12,GACETA!$A$1:$C$186,3,0) -> L | G12: Mediación, conciliación y función calificadora municipal | H12: =CONCATENATE(A12," ",C12," ",E12," ",F12) -> D00 108 0103090301 L | I12: Capacitaciones en tematicas relacionadas a la Justicia Civica
A13: D00 | B13: SECRETARÍA DEL AYUNTAMIENTO | C13: 108 | D13: Juzgados Cívicos | E13: 0103090301 | F13: =VLOOKUP(E13,GACETA!$A$1:$C$186,3,0) -> L | G13: Mediación, conciliación y función calificadora municipal | H13: =CONCATENATE(A13," ",C13," ",E13," ",F13) -> D00 108 0103090301 L | I13: Difusión de la cultura civica y cultura de la legalidad en medios de comunicación
A14: D00 | B14: SECRETARÍA DEL AYUNTAMIENTO | C14: 108 | D14: Juzgados Cívicos | E14: 0103090301 | F14: =VLOOKUP(E14,GACETA!$A$1:$C$186,3,0) -> L | G14: Mediación, conciliación y función calificadora municipal | H14: =CONCATENATE(A14," ",C14," ",E14," ",F14) -> D00 108 0103090301 L | I14: Informes de Resultados de las Acciones del Juzgado Cívico
A15: D00 | B15: SECRETARÍA DEL AYUNTAMIENTO | C15: 108 | D15: Juzgados Cívicos | E15: 0103090301 | F15: =VLOOKUP(E15,GACETA!$A$1:$C$186,3,0) -> L | G15: Mediación, conciliación y función calificadora municipal | H15: =CONCATENATE(A15," ",C15," ",E15," ",F15) -> D00 108 0103090301 L | I15: Jornadas de Trabajo en favor de la comunidad
A16: D00 | B16: SECRETARÍA DEL AYUNTAMIENTO | C16: 108 | D16: Juzgados Cívicos | E16: 0103090301 | F16: =VLOOKUP(E16,GACETA!$A$1:$C$186,3,0) -> L | G16: Mediación, conciliación y función calificadora municipal | H16: =CONCATENATE(A16," ",C16," ",E16," ",F16) -> D00 108 0103090301 L | I16: Proporcionar asesorias psicologicas y preventivas escolares, enfocado a pdres y adolecentes
A17: D00 | B17: SECRETARÍA DEL AYUNTAMIENTO | C17: 108 | D17: Juzgados Cívicos | E17: 0103090301 | F17: =VLOOKUP(E17,GACETA!$A$1:$C$186,3,0) -> L | G17: Mediación, conciliación y función calificadora municipal | H17: =CONCATENATE(A17," ",C17," ",E17," ",F17) -> D00 108 0103090301 L | I17: Realizar talleres para jovenes menores infractores para su readapatcion
... A89: L00 | B89: TESORERÍA | C89: 116 | D89: Egresos | E89: 0402010104 | F89: =VLOOKUP(E89,GACETA!$A$1:$C$186,3,0) -> O | G89: Transferencias del ayuntamiento a organismos municipales | H89: =CONCATENATE(A89," ",C89," ",E89," ",F89) -> L00 116 0402010104 O | I89: Transferencia a Organismos Descentralizados
A90: L00 | B90: TESORERÍA | C90: 116 | D90: Egresos | E90: 0404010101 | F90: H | G90: Pasivos derivados de erogaciones devengadas y pendientes de ejercicios anteriores | H90: =CONCATENATE(A90," ",C90," ",E90," ",F90) -> L00 116 0404010101 H | I90: Pago de las ADEFAS del ejercicio
A91: L00 | B91: TESORERÍA | C91: 155 | D91: Área Jurídica | E91: 0103050104 | F91: =VLOOKUP(E91,GACETA!$A$1:$C$186,3,0) -> L | G91: Asesoría jurídica al ayuntamiento | H91: =CONCATENATE(A91," ",C91," ",E91," ",F91) -> L00 155 0103050104 L | I91: Dar cumplimiento a lo ordenado en las sentencias emitidas por los tribunales
A92: L00 | B92: TESORERÍA | C92: 155 | D92: Área Jurídica | E92: 0103050104 | F92: =VLOOKUP(E92,GACETA!$A$1:$C$186,3,0) -> L | G92: Asesoría jurídica al ayuntamiento | H92: =CONCATENATE(A92," ",C92," ",E92," ",F92) -> L00 155 0103050104 L | I92: Contestación de demandas
A93: L00 | B93: TESORERÍA | C93: 155 | D93: Área Jurídica | E93: 0103050104 | F93: =VLOOKUP(E93,GACETA!$A$1:$C$186,3,0) -> L | G93: Asesoría jurídica al ayuntamiento | H93: =CONCATENATE(A93," ",C93," ",E93," ",F93) -> L00 155 0103050104 L | I93: Desahogos de requerimientos
A94: L00 | B94: TESORERÍA | C94: 155 | D94: Área Jurídica | E94: 0103050104 | F94: =VLOOKUP(E94,GACETA!$A$1:$C$186,3,0) -> L | G94: Asesoría jurídica al ayuntamiento | H94: =CONCATENATE(A94," ",C94," ",E94," ",F94) -> L00 155 0103050104 L | I94: Informes previos y justificados
A95: L00 | B95: TESORERÍA | C95: 155 | D95: Área Jurídica | E95: 0103050104 | F95: =VLOOKUP(E95,GACETA!$A$1:$C$186,3,0) -> L | G95: Asesoría jurídica al ayuntamiento | H95: =CONCATENATE(A95," ",C95," ",E95," ",F95) -> L00 155 0103050104 L | I95: Interposición de demandas de amparo
A96: L00 | B96: TESORERÍA | C96: 155 | D96: Área Jurídica | E96: 0103050104 | F96: =VLOOKUP(E96,GACETA!$A$1:$C$186,3,0) -> L | G96: Asesoría jurídica al ayuntamiento | H96: =CONCATENATE(A96," ",C96," ",E96," ",F96) -> L00 155 0103050104 L | I96: Interposición de recursos de revisión y de revocación
A97: L00 | B97: TESORERÍA | C97: 155 | D97: Área Jurídica | E97: 0103050104 | F97: =VLOOKUP(E97,GACETA!$A$1:$C$186,3,0) -> L | G97: Asesoría jurídica al ayuntamiento | H97: =CONCATENATE(A97," ",C97," ",E97," ",F97) -> L00 155 0103050104 L | I97: Oficios de contestación a diversas unidades administrativas
A98: L00 | B98: TESORERÍA | C98: 118 | D98: Catastro Municipal | E98: 0108010201 | F98: =VLOOKUP(E98,GACETA!$A$1:$C$186,3,0) -> E | G98: Servicios e información catastral estatal y municipal | H98: =CONCATENATE(A98," ",C98," ",E98," ",F98) -> L00 118 0108010201 E | I98: Realizar la recepción de solicitudes de trámite catastral
A99: L00 | B99: TESORERÍA | C99: 118 | D99: Catastro Municipal | E99: 0108010201 | F99: =VLOOKUP(E99,GACETA!$A$1:$C$186,3,0) -> E | G99: Servicios e información catastral estatal y municipal | H99: =CONCATENATE(A99," ",C99," ",E99," ",F99) -> L00 118 0108010201 E | I99: Realizar diligencias de inspección y medición física de los predios
A100: L00 | B100: TESORERÍA | C100: 118 | D100: Catastro Municipal | E100: 0108010201 | F100: =VLOOKUP(E100,GACETA!$A$1:$C$186,3,0) -> E | G100: Servicios e información catastral estatal y municipal | H100: =CONCATENATE(A100," ",C100," ",E100," ",F100) -> L00 118 0108010201 E | I100: Verificar los linderos de inmuebles realizados
A101: L00 | B101: TESORERÍA | C101: 118 | D101: Catastro Municipal | E101: 0108010201 | F101: =VLOOKUP(E101,GACETA!$A$1:$C$186,3,0) -> E | G101: Servicios e información catastral estatal y municipal | H101: =CONCATENATE(A101," ",C101," ",E101," ",F101) -> L00 118 0108010201 E | I101: verificar la Certificación de clave y valor catastral
A102: L00 | B102: TESORERÍA | C102: 118 | D102: Catastro Municipal | E102: 0108010201 | F102: =VLOOKUP(E102,GACETA!$A$1:$C$186,3,0) -> E | G102: Servicios e información catastral estatal y municipal | H102: =CONCATENATE(A102," ",C102," ",E102," ",F102) -> L00 118 0108010201 E | I102: Certificación de plano manzanero
... A118: K00 | B118: ÓRGANO INTERNO DE CONTROL MUNICIPAL | C118: 139 | D118: Control Social | E118: 0103040102 | F118: =VLOOKUP(E118,GACETA!$A$1:$C$186,3,0) -> P | G118: Participación social en la formulación, seguimiento, control y evaluación | H118: =CONCATENATE(A118," ",C118," ",E118," ",F118) -> K00 139 0103040102 P | I118: Capacitación a integrantes COCICOVIS
A119: K00 | B119: ÓRGANO INTERNO DE CONTROL MUNICIPAL | C119: 136 | D119: Auditoría Administrativa | E119: 0103040201 | F119: O | G119: Prevención, detección, disuasión, sanción y combate a la corrupción | H119: =CONCATENATE(A119," ",C119," ",E119," ",F119) -> K00 136 0103040201 O | I119: Capacitación a servidores públicos en materia de combate a la corrupción.
A120: K00 | B120: ÓRGANO INTERNO DE CONTROL MUNICIPAL | C120: 136 | D120: Auditoría Administrativa | E120: 0103040201 | F120: O | G120: Prevención, detección, disuasión, sanción y combate a la corrupción | H120: =CONCATENATE(A120," ",C120," ",E120," ",F120) -> K00 136 0103040201 O | I120: Campaña de difusión en Materia de Anticorrupción.
A121: K00 | B121: ÓRGANO INTERNO DE CONTROL MUNICIPAL | C121: 136 | D121: Auditoría Administrativa | E121: 0103040201 | F121: O | G121: Prevención, detección, disuasión, sanción y combate a la corrupción | H121: =CONCATENATE(A121," ",C121," ",E121," ",F121) -> K00 136 0103040201 O | I121: Sesiones del Comité Coordinador del Sistema Anticorrupcion Municipal
A122: K00 | B122: ÓRGANO INTERNO DE CONTROL MUNICIPAL | C122: 136 | D122: Auditoría Administrativa | E122: 0103040201 | F122: O | G122: Prevención, detección, disuasión, sanción y combate a la corrupción | H122: =CONCATENATE(A122," ",C122," ",E122," ",F122) -> K00 136 0103040201 O | I122: Atención de denuncias y/o quejas vía telefónica en el Programa Municipal Anticorrupción
A123: K00 | B123: ÓRGANO INTERNO DE CONTROL MUNICIPAL | C123: 138 | D123: Responsabilidad y Situación Patrimonial | E123: 0103040202 | F123: O | G123: Responsabilidades administrativas | H123: =CONCATENATE(A123," ",C123," ",E123," ",F123) -> K00 138 0103040202 O | I123: Elaboración de informes de expedientes en proceso de substanciación
A124: K00 | B124: ÓRGANO INTERNO DE CONTROL MUNICIPAL | C124: 138 | D124: Responsabilidad y Situación Patrimonial | E124: 0103040202 | F124: O | G124: Responsabilidades administrativas | H124: =CONCATENATE(A124," ",C124," ",E124," ",F124) -> K00 138 0103040202 O | I124: Elaboración de informes de expedientes en proceso de resolución
A125: K00 | B125: ÓRGANO INTERNO DE CONTROL MUNICIPAL | C125: 138 | D125: Responsabilidad y Situación Patrimonial | E125: 0103040203 | F125: =VLOOKUP(E125,GACETA!$A$1:$C$186,3,0) -> O | G125: Declaración de situación patrimonial, de interés y constancia de la declaración fiscal de los servidores públicos | H125: =CONCATENATE(A125," ",C125," ",E125," ",F125) -> K00 138 0103040203 O | I125: Vigilar y consultar el padrón de sujetos obligados.
A126: K00 | B126: ÓRGANO INTERNO DE CONTROL MUNICIPAL | C126: 138 | D126: Responsabilidad y Situación Patrimonial | E126: 0103040203 | F126: =VLOOKUP(E126,GACETA!$A$1:$C$186,3,0) -> O | G126: Declaración de situación patrimonial, de interés y constancia de la declaración fiscal de los servidores públicos | H126: =CONCATENATE(A126," ",C126," ",E126," ",F126) -> K00 138 0103040203 O | I126: Vigilar y consultar los movimientos de altas y bajas del sistema Backoffice Decl@raNET
A127: K00 | B127: ÓRGANO INTERNO DE CONTROL MUNICIPAL | C127: 138 | D127: Responsabilidad y Situación Patrimonial | E127: 0103040203 | F127: =VLOOKUP(E127,GACETA!$A$1:$C$186,3,0) -> O | G127: Declaración de situación patrimonial, de interés y constancia de la declaración fiscal de los servidores públicos | H127: =CONCATENATE(A127," ",C127," ",E127," ",F127) -> K00 138 0103040203 O | I127: Seguimiento de la declaración patrimonial y conflicto de intereses por parte de servidores públicos.
A128: K00 | B128: ÓRGANO INTERNO DE CONTROL MUNICIPAL | C128: 138 | D128: Responsabilidad y Situación Patrimonial | E128: 0103040203 | F128: =VLOOKUP(E128,GACETA!$A$1:$C$186,3,0) -> O | G128: Declaración de situación patrimonial, de interés y constancia de la declaración fiscal de los servidores públicos | H128: =CONCATENATE(A128," ",C128," ",E128," ",F128) -> K00 138 0103040203 O | I128: Campañas de difusión respecto del cumplimiento de obligaciones de los servidores públicos.
A129: K00 | B129: ÓRGANO INTERNO DE CONTROL MUNICIPAL | C129: 138 | D129: Responsabilidad y Situación Patrimonial | E129: 0103040205 | F129: =VLOOKUP(E129,GACETA!$A$1:$C$186,3,0) -> O | G129: Investigación de faltas administrativas | H129: =CONCATENATE(A129," ",C129," ",E129," ",F129) -> K00 138 0103040205 O | I129: Atención de denuncias por posibles faltas administrativas, actos y hechos de corrupción.
A130: K00 | B130: ÓRGANO INTERNO DE CONTROL MUNICIPAL | C130: 138 | D130: Responsabilidad y Situación Patrimonial | E130: 0103040205 | F130: =VLOOKUP(E130,GACETA!$A$1:$C$186,3,0) -> O | G130: Investigación de faltas administrativas | H130: =CONCATENATE(A130," ",C130," ",E130," ",F130) -> K00 138 0103040205 O | I130: Inicio de investigación por posibles faltas administrativas, actos y hechos de corrupción.
A131: K00 | B131: ÓRGANO INTERNO DE CONTROL MUNICIPAL | C131: 138 | D131: Responsabilidad y Situación Patrimonial | E131: 0103040205 | F131: =VLOOKUP(E131,GACETA!$A$1:$C$186,3,0) -> O | G131: Investigación de faltas administrativas | H131: =CONCATENATE(A131," ",C131," ",E131," ",F131) -> K00 138 0103040205 O | I131: Emisión de informe de Presunta Responsabilidad Administrativa (IPRA)
A132: E00 | B132: ADMINISTRACIÓN | C132: 120 | D132: Administración y Desarrollo de Personal | E132: 0105020105 | F132: =VLOOKUP(E132,GACETA!$A$1:$C$186,3,0) -> E | G132: Desarrollo e impulso de la profesionalización, la investigación, estadísticas | H132: =CONCATENATE(A132," ",C132," ",E132," ",F132) -> E00 120 0105020105 E | I132: Gestión con instituciones especializadas en materia hacendaria para la impartición de cursos.
A133: E00 | B133: ADMINISTRACIÓN | C133: 120 | D133: Administración y Desarrollo de Personal | E133: 0105020105 | F133: =VLOOKUP(E133,GACETA!$A$1:$C$186,3,0) -> E | G133: Desarrollo e impulso de la profesionalización, la investigación, estadísticas | H133: =CONCATENATE(A133," ",C133," ",E133," ",F133) -> E00 120 0105020105 E | I133: Capacitar a servidores públicos de acuerdo al perfil solicitado
A134: E00 | B134: ADMINISTRACIÓN | C134: 120 | D134: Administración y Desarrollo de Personal | E134: 0105020601 | F134: =VLOOKUP(E134,GACETA!$A$1:$C$186,3,0) -> P | G134: Administración de personal | H134: =CONCATENATE(A134," ",C134," ",E134," ",F134) -> E00 120 0105020601 P | I134: Llevar a cabo el reclutamiento, selección, inducción y promoción del personal, así como la evaluación del desempeño.
A135: E00 | B135: ADMINISTRACIÓN | C135: 120 | D135: Administración y Desarrollo de Personal | E135: 0105020601 | F135: =VLOOKUP(E135,GACETA!$A$1:$C$186,3,0) -> P | G135: Administración de personal | H135: =CONCATENATE(A135," ",C135," ",E135," ",F135) -> E00 120 0105020601 P | I135: Armar expedientes de acuerdo a perfil definido sobre sistema de evaluación de personal
A136: E00 | B136: ADMINISTRACIÓN | C136: 120 | D136: Administración y Desarrollo de Personal | E136: 0105020602 | F136: =VLOOKUP(E136,GACETA!$A$1:$C$186,3,0) -> M | G136: Capacitación y profesionalización para el desarrollo del personal | H136: =CONCATENATE(A136," ",C136," ",E136," ",F136) -> E00 120 0105020602 M | I136: Capacitar a los servidores públicos para que puedan realizar sus funciones correspondientes de una manera eficiente y eficaz.
... A146: I01 | B146: Dirección de Desarrollo Social | C146: 112 | D146: Participación Ciudadana | E146: 0202020101 | F146: =VLOOKUP(E146,GACETA!$A$1:$C$186,3,0) -> S | G146: Promoción a la participación comunitaria | H146: =CONCATENATE(A146," ",C146," ",E146," ",F146) -> I01 112 0202020101 S | I146: Realizar consultas de Salud Bucal en los Centros de Desarrollo Comunitario para mejorar el bienestar social
B147: #N/A | D147: #N/A | F147: =VLOOKUP(E147,GACETA!$A$1:$C$186,3,0) -> #N/A | G147: #N/A | H147: =CONCATENATE(A147," ",C147," ",E147," ",F147) -> #N/A | I147: Actividades de las UTC de mejoramiento urbano y social
A148: I01 | B148: Dirección de Desarrollo Social | C148: 112 | D148: Participación Ciudadana | E148: 0202020101 | F148: =VLOOKUP(E148,GACETA!$A$1:$C$186,3,0) -> S | G148: Promoción a la participación comunitaria | H148: =CONCATENATE(A148," ",C148," ",E148," ",F148) -> I01 112 0202020101 S | I148: Realizar reuniones vecinales a cargo de las Unidades Territoriales Comunitarias para atender las demandas ciudadanas en materia de bienestar social
A149: I01 | B149: Dirección de Desarrollo Social | C149: 112 | D149: Participación Ciudadana | E149: 0202020102 | F149: =VLOOKUP(E149,GACETA!$A$1:$C$186,3,0) -> M | G149: Apoyo Solidario | H149: =CONCATENATE(A149," ",C149," ",E149," ",F149) -> I01 112 0202020102 M | I149: Entregar Tarjetas de Movilidad a estudiantes del municipio que se encuentran en condiciones de rezago social
A150: I01 | B150: Dirección de Desarrollo Social | C150: 112 | D150: Participación Ciudadana | E150: 0202020102 | F150: =VLOOKUP(E150,GACETA!$A$1:$C$186,3,0) -> M | G150: Apoyo Solidario | H150: =CONCATENATE(A150," ",C150," ",E150," ",F150) -> I01 112 0202020102 M | I150: Realizar Pintando tu fachada
A151: I01 | B151: Dirección de Desarrollo Social | C151: 112 | D151: Participación Ciudadana | E151: 0202020102 | F151: =VLOOKUP(E151,GACETA!$A$1:$C$186,3,0) -> M | G151: Apoyo Solidario | H151: =CONCATENATE(A151," ",C151," ",E151," ",F151) -> I01 112 0202020102 M | I151: Entregar sillas de ruedas para contribuir en el bienestar de las personas con movilidad reducida
A152: I01 | B152: Dirección de Desarrollo Social | C152: 112 | D152: Participación Ciudadana | E152: 0202020102 | F152: =VLOOKUP(E152,GACETA!$A$1:$C$186,3,0) -> M | G152: Apoyo Solidario | H152: =CONCATENATE(A152," ",C152," ",E152," ",F152) -> I01 112 0202020102 M | I152: Entregar auxiliares auditivos para contribuir en el bienestar de las personas con debilidad auditiva
A153: I01 | B153: Dirección de Desarrollo Social | C153: 112 | D153: Participación Ciudadana | E153: 0202020102 | F153: =VLOOKUP(E153,GACETA!$A$1:$C$186,3,0) -> M | G153: Apoyo Solidario | H153: =CONCATENATE(A153," ",C153," ",E153," ",F153) -> I01 112 0202020102 M | I153: Entregar apoyos para emprendimientos de los ciudadanos ecatepenses en los Centros de Desarrollo Comunitario
A154: I01 | B154: Dirección de Desarrollo Social | C154: 112 | D154: Participación Ciudadana | E154: 0202020102 | F154: =VLOOKUP(E154,GACETA!$A$1:$C$186,3,0) -> M | G154: Apoyo Solidario | H154: =CONCATENATE(A154," ",C154," ",E154," ",F154) -> I01 112 0202020102 M | I154: Entregar apoyos que contribuyan a mejorar la economía del hogar de los ecatepenses
A155: A01 | B155: Comunicación Social | C155: 103 | D155: Comunicación Social | E155: 0108030103 | F155: =VLOOKUP(E155,GACETA!$A$1:$C$186,3,0) -> F | G155: Difusión y comunicación institucional | H155: =CONCATENATE(A155," ",C155," ",E155," ",F155) -> A01 103 0108030103 F | I155: Campañas publicitarias de acciones gubernamentales
A156: A01 | B156: Comunicación Social | C156: 103 | D156: Comunicación Social | E156: 0108030103 | F156: =VLOOKUP(E156,GACETA!$A$1:$C$186,3,0) -> F | G156: Difusión y comunicación institucional | H156: =CONCATENATE(A156," ",C156," ",E156," ",F156) -> A01 103 0108030103 F | I156: Cobertura de eventos relacionados al municipio
A157: A01 | B157: Comunicación Social | C157: 103 | D157: Comunicación Social | E157: 0108030103 | F157: =VLOOKUP(E157,GACETA!$A$1:$C$186,3,0) -> F | G157: Difusión y comunicación institucional | H157: =CONCATENATE(A157," ",C157," ",E157," ",F157) -> A01 103 0108030103 F | I157: Boletín informativo de las acciones de gobierno
A158: A01 | B158: Comunicación Social | C158: 103 | D158: Comunicación Social | E158: 0108030103 | F158: =VLOOKUP(E158,GACETA!$A$1:$C$186,3,0) -> F | G158: Difusión y comunicación institucional | H158: =CONCATENATE(A158," ",C158," ",E158," ",F158) -> A01 103 0108030103 F | I158: Reuniones con medios de comunicación
A159: A01 | B159: Comunicación Social | C159: 103 | D159: Comunicación Social | E159: 0108030103 | F159: =VLOOKUP(E159,GACETA!$A$1:$C$186,3,0) -> F | G159: Difusión y comunicación institucional | H159: =CONCATENATE(A159," ",C159," ",E159," ",F159) -> A01 103 0108030103 F | I159: Reels
... A179: F00 | B179: DIRECCIÓN DE DESARROLLO URBANO | C179: 123 | D179: Desarrollo Urbano | E179: 0103080107 | F179: =VLOOKUP(E179,GACETA!$A$1:$C$186,3,0) -> M | G179: Instrumentación urbana | H179: =CONCATENATE(A179," ",C179," ",E179," ",F179) -> F00 123 0103080107 M | I179: Otorgar licencias de construccion y licencias de uso de suelo
E180: 0103080107 | F180: =VLOOKUP(E180,GACETA!$A$1:$C$186,3,0) -> M | G180: Instrumentación urbana | H180: =CONCATENATE(A180," ",C180," ",E180," ",F180) -> 0103080107 M | I180: Otorgar permisos de anuncios publicitarios
A181: F00 | B181: DIRECCIÓN DE DESARROLLO URBANO | C181: 123 | D181: Desarrollo Urbano | E181: 0103080107 | F181: =VLOOKUP(E181,GACETA!$A$1:$C$186,3,0) -> M | G181: Instrumentación urbana | H181: =CONCATENATE(A181," ",C181," ",E181," ",F181) -> F00 123 0103080107 M | I181: Creación de acervos de información
A182: F00 | B182: DIRECCIÓN DE DESARROLLO URBANO | C182: 123 | D182: Desarrollo Urbano | E182: 0103080107 | F182: =VLOOKUP(E182,GACETA!$A$1:$C$186,3,0) -> M | G182: Instrumentación urbana | H182: =CONCATENATE(A182," ",C182," ",E182," ",F182) -> F00 123 0103080107 M | I182: Digitalización de la información del archivo de concentración de la dependencia
A183: F00 | B183: DIRECCIÓN DE DESARROLLO URBANO | C183: 123 | D183: Desarrollo Urbano | E183: 0202010106 | F183: =VLOOKUP(E183,GACETA!$A$1:$C$186,3,0) -> K | G183: Participación comunitaria para el mejoramiento urbano | H183: =CONCATENATE(A183," ",C183," ",E183," ",F183) -> F00 123 0202010106 K | I183: Intervencion para rehabilitación de fachadas en zonas prioritarias
A184: F00 | B184: DIRECCIÓN DE DESARROLLO URBANO | C184: 123 | D184: Desarrollo Urbano | E184: 0202010106 | F184: =VLOOKUP(E184,GACETA!$A$1:$C$186,3,0) -> K | G184: Participación comunitaria para el mejoramiento urbano | H184: =CONCATENATE(A184," ",C184," ",E184," ",F184) -> F00 123 0202010106 K | I184: Reuniones informativas con los habitantes
A185: F00 | B185: DIRECCIÓN DE DESARROLLO URBANO | C185: 123 | D185: Desarrollo Urbano | E185: 0202010106 | F185: =VLOOKUP(E185,GACETA!$A$1:$C$186,3,0) -> K | G185: Participación comunitaria para el mejoramiento urbano | H185: =CONCATENATE(A185," ",C185," ",E185," ",F185) -> F00 123 0202010106 K | I185: Generar diagnósticos y planes de trabajo
A186: F00 | B186: DIRECCIÓN DE DESARROLLO URBANO | C186: 123 | D186: Desarrollo Urbano | E186: 0202050104 | F186: =VLOOKUP(E186,GACETA!$A$1:$C$186,3,0) -> E | G186: Regularización de predios | H186: =CONCATENATE(A186," ",C186," ",E186," ",F186) -> F00 123 0202050104 E | I186: estión para la regularización de los predios conforme al régimen jurídico urbano, realizada.
A187: F00 | B187: DIRECCIÓN DE DESARROLLO URBANO | C187: 123 | D187: Desarrollo Urbano | E187: 0202050104 | F187: =VLOOKUP(E187,GACETA!$A$1:$C$186,3,0) -> E | G187: Regularización de predios | H187: =CONCATENATE(A187," ",C187," ",E187," ",F187) -> F00 123 0202050104 E | I187: Asesoría jurídíca administrativa en materia de vivienda
A188: F00 | B188: DIRECCIÓN DE DESARROLLO URBANO | C188: 123 | D188: Desarrollo Urbano | E188: 0202050104 | F188: =VLOOKUP(E188,GACETA!$A$1:$C$186,3,0) -> E | G188: Regularización de predios | H188: =CONCATENATE(A188," ",C188," ",E188," ",F188) -> F00 123 0202050104 E | I188: Campañas de regularización de predios
A189: F00 | B189: DIRECCIÓN DE DESARROLLO URBANO | C189: 123 | D189: Desarrollo Urbano | E189: 0108010301 | F189: =VLOOKUP(E189,GACETA!$A$1:$C$186,3,0) -> E | G189: Control de la función registral | H189: =CONCATENATE(A189," ",C189," ",E189," ",F189) -> F00 123 0108010301 E | I189: Entrega de testamentos a los ciudadanos
A190: F00 | B190: DIRECCIÓN DE DESARROLLO URBANO | C190: 123 | D190: Desarrollo Urbano | E190: 0108010301 | F190: =VLOOKUP(E190,GACETA!$A$1:$C$186,3,0) -> E | G190: Control de la función registral | H190: =CONCATENATE(A190," ",C190," ",E190," ",F190) -> F00 123 0108010301 E | I190: Integración de expediente para trámite de testamento ante las Notarias que suscriban convenio
A191: F00 | B191: DIRECCIÓN DE DESARROLLO URBANO | C191: 123 | D191: Desarrollo Urbano | E191: 0108010301 | F191: =VLOOKUP(E191,GACETA!$A$1:$C$186,3,0) -> E | G191: Control de la función registral | H191: =CONCATENATE(A191," ",C191," ",E191," ",F191) -> F00 123 0108010301 E | I191: Asesorias para obtener testamento
A192: G00 | B192: DIRECCIÓN DE ECOLOGÍA | C192: 160 | D192: Prevención y Control Ambiental | E192: 0201040109 | F192: =VLOOKUP(E192,GACETA!$A$1:$C$186,3,0) -> V | G192: Concertación y participación ciudadana para la protección del ambiente | H192: =CONCATENATE(A192," ",C192," ",E192," ",F192) -> G00 160 0201040109 V | I192: Emisión de permisos, contancias y licencias en pro del mejoramiento ambienta
... A228: O00 | B228: EDUCACIÓN CULTURAL Y BIENESTAR SOCIAL | C228: 141 | D228: Educación | E228: 0205020105 | F228: =VLOOKUP(E228,GACETA!$A$1:$C$186,3,0) -> S | G228: Apoyo municipal a la educación media superior | H228: =CONCATENATE(A228," ",C228," ",E228," ",F228) -> O00 141 0205020105 S | I228: Alto Rendimiento Educativo de Media Superior
B229: #N/A | D229: #N/A | F229: =VLOOKUP(E229,GACETA!$A$1:$C$186,3,0) -> #N/A | G229: #N/A | H229: =CONCATENATE(A229," ",C229," ",E229," ",F229) -> #N/A | I229: Mantenimiento a Escuelas de Media Superior
A230: O00 | B230: EDUCACIÓN CULTURAL Y BIENESTAR SOCIAL | C230: 141 | D230: Educación | E230: 0205020105 | F230: =VLOOKUP(E230,GACETA!$A$1:$C$186,3,0) -> S | G230: Apoyo municipal a la educación media superior | H230: =CONCATENATE(A230," ",C230," ",E230," ",F230) -> O00 141 0205020105 S | I230: Feria de Oferta Superior
A231: O00 | B231: EDUCACIÓN CULTURAL Y BIENESTAR SOCIAL | C231: 141 | D231: Educación | E231: 0205030105 | F231: =VLOOKUP(E231,GACETA!$A$1:$C$186,3,0) -> S | G231: Apoyo municipal a la educación superior | H231: =CONCATENATE(A231," ",C231," ",E231," ",F231) -> O00 141 0205030105 S | I231: Alto Rendimieno Educativo Superior
A232: O00 | B232: EDUCACIÓN CULTURAL Y BIENESTAR SOCIAL | C232: 141 | D232: Educación | E232: 0205030105 | F232: =VLOOKUP(E232,GACETA!$A$1:$C$186,3,0) -> S | G232: Apoyo municipal a la educación superior | H232: =CONCATENATE(A232," ",C232," ",E232," ",F232) -> O00 141 0205030105 S | I232: Platicas informativas Nivel Superior
A233: O00 | B233: EDUCACIÓN CULTURAL Y BIENESTAR SOCIAL | C233: 141 | D233: Educación | E233: 0205050101 | F233: =VLOOKUP(E233,GACETA!$A$1:$C$186,3,0) -> S | G233: Alfabetización y educación básica para adultos | H233: =CONCATENATE(A233," ",C233," ",E233," ",F233) -> O00 141 0205050101 S | I233: Difusión y Certificación de Alfabetización
A234: O00 | B234: EDUCACIÓN CULTURAL Y BIENESTAR SOCIAL | C234: 141 | D234: Educación | E234: 0205050102 | F234: =VLOOKUP(E234,GACETA!$A$1:$C$186,3,0) -> S | G234: Formación para el trabajo | H234: =CONCATENATE(A234," ",C234," ",E234," ",F234) -> O00 141 0205050102 S | I234: Cursos de Capacitación para adultos
A235: J00 | B235: GOBIERNO MUNICIPAL | C235: 102 | D235: Derechos Humanos | E235: 0102040102 | F235: =VLOOKUP(E235,GACETA!$A$1:$C$186,3,0) -> E | G235: Protección y defensa de los derechos humanos | H235: =CONCATENATE(A235," ",C235," ",E235," ",F235) -> J00 102 0102040102 E | I235: Distribuir trípticos a ciudadanos y migrantes con información referente a sus derechos humanos y de relevancia.
A236: J00 | B236: GOBIERNO MUNICIPAL | C236: 102 | D236: Derechos Humanos | E236: 0102040102 | F236: =VLOOKUP(E236,GACETA!$A$1:$C$186,3,0) -> E | G236: Protección y defensa de los derechos humanos | H236: =CONCATENATE(A236," ",C236," ",E236," ",F236) -> J00 102 0102040102 E | I236: Brindar acompañamiento y apoyo en trámites a los migrante
A237: J00 | B237: GOBIERNO MUNICIPAL | C237: 102 | D237: Derechos Humanos | E237: 0102040102 | F237: =VLOOKUP(E237,GACETA!$A$1:$C$186,3,0) -> E | G237: Protección y defensa de los derechos humanos | H237: =CONCATENATE(A237," ",C237," ",E237," ",F237) -> J00 102 0102040102 E | I237: Ofrecer Pláticas jurídicas a los migrantes que, así como a las familias de migrantes que radican en Ecatepec
A238: J00 | B238: GOBIERNO MUNICIPAL | C238: 144 | D238: Gobernación | E238: 0103020104 | F238: =VLOOKUP(E238,GACETA!$A$1:$C$186,3,0) -> E | G238: Capacitación para el desarrollo de la cultura política | H238: =CONCATENATE(A238," ",C238," ",E238," ",F238) -> J00 144 0103020104 E | I238: Distribuir trípticos a la comunidad en general en cuanto a atribuciones, obligaciones y prohibiciones de delegaciones municipales y copacis, dando un enfoque referente al contenido sobre normatividad municipal, cívica y democrática.
A239: J00 | B239: GOBIERNO MUNICIPAL | C239: 144 | D239: Gobernación | E239: 0103020104 | F239: =VLOOKUP(E239,GACETA!$A$1:$C$186,3,0) -> E | G239: Capacitación para el desarrollo de la cultura política | H239: =CONCATENATE(A239," ",C239," ",E239," ",F239) -> J00 144 0103020104 E | I239: Plantear campañas que promueven la participacion ciudadana, con temas de valores civicos y democraticos en las personas y su vida en sociedad
A240: J00 | B240: GOBIERNO MUNICIPAL | C240: 144 | D240: Gobernación | E240: 0103020104 | F240: =VLOOKUP(E240,GACETA!$A$1:$C$186,3,0) -> E | G240: Capacitación para el desarrollo de la cultura política | H240: =CONCATENATE(A240," ",C240," ",E240," ",F240) -> J00 144 0103020104 E | I240: Crear mesa de trabajo y/o atención a reuniones vecinales y manifestaciones generadas por diversos motivos, con el fin de mantener la paz social
A241: J00 | B241: GOBIERNO MUNICIPAL | C241: 144 | D241: Gobernación | E241: 0103020104 | F241: =VLOOKUP(E241,GACETA!$A$1:$C$186,3,0) -> E | G241: Capacitación para el desarrollo de la cultura política | H241: =CONCATENATE(A241," ",C241," ",E241," ",F241) -> J00 144 0103020104 E | I241: Formular supervisiones a los integrantes de los Consejos de Participación Ciudadana y Delegados Municipales, para impulsar sus habilidades de gestión
... A276: Q00 | B276: SEGURIDAD PÚBLICA Y TRÁNSITO | C276: 152 | D276: Atención a la Mujer | E276: 0107010102 | F276: =VLOOKUP(E276,GACETA!$A$1:$C$186,3,0) -> M | G276: Tecnología, inteligencia e investigación para la prevención y combate al delito | H276: =CONCATENATE(A276," ",C276," ",E276," ",F276) -> Q00 152 0107010102 M | I276: Elaboración de informes mensuales de resultados obtenisdos
B277: #N/A | D277: #N/A | F277: =VLOOKUP(E277,GACETA!$A$1:$C$186,3,0) -> #N/A | G277: #N/A | H277: =CONCATENATE(A277," ",C277," ",E277," ",F277) -> #N/A | I277: Elaboración de mapas georeferenciados sobre los casos de violencia de género registrados
A278: M00 | B278: CONSEJERÍA JURÍDICA | C278: 155 | D278: Área Jurídica | E278: 0103050104 | F278: =VLOOKUP(E278,GACETA!$A$1:$C$186,3,0) -> L | G278: Asesoría jurídica al ayuntamiento | H278: =CONCATENATE(A278," ",C278," ",E278," ",F278) -> M00 155 0103050104 L | I278: Atender demandas en contra de la Administración Pública Municipal atendidas.
A279: M00 | B279: CONSEJERÍA JURÍDICA | C279: 155 | D279: Área Jurídica | E279: 0103050104 | F279: =VLOOKUP(E279,GACETA!$A$1:$C$186,3,0) -> L | G279: Asesoría jurídica al ayuntamiento | H279: =CONCATENATE(A279," ",C279," ",E279," ",F279) -> M00 155 0103050104 L | I279: Resoluciones jurídicas sujetas a derecho, conforme al marco jurídico, normativo y procedimental aplicable en la materia
A280: M00 | B280: CONSEJERÍA JURÍDICA | C280: 155 | D280: Área Jurídica | E280: 0103050104 | F280: =VLOOKUP(E280,GACETA!$A$1:$C$186,3,0) -> L | G280: Asesoría jurídica al ayuntamiento | H280: =CONCATENATE(A280," ",C280," ",E280," ",F280) -> M00 155 0103050104 L | I280: Asistir a la ciudadania en la gestión de sus asuntos juridicos
A281: M00 | B281: CONSEJERÍA JURÍDICA | C281: 155 | D281: Área Jurídica | E281: 0103050104 | F281: =VLOOKUP(E281,GACETA!$A$1:$C$186,3,0) -> L | G281: Asesoría jurídica al ayuntamiento | H281: =CONCATENATE(A281," ",C281," ",E281," ",F281) -> M00 155 0103050104 L | I281: Orientación Juridica en beneficio a niñas, niños y adolescentes.
A282: M00 | B282: CONSEJERÍA JURÍDICA | C282: 112 | D282: Participación Ciudadana | E282: 0108010101 | F282: =VLOOKUP(E282,GACETA!$A$1:$C$186,3,0) -> E | G282: Asesoría jurídica para los mexiquenses | H282: =CONCATENATE(A282," ",C282," ",E282," ",F282) -> M00 112 0108010101 E | I282: Brindar asistencia jurídica otorgada a la población fundamentada y motivada
A283: H00 | B283: SERVICIOS PÚBLICOS | C283: 147 | D283: Mercados y centrales de abasto | E283: 0202060106 | F283: =VLOOKUP(E283,GACETA!$A$1:$C$186,3,0) -> E | G283: Coordinación para servicios de administración y mantenimiento de mercados y centrales de abasto | H283: =CONCATENATE(A283," ",C283," ",E283," ",F283) -> H00 147 0202060106 E | I283: Procedimiento Administrativo para la reactivación de locales inactivos en mercados públicos municipales
A284: H00 | B284: SERVICIOS PÚBLICOS | C284: 147 | D284: Mercados y centrales de abasto | E284: 0202060103 | F284: =VLOOKUP(E284,GACETA!$A$1:$C$186,3,0) -> E | G284: Coordinación para la conservación de parques y jardines | H284: =CONCATENATE(A284," ",C284," ",E284," ",F284) -> H00 147 0202060103 E | I284: Actualzación refrendo 2026 de cédulas de concesión de mercado público municipal
...

Sheet ESTRUCTURA 2026
A1: AREA | B1: NOMBRE AREA | C1: AUXILIAR | D1: NOMBRE AUXILIAR | E1: ESTRUCTURA | F1: CONAC | G1: NOMBRE PROYECTO | H1: FULL | I1: OBJETIVO
A2: A00 | B2: PRESIDENCIA | C2: 100 | D2: Secretaría Particular | E2: 0103010101 | F2: P | G2: Relaciones públicas | H2: A00 100 0103010101 P
A3: A02 | B3: Derechos Humanos | C3: 102 | D3: Derechos Humanos | E3: 0102040102 | F3: E | G3: Protección y defensa de los derechos humanos | H3: A02 102 0102040102 E | I3: Asesoría jurídica a ciudadanos por presuntas violaciones a derechos humanos
A4: J00 | B4: GOBIERNO MUNICIPAL | C4: 102 | D4: Derechos Humanos | E4: 0102040102 | F4: E | G4: Protección y defensa de los derechos humanos | H4: J00 102 0102040102 E | I4: Distribuir trípticos a ciudadanos y migrantes con información referente a sus derechos humanos y de relevancia.
A5: A01 | B5: Comunicación Social | C5: 103 | D5: Comunicación Social | E5: 0108030103 | F5: F | G5: Difusión y comunicación institucional | H5: A01 103 0108030103 F | I5: Campañas publicitarias de acciones gubernamentales
A6: Q00 | B6: SEGURIDAD PÚBLICA Y TRÁNSITO | C6: 104 | D6: Seguridad Pública | E6: 0107010101 | F6: E | G6: Operación y vigilancia para la seguridad y prevención del delito | H6: Q00 104 0107010101 E | I6: Dispositivos de Seguridad
A7: T00 | B7: COORDINACIÓN MUNICIPAL DE PROTECCIÓN CIVIL | C7: 105 | D7: Coordinación Municipal de Protección Civil | E7: 0107020101 | F7: E | G7: Mitigación del impacto de fenómenos perturbadores | H7: T00 105 0107020101 E | I7: Valoración de riesgos en edificios públicos y privados, así como en zonas con riesgo geológico.
A8: D00 | B8: SECRETARÍA DEL AYUNTAMIENTO | C8: 108 | D8: Juzgados Cívicos | E8: 0103090301 | F8: L | G8: Mediación, conciliación y función calificadora municipal | H8: D00 108 0103090301 L | I8: Garantizar la paz social, convivencia familiar y vecinal a través de medios alternativos de solucion de controversias.
A9: B01 | B9: Sindicatura I | C9: 110 | D9: Acción Cívica | E9: 0202020102 | F9: M | G9: Apoyo Solidario | H9: B01 110 0202020102 M | I9: Realizar acciones, obras y apoyos en comunidades por medio de atención a la ciudadanía
A10: B02 | B10: Sindicatura II | C10: 110 | D10: Acción Cívica | E10: 0202020102 | F10: M | G10: Apoyo Solidario | H10: B02 110 0202020102 M | I10: Llevar acabo Sesiones de cabildo para abordar temas en benificio de la poblacion
A11: C01 | B11: Regiduría I | C11: 110 | D11: Acción Cívica | E11: 0202020102 | F11: M | G11: Apoyo Solidario | H11: C01 110 0202020102 M | I11: Realizar acciones, obras y apoyos en comunidades por medio de atención a la ciudadanía
A12: C02 | B12: Regiduría II | C12: 110 | D12: Acción Cívica | E12: 0202020102 | F12: M | G12: Apoyo Solidario | H12: C02 110 0202020102 M | I12: Realizar acciones, obras y apoyos en comunidades por medio de atención a la ciudadanía
A13: C03 | B13: Regiduría III | C13: 110 | D13: Acción Cívica | E13: 0202020102 | F13: M | G13: Apoyo Solidario | H13: C03 110 0202020102 M | I13: Realizar acciones, obras y apoyos en comunidades por medio de atención a la ciudadanía
A14: C04 | B14: Regiduría IV | C14: 110 | D14: Acción Cívica | E14: 0202020102 | F14: M | G14: Apoyo Solidario | H14: C04 110 0202020102 M | I14: Realizar acciones, obras y apoyos en comunidades por medio de atención a la ciudadanía
... A27: F00 | B27: DIRECCIÓN DE DESARROLLO URBANO | C27: 123 | D27: Desarrollo Urbano | E27: 0103080104 | F27: P | G27: Planeación integral y concertada | H27: F00 123 0103080104 P | I27: Elaboración de Plan Municipal de Desarrolllo Urbano
A28: X00 | B28: DIRECCIÓN DE OBRAS PÚBLICAS | C28: 124 | D28: Obras Públicas | E28: 0105020511 | F28: O | G28: Registro, control contable-presupuestal y cuenta de la hacienda pública municipal | H28: X00 124 0105020511 O
A29: H00 | B29: SERVICIOS PÚBLICOS | C29: 125 | D29: Servicios Públicos | E29: 0201010101 | F29: V | G29: Manejo integral de residuos sólidos | H29: H00 125 0201010101 V
A30: I02 | B30: Salud | C30: 129 | D30: Control Antirrábico y Bienestar Animal | E30: 0201050201 | F30: E | G30: Concientización y canalización Animal | H30: I02 129 0201050201 E | I30: Jornada de adopción de canino y/o felino
A31: N00 | B31: DIRECCIÓN DE DESARROLLO ECONÓMICO | C31: 131 | D31: Fomento Industrial | E31: 0304020102 | F31: F | G31: Fortalecimiento a la micro y pequeña empresa | H31: N00 131 0304020102 F | I31: Solicitudes de Licencia de funcionamiento
A32: K00 | B32: ÓRGANO INTERNO DE CONTROL MUNICIPAL | C32: 134 | D32: Auditoría Financiera | E32: 0103040101 | F32: O | G32: Fiscalización, control y evaluación interna de la gestión pública | H32: K00 134 0103040101 O | I32: Atención a las recomendaciones o pliego de observaciones de auditorías externas
A33: O00 | B33: EDUCACIÓN CULTURAL Y BIENESTAR SOCIAL | C33: 141 | D33: Educación | E33: 0205010110 | F33: S | G33: Apoyo municipal a la educación básica | H33: O00 141 0205010110 S | I33: Ejecución de programas para contribuir a mejorar el desarrollo integral de la comunidad estudiantil de Educación básica
A34: I00 | B34: PROMOCIÓN SOCIAL | C34: 143 | D34: Atención a la Juventud | E34: 0206080602 | F34: E | G34: Promoción del bienestar adolescente y juvenil | H34: I00 143 0206080602 E | I34: Prevención de la Violencia
A35: V00 | B35: DIRECCIÓN DE LAS MUJERES | C35: 152 | D35: Atención a la Mujer | E35: 0206080501 | F35: E | G35: Coordinación Institucional para la igualdad de género | H35: V00 152 0206080501 E | I35: Talleres de capacitación en igualdad de género a servidores públicos
A36: F01 | B36: Desarrollo Urbano y Servicios Públicos | C36: 154 | D36: Vialidad y Transporte | E36: 0105020602 | F36: M | G36: Capacitación y profesionalización para el desarrollo del personal | H36: F01 154 0105020602 M | I36: Se brindan las herramientas al personal mediante programas de capacitación técnica, operativa y de educación vial.
A37: G00 | B37: DIRECCIÓN DE ECOLOGÍA | C37: 160 | D37: Prevención y Control Ambiental | E37: 0201040109 | F37: V | G37: Concertación y participación ciudadana para la protección del ambiente | H37: G00 160 0201040109 V | I37: Emisión de permisos, contancias y licencias en pro del mejoramiento ambienta

Sheet dgeneral
A1: id | B1: clave | C1: dependencia
B2: A00 | C2: PRESIDENCIA
B3: A01 | C3: Comunicación Social
B4: A02 | C4: Derechos Humanos
B5: B01 | C5: Sindicatura I
B6: B02 | C6: Sindicatura II
B7: C01 | C7: Regiduría I
B8: C02 | C8: Regiduría II
B9: C03 | C9: Regiduría III
B10: C04 | C10: Regiduría IV
B11: C05 | C11: Regiduría V
B12: C06 | C12: Regiduría VI
B13: C07 | C13: Regiduría VII
... B37: X00 | C37: DIRECCIÓN DE OBRAS PÚBLICAS

Sheet dauxiliar
A1: id | B1: clave | C1: dependencia
B2: 100 | C2: Secretaría Particular
B3: 101 | C3: Secretaría Técnica
B4: 102 | C4: Derechos Humanos
B5: 103 | C5: Comunicación Social
B6: 104 | C6: Seguridad Pública
B7: 105 | C7: Coordinación Municipal de Protección Civil
B8: 106 | C8: Cuerpo de Bomberos
B9: 108 | C9: Juzgados Cívicos
B10: 109 | C10: Registro Civil
B11: 110 | C11: Acción Cívica
B12: 111 | C12: Coordinación de Delegaciones
B13: 112 | C13: Participación Ciudadana
... B54: 172 | C54: Atención a la Población de la Diversidad Sexual

Sheet proyectos
A1: id | B1: clave | C1: conac | D1: descripcion
B2: 0102040102 | C2: E | D2: Protección y defensa de los derechos humanos
B3: 0102040103 | C3: E | D3: Desarrollo institucional para los derechos humanos
B4: 0103010101 | C4: P | D4: Relaciones públicas
B5: 0103010103 | C5: E | D5: Audiencia pública y consulta popular
B6: 0103020104 | C6: E | D6: Capacitación para el desarrollo de la cultura política
B7: 0103030101 | C7: E | D7: Conservación, restauración y difusión del patrimonio cultural
B8: 0103040101 | C8: O | D8: Fiscalización, control y evaluación interna de la gestión pública
B9: 0103040102 | C9: P | D9: Participación social en la formulación, seguimiento, control y evaluación
B10: 0103040201 | C10: O | D10: Prevención, detección, disuasión, sanción y combate a la corrupción
B11: 0103040202 | C11: O | D11: Responsabilidades administrativas
B12: 0103040203 | C12: O | D12: Declaración de situación patrimonial, de interés y constancia de la declaración fiscal de los servidores públicos
B13: 0103040205 | C13: O | D13: Investigación de faltas administrativas
... B268: 0404010101 | C268: H | D268: Pasivos derivados de erogaciones devengadas y pendientes de ejercicios anteriores

Sheet Objetivo
A1: ÁREA ADMINISTRATIVA | B1: Denominación de Programa | C1: Denominación de Proyecto | D1: Obejetivo | E1: Propuesta de Objetivo para el PDM 2025 | F1: Descripción de Acciones
A2: SECRETARÍA DEL AYUNTAMIENTO | B2: Reglamentación municipal | C2: Revisión y emisión de la reglamentación municipal | D2: Incluye todos los procesos necesarios para que los ayuntamientos desarrollen los trabajos para creación, rediseño, actualización, publicación y difusión de la reglamentación municipal. | F2: Reglamentos y disposiciones de observancia general en el municipio publicadas | I2: Metas
F3: Capacitaciones en materia reglamentaria otorgadas | I3: Qué podemos aprovechar
F4: Revisión de propuestas viables de modificación a Leyes, decretos y reglamentos municipales | I4: Qué temas podemos atender
F5: Realización de sesiones de cabildo
B6: Consolidación de la administración pública para resultados | C6: Control del patrimonio y normatividad | D6: Comprende el conjunto de actividades y herramientas para coadyuvar a que la actuación de los servidores públicos sea eficaz, eficiente y transparente, a fin de generar resultados con apego a los principios de legalidad, objetividad, profesionalismo, honradez, lealtad, imparcialidad, eficiencia, eficacia, equidad, transparencia, economía, integridad, que permiten la toma de decisiones sobre la aplicación de los recursos públicos con el objeto de mejorar la calidad del gasto público y la rendición de cuentas. | F6: Realizar los levantamientos fisicos de los bienes muebles e inmuebles.
F7: Actualizar el inventario mediante revisiones fisicas por areas de trabajo de la Administracion Publica Municipal.
F8: Digitalización de documentación oficial por área,
B9: Justicia civica municipal | C9: Mediación, conciliación y función calificadora municipal | D9: Se orienta al cumplimiento de las atribuciones municipales contenidas en la Ley de Justicia Cívica del Estado de México y Municipios, así como la Ley de Mediación, Conciliación y Promoción de la Paz Social para el Estado de México, vigentes | F9: Garantizar la paz social, convivencia familiar y vecinal a través de medios alternativos de solucion de controversias.
F10: Citar a las partes en conflicto con la finalidad de dirimir sus diferencias a través del dialogo y medios alternativos de solución
F11: Dar cumplimiento a los ordenamientos legales a través de la aplicación de sanciones por infracciones
F12: Capacitaciones en tematicas relacionadas a la Justicia Civica
F13: Difusión de la cultura civica y cultura de la legalidad en medios de comunicación
F14: Informes de Resultados de las Acciones del Juzgado Cívico
F15: Jornadas de Trabajo en favor de la comunidad
B16: Protección jurídica de las personas | C16: Actualizacion y operación del registro civil | D16: Conjunto de acciones para el fortalecimiento de la certeza jurídica, edificando una alianza entre los distintos órdenes de gobierno y la población, a fin de consolidar una cultura de legalidad que impacte en la prevención del delito. | F16: Emitir copias certificadas de actas en las oficialías del Registro Civil aprovechando el uso de las tecnologías.
F17: Proporcionar las constancias de no registro de una forma más ágil a los solicitantes
F18: Supervisiones a las Oficialías del Registro Civil
F19: Incrementar el número de parejas que regularizan su estado civil mediante campañas de matrimonios masivos.
F20: Incrementar el número de parejas que regularicen su estatus jurídico y personalidad mediante campañas de registros extemporáneos
F21: Eventos de Matrimonios Masivos
A22: Sindicatura I | B22: Conducción de las políticas generales de gobierno | C22: Audiencia Pública y consulta popular | D22: Ejercer un gobierno democrático que impulse la participación social y ofrezca servicio de calidad en el marco de legalidad y justicia, para elevar las condiciones de vida en la población | F22: Fortalecer el marco normativo del ayuntamiento
F23: Divulgación de las políticas públicas municipales en los medios de comunicación institucional
A24: Sindicatura II | B24: Conducción de las políticas generales de gobierno | C24: Audiencia Pública y consulta popular | D24: Ejercer un gobierno democrático que impulse la participación social y ofrezca servicio de calidad en el marco de legalidad y justicia, para elevar las condiciones de vida en la población | F24: Fortalecer el marco normativo del ayuntamiento
F25: Divulgación de las políticas públicas municipales en los medios de comunicación institucional
A26: REGIDURÍA I | B26: Conducción de las políticas generales de gobierno | C26: Audiencia Pública y consulta popular | D26: Ejercer un gobierno democrático que impulse la participación social y ofrezca servicio de calidad en el marco de legalidad y justicia, para elevar las condiciones de vida en la población | F26: Fortalecer el marco normativo del ayuntamiento
F27: Divulgación de las políticas públicas municipales en los medios de comunicación institucional
A28: REGIDURÍA II | B28: Conducción de las políticas generales de gobierno | C28: Audiencia Pública y consulta popular | D28: Ejercer un gobierno democrático que impulse la participación social y ofrezca servicio de calidad en el marco de legalidad y justicia, para elevar las condiciones de vida en la población | F28: Fortalecer el marco normativo del ayuntamiento
F29: Divulgación de las políticas públicas municipales en los medios de comunicación institucional
A30: REGIDURÍA III | B30: Conducción de las políticas generales de gobierno | C30: Audiencia Pública y consulta popular | D30: Ejercer un gobierno democrático que impulse la participación social y ofrezca servicio de calidad en el marco de legalidad y justicia, para elevar las condiciones de vida en la población | F30: Fortalecer el marco normativo del ayuntamiento
F31: Divulgación de las políticas públicas municipales en los medios de comunicación institucional
A32: REGIDURÍA IV | B32: Conducción de las políticas generales de gobierno | C32: Audiencia Pública y consulta popular | D32: Ejercer un gobierno democrático que impulse la participación social y ofrezca servicio de calidad en el marco de legalidad y justicia, para elevar las condiciones de vida en la población | F32: Fortalecer el marco normativo del ayuntamiento
F33: Divulgación de las políticas públicas municipales en los medios de comunicación institucional
A34: REGIDURÍA V | B34: Conducción de las políticas generales de gobierno | C34: Audiencia Pública y consulta popular | D34: Ejercer un gobierno democrático que impulse la participación social y ofrezca servicio de calidad en el marco de legalidad y justicia, para elevar las condiciones de vida en la población | F34: Fortalecer el marco normativo del ayuntamiento
F35: Divulgación de las políticas públicas municipales en los medios de comunicación institucional
A36: REGIDURÍA VI | B36: Conducción de las políticas generales de gobierno | C36: Audiencia Pública y consulta popular | D36: Ejercer un gobierno democrático que impulse la participación social y ofrezca servicio de calidad en el marco de legalidad y justicia, para elevar las condiciones de vida en la población | F36: Fortalecer el marco normativo del ayuntamiento
F37: Divulgación de las políticas públicas municipales en los medios de comunicación institucional
A38: REGIDURÍA VII | B38: Conducción de las políticas generales de gobierno | C38: Audiencia Pública y consulta popular | D38: Ejercer un gobierno democrático que impulse la participación social y ofrezca servicio de calidad en el marco de legalidad y justicia, para elevar las condiciones de vida en la población | F38: Fortalecer el marco normativo del ayuntamiento
F39: Divulgación de las políticas públicas municipales en los medios de comunicación institucional
A40: REGIDURÍA VIII | B40: Conducción de las políticas generales de gobierno | C40: Audiencia Pública y consulta popular | D40: Ejercer un gobierno democrático que impulse la participación social y ofrezca servicio de calidad en el marco de legalidad y justicia, para elevar las condiciones de vida en la población | F40: Fortalecer el marco normativo del ayuntamiento
F41: Divulgación de las políticas públicas municipales en los medios de comunicación institucional
A42: REGIDURÍA IX | B42: Conducción de las políticas generales de gobierno | C42: Audiencia Pública y consulta popular | D42: Ejercer un gobierno democrático que impulse la participación social y ofrezca servicio de calidad en el marco de legalidad y justicia, para elevar las condiciones de vida en la población | F42: Fortalecer el marco normativo del ayuntamiento
F43: Divulgación de las políticas públicas municipales en los medios de comunicación institucional
A44: REGIDURÍA X | B44: Conducción de las políticas generales de gobierno | C44: Audiencia Pública y consulta popular | D44: Ejercer un gobierno democrático que impulse la participación social y ofrezca servicio de calidad en el marco de legalidad y justicia, para elevar las condiciones de vida en la población | F44: Fortalecer el marco normativo del ayuntamiento
F45: Divulgación de las políticas públicas municipales en los medios de comunicación institucional
A46: REGIDURÍA XI | B46: Conducción de las políticas generales de gobierno | C46: Audiencia Pública y consulta popular | D46: Ejercer un gobierno democrático que impulse la participación social y ofrezca servicio de calidad en el marco de legalidad y justicia, para elevar las condiciones de vida en la población | F46: Fortalecer el marco normativo del ayuntamiento
F47: Divulgación de las políticas públicas municipales en los medios de comunicación institucional
A48: REGIDURÍA XII | B48: Conducción de las políticas generales de gobierno | C48: Audiencia Pública y consulta popular | D48: Ejercer un gobierno democrático que impulse la participación social y ofrezca servicio de calidad en el marco de legalidad y justicia, para elevar las condiciones de vida en la población | F48: Fortalecer el marco normativo del ayuntamiento
F49: Divulgación de las políticas públicas municipales en los medios de comunicación institucional
A50: TESORERÍA MUNICIPAL | B50: Fortalecimiento de los ingresos | C50: Captación y recaudación de ingresos | D50: Incluye acciones que permitan elevar la calidad, capacidad y equidad tributaria, con seguridad jurídica , transparencia y simplificación de trámites para el contribuyente, desarrollando un régimen fiscal que amplíe la base de contribuyentes e intensificando las acciones de control para el cumplimiento de las obligaciones tributarias que eviten la elusión y evasión fiscal. | F50: Difusión masiva de los apoyos, subsidios, fiscales y exhortación al pago puntual.
F51: Actualización del padrón de cobro de impuesto predial
F52: Actualización de los padrones de Multas Federales
F53: Actualización de los padrones de Multas Locales
F54: Determinación de Créditos Fiscales para contribuyentes morosos, omisos y remisos (Contribuciones, Derechos y Aprovechamientos)
F55: Recuperación de créditos fiscales
F56: Emisión y entrega de cartas invitación para pagos pendientes (Predial)
F57: Requerimiento de pago para contribuyentes morosos (Notificación)
F58: Expedición y Entrega de Mandamientos de Ejecución
F59: Visita de cajas móviles a comunidades para la recaudación del impuesto predial
F60: Actualización y Cobro de Impuesto Predial por concepto de Diferencias de Construcción No Declaradas
F61: Traslado de Dominio Autorizados
F62: Emisión de Certificación de traslado de dominio
F63: Emisión, Pago y Entrega de Certificaciones de No Adeudo de Impuesto Predial y Aportación de Mejoras
C64: Registro y control de caja y tesorería | D64: Incluye acciones que permitan elevar la calidad, capacidad y equidad tributaria, con seguridad jurídica , transparencia y simplificación de trámites para el contribuyente, desarrollando un régimen fiscal que amplíe la base de contribuyentes e intensificando las acciones de control para el cumplimiento de las obligaciones tributarias que eviten la elusión y evasión fiscal. | F64: Llevar el control y registro de cajas, mediante el reporte de total de operaciones, inspeccionando el buen manejo de estas.
B65: Gasto social e inversión pública | C65: Asignación, registro, seguimiento y control de la inversión pública municipal | D65: Elaborar con las Dependencias y Organismos municipales los planes y programas estatales, sectoriales, regionales y los referentes a inversión pública física, vigilanbdo que los recursos que se asignen se apliquen de acuerdo a la normatividad vigente, así como fortalecer a relación con el estado, la federación y otros municipios, reconociendo sus responsabilidades en la ejecución de la obra pública. | F65: Revisión de los Expedientes de Obras Publicas (estimaciones)
F66: Actualización del Sistema de Recursos Federales Transferidos
F67: Seguimiento a las Gestiones de los Recursos Federales y Estatales
F68: Actualización del Sistema de Avance Mensual (SIAVAMEN)
B69: Planeación y presupuesto basado en resultados | C69: Planeación y evaluación para el desarrollo municipal | D69: Incluye las acciones y procedimientos necesarias para desarrollar y fortalecer las fases para la planeación, programación-presupuestación, seguimiento y evaluación programatica presupuestal, considerando las fases de registro contable - presupuestal y el correspondiente proceso de rendición de cuentas, adicionalmente incluye los procedimientos de planeación, evaluación de los planes de desarrollo municipal, los programas regionales y sociales que de él dervan. | F69: Seguimiento a los resultados y ejecución de los recursos con los que dispone el municipio.
C70: Integración, seguimiento y control presupuestal del ayuntamiento | D70: Incluye las acciones y procedimientos necesarias para desarrollar y fortalecer las fases para la planeación, programación-presupuestación, seguimiento y evaluación programatica presupuestal, considerando las fases de registro contable - presupuestal y el correspondiente proceso de rendición de cuentas, adicionalmente incluye los procedimientos de planeación, evaluación de los planes de desarrollo municipal, los programas regionales y sociales que de él dervan. | F70: Mejorar el control del presupuesto, mediante la emisión de reportes
F71: Asesorar a las diversas áreas en materia presupuestal
F72: Integración del presupuesto de ingresos y egresos definitivo para el ejercicio fiscal 2024
F73: Integración del anteproyecto de presupuesto de ingresos y egresos para el ejercicio fiscal 2025
C74: Registro, control contable-presupuestal y cuenta de la hacienda pública municipal | D74: Incluye las acciones y procedimientos necesarias para desarrollar y fortalecer las fases para la planeación, programación-presupuestación, seguimiento y evaluación programatica presupuestal, considerando las fases de registro contable - presupuestal y el correspondiente proceso de rendición de cuentas, adicionalmente incluye los procedimientos de planeación, evaluación de los planes de desarrollo municipal, los programas regionales y sociales que de él dervan. | F74: Reportes trimestrales enviados al OSFEM
F75: Envió de la cuenta pública OSFEM
F76: Reportes y reactivos enviados al SEVAC
F77: Reportes CONAC
F78: Dispersión nomina
B79: Deuda pública | C79: Amortización de la deuda (Capital) | D79: Refiere todas aquellas acciones relacionadas con el manejo eficiente y sustentable de la deuda pública, entre ellas, la contratación, amortización, servicio. Refinanciamiento y/o reestructuración de la deuda del gobierno municipal, así como el registro, vigilancia, seguimiento y control de sus obligaciónes multianuales correpondientes al gobierno municipal. | F79: Pago a capital de financiamiento
C80: Costo financiero de la deuda (Intereses) | D80: Refiere todas aquellas acciones relacionadas con el manejo eficiente y sustentable de la deuda pública, entre ellas, la contratación, amortización, servicio. Refinanciamiento y/o reestructuración de la deuda del gobierno municipal, así como el registro, vigilancia, seguimiento y control de sus obligaciónes multianuales correpondientes al gobierno municipal. | F80: Pago a Intereses de Financiamiento
B81: Transferencias | C81: Convenios de Coordinación | D81: Comprende la suma de recursos transferidos por los municipios y organismos municipales para cumplir con objetivos diversos, además engloba las acciones necesarias para la celebración de convenios previstos en la Ley de Coordinación Fiscal vigente | F81: Seguimiento a convenio en términos de la Ley de Coordinación Fiscal
C82: Transferencias del ayuntamiento a organismos municipales | D82: Comprende la suma de recursos transferidos por los municipios y organismos municipales para cumplir con objetivos diversos, además engloba las acciones necesarias para la celebración de convenios previstos en la Ley de Coordinación Fiscal vigente | F82: Transferencia del ayuntamiento a Organismos Descentralizados
B83: Previsiones para el pago de adeudos de ejercicios fiscales anteriores | C83: Pasivos derivados de erogaciones devengadas y pendientes de ejercicios anteriores | D83: Tiene por objeto integrar los recursos financieros presupuestales para el pago de adeudos que no fueron cubiertos en ejercicios anteriores. | F83: Pago de las ADEFAS del ejercicio
B84: Asistencia Jurídica al Ejecutivo | C84: Asesoría Jurídica al Ayuntamiento | D84: Fortalecimiento y mejora de los procedimientos regulatorios y conductos legales establecidos, que influyan directamente en la garantía jurídica del gobierno y la sociedad. | F84: Dar cumplimiento a lo ordenado en las sentencias emitidas por los tribunales
F85: Contestación de demandas
F86: Desahogos de requerimientos
F87: Informes previos y justificados
F88: Interposición de demandas de amparo
F89: Interposición de recursos de revisión y de revocación
F90: Oficios de contestación a diversas unidades administrativas
B91: Modernización del catastro mexiquense | C91: Servicios e información catastral estatal y municipal | D91: Engloba las acciones que se llevan a cabo por los gobiernos municipales en los procesos de registro de bienes inmuebles en el territorio estatal, así como determinar extensión geográfica y valor catastral por demarcación que definan la imposición fiscal. | F91: Recepción de solicitudes de trámite catastral presentadas por la ciudadanía
F92: Atención de las solicitudes de trámite catastral presentadas por la ciudadanía
F93: Programación para la realización de las diligencias de inspección y medición física de los predios
F94: Levantamiento topográficos catastrales de inmuebles realizados
F95: Revaluación de cuentas catastrales a través del sistema cartográfico catastral
F96: Elaboración de proyecto de modificación de valores unitarios de suelo para el ejercicio fiscal 2025, (Áreas Homogéneas y bandas de valor)
B97: Gobierno Electrónico | C97: Innovación gubernamental con tecnologías de información | D97: ENGLOBA TODAS LAS ACTIVIDADES O SERVICIOS QUE LAS ADMINISTRACIONES MUNICIPALES OTORGAN A LA POBLACIÓN A TRAVÉS DE TECNOLOGÍAS DE INFORMACIÓN, MEJORANDO LA EFICIENCIA Y EFICACIA EN LOS PROCESOS FACILITANDO LA OPERACIÓN Y DISTRIBUCIÓN DE INFORMACIÓN QUE SE BRINDA A LA POBLACIÓN. | F97: Reportes de servicios de areas
F98: Mantenimiento preventivo de equipos de computo
F99: Reportes de servicios de RED
F100: Reportes de servicios de telefonia
...

Sheet Ob, Nuevos
G2: Ecatepec como Modelo de Protección Civil
F7: Estrategias
B8: programa | C8: proyecto
A9: DIRECCIÓN GENERAL DE SEGURIDAD CIUDADANA Y TRÁNSITO MUNICIPAL | B9: Seguridad pública | C9: Operación y vigilancia para la seguridad y prevención del delito | D9: Incluye los proyectos orientados a combatir la inseguridad pública con estricto apego a la ley para erradicar la impunidad y la corrupción, mediante la profesionalización de los cuerpos de seguridad, modificando los métodos y programas de estudio para humanizarlos, dignificarlos y hacerlos más eficientes, aplicando sistemas de reclutamiento y selección confiable y riguroso proceso estandarizado de evaluación, así como promover la participación social en acciones preventivas del delito. | E9: Disminuir la incidencia delictiva, mediante la reestructuración del territorio del municiio como Plan operativo, en el municipio cde Ecatepec. | F9: Disminuir, índice de delitos por medio de la optimización del Modelo Operativo Policial. Territorialidad del Municipio para la proximidad de elementos policiales así como identificar los cuadrantes para ejecutar operativos conjuntos para reducir la generación de violencia y delitos que atenten a la sociedad. | G9: Dispositivos de Seguridad
C10: Tecnología, inteligencia e investigación para la prevención y combate al delito | D10: Incluye los proyectos orientados a combatir la inseguridad pública con estricto apego a la ley para erradicar la impunidad y la corrupción, mediante la profesionalización de los cuerpos de seguridad, modificando los métodos y programas de estudio para humanizarlos, dignificarlos y hacerlos más eficientes, aplicando sistemas de reclutamiento y selección confiable y riguroso proceso estandarizado de evaluación, así como promover la participación social en acciones preventivas del delito. | E10: Fortalecer la inteligencia e investigación, por medio de la explotación y el emleo de las tecnologías de informació y comunicación. | G10: Generación de folios para realizar puestas a disposición ante el Ministerio Público y las oficialías calificadoras-conciliadoras por faltas administrativas.
F11: Con la ayuda de la tenología, inteligencia e investigación | G11: Registro o captura del Informe Policial Homologado puestas a disposición ante el Ministerio Público
F12: Pln de comunicaciones policial | G12: Consulta de los datos generales de las personas y vehículos en el sistema Único de Investigación Criminal (SUIC)
G13: Consulta de los datos generales de las personas y vehículos en el Sistema Único de Investigación Criminal Estatal (SUICE)
G14: Registro de delitos en el Sistema Nacional de detenciones del fuero común y federal.
G15: Registro de delitos en el Sistema Nacional de detenciones de faltas administrativas.
G16: Informe de Incidencia Delictiva para poder determinar e implementar más operativos.
G17: Registro de llamadas de emergencia de la ciudadanía a través del Sistema SafetyNat Cad
G18: Actualización integral del atlas de la incidencia delictiva municipal
G19: Análisis delictivo para la prevención y combate de los delitos de alto impacto
G20: Publicaciones informativas a través de las cuentas oficiales de redes sociales
C21: Formación profresional especializada para personas servidoras públicas de instituciones de seguridad pública | D21: Incluye los proyectos orientados a combatir la inseguridad pública con estricto apego a la ley para erradicar la impunidad y la corrupción, mediante la profesionalización de los cuerpos de seguridad, modificando los métodos y programas de estudio para humanizarlos, dignificarlos y hacerlos más eficientes, aplicando sistemas de reclutamiento y selección confiable y riguroso proceso estandarizado de evaluación, así como promover la participación social en acciones preventivas del delito. | E21: Elevar la percepción de seguridad por medio de programas anticorrupción, de prevención dirigidos a la capacitación de elementos de seguridad y servidores públicos en el municipio. Atender las causa que originan la violencia a través de recuperación de espacios, promoción de ética, valores y sentido de pertenencia, respeto a los derechos humanos, | G21: Capacitación a las fuerzas policiacas en diversos rubros de seguridad pública
F22: Evaluación de los elementos de seguridad para la depuración y reclutamiento | G22: Registro ante el Sistema Nacional de Personal de Seguridad Pública, para la emisión del Certificado Único Policial.
G23: Aplicación de Exámenes de Control de Confianza a personal en activo
G24: Recepción de expedientes derivado de quejas. Tarjetas informativas, redes sociales o denuncias anónimas, encontrar de los elementos que pertenecen a la DSPYT, así como la resolución de los mismos.
G25: Integración y seguimiento a Juicios Administrativos, ante diferentes órganos jurisdiccionales, locales y Federales en contra de la comisión de Honor y justicia de la dirección de Seguridad pública y Transito
C26: Vinculación, participación, prevención del delito y denuncia social | D26: Incluye los proyectos orientados a combatir la inseguridad pública con estricto apego a la ley para erradicar la impunidad y la corrupción, mediante la profesionalización de los cuerpos de seguridad, modificando los métodos y programas de estudio para humanizarlos, dignificarlos y hacerlos más eficientes, aplicando sistemas de reclutamiento y selección confiable y riguroso proceso estandarizado de evaluación, así como promover la participación social en acciones preventivas del delito. | E26: Incrementar la cooordinación con otras instancias de gobierno, con la iniciativa privada y sectores de la sociedad civil con el fin de crear mecanismos de colaboración a favor de la seguridad y la paz. | G26: Atenciones ciudadanas en materia de violencia familiar y de género
G27: Atenciones ciudadanas por extravío o desaparición de personas
G28: Asesoría a mujeres en situaciones de violencia
G29: Actividades culturales y deportivas con la comunidad
C30: Mantenimiento de los dispositivos para el control de transito y educación vial | E30: Implementar acciones específicas para mejorar la gestión de la seguridad vial, / proveer infraestructura segura y con accesibilidad universal, / fomentar el uso de vehículos más seguros / educar a las personas usuarias sobre la importancia de la seguridad vial / mejorar la respuesta posterior a los hechos de tránsito para dar una atención integral a las víctimas directas e indirectas en términos de atención pre-hospitalaria y acceso a la justicia.
B34: Coordinación Intergubernamental para la seguridad publica | C34: Acciones del programa nacional de seguridad pública | D34: Se orienta a la coordinación de acciones que permitan eficientar los mecanismos en materia de seguridad pública con apego a la legalidad que garantice el logro de objetivos gubernamentales. | E34: Eficientar los mecanismos en materia de seguridad pública, para ampliar el alcacnce a la respueta policial y de prevención | G34: Celebración de sesiones del consejo Intermunicipal de Seguridad pública
G35: Sesiones del consejo municipal de seguridad publica
G36: Programa para la adquisicion de implementos basicos para el desarrollo de la funcion policial

Sheet Pp y Py 2026
A1: DG | B1: ÁREA ADMINISTRATIVA | C1: Fin | D1: FN | E1: SF | F1: PG | G1: SP | H1: Py | I1: DG | J1: D Aux | K1: Denominación de Programa | L1: Denominación de Proyecto
A2: D00 | B2: SECRETARÍA DEL AYUNTAMIENTO | C2: 01 | D2: 03 | E2: 09 | F2: 02 | G2: 01 | H2: 01 | I2: D00 | J2: 155 | K2: Reglamentación municipal | L2: Revisión y emisión de la reglamentación municipal
C3: 01 | D3: 05 | E3: 02 | F3: 06 | G3: 06 | I3: D00 | J3: 114 | K3: Consolidación de la administración pública de resultados | L3: Control del patrimonio y normatividad
C4: 01 | D4: 03 | E4: 09 | F4: 03 | G4: 01 | I4: D00 | J4: 108 | K4: Justicia Cívica Municipal | L4: Mediación, conciliación y función calificadora municipal
C5: 01 | D5: 08 | E5: 01 | F5: 01 | G5: 02 | I5: D00 | J5: 109 | K5: Protección Jurídica de las Personas | L5: Actualizacion y operación del Registro Civil | M5: Este faltabaa
A6: B01 | B6: Sindicatura I | C6: 02 | D6: 02 | E6: 02 | F6: 01 | G6: 02 | I6: B01 | J6: 110 | K6: Desarrollo comunitario | L6: Apoyo solidario
A7: B02 | B7: Sindicatura II | C7: 02 | D7: 02 | E7: 02 | F7: 01 | G7: 02 | I7: B02 | J7: 110 | K7: Desarrollo comunitario | L7: Apoyo solidario
A8: C01 | B8: REGIDURÍA I | C8: 02 | D8: 02 | E8: 02 | F8: 01 | G8: 02 | I8: C01 | J8: 110 | K8: Desarrollo comunitario | L8: Apoyo solidario
A9: C02 | B9: REGIDURÍA II | C9: 02 | D9: 02 | E9: 02 | F9: 01 | G9: 02 | I9: C02 | J9: 110 | K9: Desarrollo comunitario | L9: Apoyo solidario
A10: C03 | B10: REGIDURÍA III | C10: 02 | D10: 02 | E10: 02 | F10: 01 | G10: 02 | I10: C03 | J10: 110 | K10: Desarrollo comunitario | L10: Apoyo solidario
A11: C04 | B11: REGIDURÍA IV | C11: 02 | D11: 02 | E11: 02 | F11: 01 | G11: 02 | I11: C04 | J11: 110 | K11: Desarrollo comunitario | L11: Apoyo solidario
A12: C05 | B12: REGIDURÍA V | C12: 02 | D12: 02 | E12: 02 | F12: 01 | G12: 02 | I12: C05 | J12: 110 | K12: Desarrollo comunitario | L12: Apoyo solidario
A13: C06 | B13: REGIDURÍA VI | C13: 02 | D13: 02 | E13: 02 | F13: 01 | G13: 02 | I13: C06 | J13: 110 | K13: Desarrollo comunitario | L13: Apoyo solidario
A14: C07 | B14: REGIDURÍA VII | C14: 02 | D14: 02 | E14: 02 | F14: 01 | G14: 02 | I14: C07 | J14: 110 | K14: Desarrollo comunitario | L14: Apoyo solidario
A15: C08 | B15: REGIDURÍA VIII | C15: 02 | D15: 02 | E15: 02 | F15: 01 | G15: 02 | I15: C08 | J15: 110 | K15: Desarrollo comunitario | L15: Apoyo solidario
A16: C09 | B16: REGIDURÍA IX | C16: 02 | D16: 02 | E16: 02 | F16: 01 | G16: 02 | I16: C09 | J16: 110 | K16: Desarrollo comunitario | L16: Apoyo solidario
A17: C10 | B17: REGIDURÍA X | C17: 02 | D17: 02 | E17: 02 | F17: 01 | G17: 02 | I17: C10 | J17: 110 | K17: Desarrollo comunitario | L17: Apoyo solidario
... A20: L00 | B20: TESORERÍA MUNICIPAL | C20: 01 | D20: 05 | E20: 02 | F20: 02 | G20: 01 | I20: L00 | J20: 115 | K20: Fortalecimiento de los ingresos | L20: Captación y recaudación de ingresos
C21: 01 | D21: 05 | E21: 02 | F21: 02 | G21: 09 | I21: L00 | J21: 115 | L21: Registro y control de caja y tesorería
C22: 01 | D22: 05 | E22: 02 | F22: 03 | G22: 04 | I22: L00 | J22: 119 | K22: Administración del programa de inversión pública | L22: Asignación, registro, seguimiento y control de la inversión pública municipal
C23: 01 | D23: 05 | E23: 02 | F23: 05 | G23: 08 | I23: L00 | J23: 119 | K23: Planeación y presupuesto basado en resultados | L23: Planeación y evaluación para el desarrollo municipal
C24: 01 | D24: 05 | E24: 02 | F24: 05 | G24: 10 | I24: L00 | J24: 117 | L24: Integración, seguimiento y control presupuestal del ayuntamiento
C25: 01 | D25: 05 | E25: 02 | F25: 05 | G25: 11 | I25: L00 | J25: 116 | L25: Registro, control contable-presupuestal y cuenta de la hacienda pública municipal
C26: 04 | D26: 01 | E26: 01 | F26: 01 | G26: 04 | I26: L00 | J26: 116 | K26: Deuda pública | L26: Amortización de la deuda (Capital)
C27: 04 | D27: 01 | E27: 01 | F27: 01 | G27: 05 | I27: L00 | J27: 116 | L27: Costo financiero de la deuda (Intereses)
C28: 04 | D28: 02 | E28: 01 | F28: 01 | G28: 03 | I28: L00 | J28: 115 | K28: Transferencias | L28: Convenios de Coordinación
C29: 04 | D29: 02 | E29: 01 | F29: 01 | G29: 04 | I29: L00 | J29: 116 | L29: Transferencias del ayuntamiento a organismos municipales
C30: 04 | D30: 04 | E30: 01 | F30: 01 | G30: 01 | I30: L00 | J30: 116 | K30: Previsiones para el pago de adeudos de ejercicios fiscales anteriores | L30: Pasivos derivados de erogaciones devengadas y pendientes de ejercicios anteriores
C31: 01 | D31: 03 | E31: 05 | F31: 01 | G31: 04 | I31: L00 | J31: 155 | K31: Asistencia Jurídica al Ejecutivo | L31: Asesoría Jurídica al Ayuntamiento
C32: 01 | D32: 08 | E32: 01 | F32: 02 | G32: 01 | I32: L00 | J32: 118 | K32: Modernización del catastro mexiquense | L32: Servicios e información catastral estatal y municipal
C33: 01 | D33: 08 | E33: 05 | F33: 01 | G33: 03 | I33: L00 | J33: 137 | K33: Gobierno digítal | L33: Innovación gubernamental con tecnologías de información
A34: K00 | B34: ÓRGANO INTERNO DE CONTROL MUNICIPAL | C34: 01 | D34: 03 | E34: 04 | F34: 01 | G34: 01 | I34: K00 | J34: 134 | K34: Función pública y combate a la corrupción y control de riesgos administrativos | L34: Fiscalizacion, control y evaluacion interna de la gestion publica
C35: 01 | D35: 03 | E35: 04 | F35: 01 | G35: 02 | I35: K00 | J35: 139 | L35: Participación social en la formulación, seguimiento, control y evaluación interna de obras, programas y servicios públicos
C36: 01 | D36: 03 | E36: 04 | F36: 02 | G36: 01 | I36: K00 | J36: 136 | K36: Sistema Anticprrupcion del Estado de Mexico y Municipios | L36: Prevención, detección, disuación, sanción y combate a la corrupción
C37: 01 | D37: 03 | E37: 04 | F37: 02 | G37: 02 | I37: K00 | J37: 138 | L37: Responsabilidades administrativas
C38: 01 | D38: 03 | E38: 04 | F38: 02 | G38: 03 | I38: K00 | J38: 138 | L38: Declaración de situación patrimonial, de interés y constancia de la declaración fiscal de los servidores públicos.
C39: 01 | D39: 03 | E39: 04 | F39: 02 | G39: 05 | I39: K00 | J39: 138 | L39: Investigación de faltas administrativas
A40: E00 | B40: DIRECCIÓN DE ADMINISTRACIÓN | C40: 01 | D40: 05 | E40: 02 | F40: 01 | G40: 05 | I40: E00 | J40: 120 | K40: Desarrollo municipal | L40: Desarrollo e impulso de la profesionalización, la investigación, estadísticas hacendarias y proyectos especiales
C41: 01 | D41: 05 | E41: 02 | F41: 01 | G41: 05 | I41: E00 | J41: 120
C42: 01 | D42: 05 | E42: 02 | F42: 06 | G42: 01 | I42: E00 | J42: 120 | K42: Consolidación de la administración pública de resultados | L42: Administración de personal
C43: 01 | D43: 05 | E43: 02 | F43: 06 | G43: 01 | I43: E00 | J43: 120
C44: 01 | D44: 05 | E44: 02 | F44: 06 | G44: 02 | I44: E00 | J44: 120 | L44: Capacitación y profesionalización para el desarrollo personal.
C45: 01 | D45: 05 | E45: 02 | F45: 06 | G45: 02 | I45: E00 | J45: 120
C46: 01 | D46: 05 | E46: 02 | F46: 06 | G46: 03 | I46: E00 | J46: 121 | L46: Adquisiciones y servicios
C47: 01 | D47: 05 | E47: 02 | F47: 06 | G47: 03 | I47: E00 | J47: 121
C48: 01 | D48: 05 | E48: 02 | F48: 06 | G48: 06 | I48: E00 | J48: 114 | L48: Control del patrimonio y normatividad
C49: 01 | D49: 05 | E49: 02 | F49: 06 | G49: 06 | I49: E00 | J49: 114
A50: I01 | B50: DIRECCIÓN DE BIENESTAR, PARTICIPACIÓN CIUDADANA Y TERRITORIAL | C50: 02 | D50: 02 | E50: 02 | F50: 01 | G50: 01 | I50: I01 | J50: 112 | K50: Desarrollo comunitario | L50: Promoción a la participación comunitaria
C51: 02 | D51: 02 | E51: 02 | F51: 01 | G51: 02 | I51: I01 | J51: 112 | L51: Apoyo solidario
A52: A01 | B52: DIRECCION DE COMUNICACIÓN SOCIAL | C52: 01 | D52: 08 | E52: 03 | F52: 01 | G52: 03 | I52: A01 | J52: 103 | K52: Comunicación pública y fortalecimiento informativo | L52: Difusión y comunicación institucional
A53: N00 | B53: DIRECCIÓN DE DESARROLLO ECONÓMICO | C53: 03 | D53: 01 | E53: 02 | F53: 01 | G53: 06 | I53: N00 | J53: 140 | K53: Empleo | L53: Colocación de trabajadores desempleados
C54: 03 | D54: 01 | E54: 02 | F54: 01 | G54: 07 | I54: N00 | J54: 140 | L54: Fomento y apoyo para el autoempleo
C55: 03 | D55: 04 | E55: 02 | F55: 01 | G55: 02 | I55: N00 | J55: 131 | K55: Modernización industrial y del comercio | L55: Fortalecimiento a la micro y pequeña empresa
C56: 01 | D56: 05 | E56: 02 | F56: 06 | G56: 08 | I56: N00 | J56: 137 | K56: Consolidación de la administración pública de resultados | L56: Simplificación y modernización de la administración pública
C57: 03 | D57: 07 | E57: 01 | F57: 01 | G57: 01 | I57: N00 | J57: 149 | K57: Desarrollo integral del turísmo mexiquense | L57: Difusión y promoción del turismo mexiquense
C58: 03 | D58: 09 | E58: 03 | F58: 01 | G58: 04 | I58: N00 | J58: 133 | K58: Promoción Artesanal | L58: Promoción y fomento artesanal para el desarrollo del Estado de México
A59: F00 | B59: DIRECCIÓN DE DESARROLLO URBANO | C59: 01 | D59: 03 | E59: 08 | F59: 01 | G59: 04 | I59: F00 | J59: 123 | K59: Política territorial moderna y sostenible | L59: Planeación integral y concertada
C60: 01 | D60: 03 | E60: 08 | F60: 01 | G60: 07 | I60: F00 | J60: 123 | L60: Instrumentación urbana
C61: 02 | D61: 02 | E61: 01 | F61: 01 | G61: 06 | I61: F00 | J61: 123 | K61: Infraestructura de espacios públicos | L61: Participación comunitaria para el mejoramiento urbano
C62: 02 | D62: 02 | E62: 05 | F62: 01 | G62: 04 | I62: F00 | J62: 123 | K62: Vivienda para el bienestar | L62: Regularización de Predios
C63: 01 | D63: 08 | E63: 01 | F63: 03 | G63: 01 | I63: F00 | J63: 123 | K63: Proteccion juridica y registro de los bienes inmuebles | L63: Control de la funcion registral
C64: 01 | D64: 08 | E64: 01 | F64: 03 | G64: 01 | I64: F00 | J64: 123
C65: 01 | D65: 08 | E65: 01 | F65: 03 | G65: 01 | I65: F00 | J65: 123
A66: G00 | B66: MEDIO AMBIENTE Y ECOLOGIA | C66: 02 | D66: 01 | E66: 04 | F66: 01 | G66: 09 | I66: G00 | J66: 160 | K66: Protección integral del ambiente para el bienestar | L66: Concertación y participación ciudadana para la protección del ambiente
C67: 02 | D67: 01 | E67: 05 | F67: 01 | G67: 01 | I67: G00 | J67: 160 | K67: Manejo sustentable y conservación de los ecosistemas y la biodiversidad | L67: Promoción difusión de parques recreativos
C68: 02 | D68: 01 | E68: 05 | F68: 01 | G68: 02 | I68: G00 | J68: 160 | L68: Conservación ecológica sostenible y protección de la flora y fauna
C69: 03 | D69: 02 | E69: 02 | F69: 01 | G69: 03 | I69: G00 | J69: 160 | K69: Desarrollo Forestal | L69: Reforestación y restauración forestal integral
C70: 03 | D70: 02 | E70: 02 | F70: 01 | G70: 05 | I70: G00 | J70: 160 | L70: Protección de los ecosistemas forestales
A71: F00 | B71: DIRECCIÓN DE OBRAS PÚBLICAS | C71: 02 | D71: 01 | E71: 03 | F71: 01 | G71: 01 | I71: F00 | J71: 124 | K71: Manejo de aguas residuales, drenaje y alcantarillado | L71: Construcción de infraestructura para drenaje y alcantarillado
C72: 02 | D72: 02 | E72: 01 | F72: 01 | G72: 09 | I72: F00 | J72: 124 | K72: Infraestructura de espacios públicos | L72: Construcción de vialidades urbanas
C73: 02 | D73: 02 | E73: 01 | F73: 01 | G73: 10 | I73: F00 | J73: 124 | L73: Rehabilitación de Vialidades Urbanas
C74: 02 | D74: 02 | E74: 01 | F74: 01 | G74: 11 | I74: F00 | J74: 124 | L74: Equipamiento de vialidades urbanas
C75: 02 | D75: 02 | E75: 01 | F75: 01 | G75: 12 | I75: F00 | J75: 124 | L75: Construcción y ampliación de edificaciones urbanas
C76: 02 | D76: 02 | E76: 01 | F76: 01 | G76: 13 | I76: F00 | J76: 124 | L76: Rehabilitación de edificaciones urbanas
C77: 02 | D77: 02 | E77: 03 | F77: 01 | G77: 05 | I77: F00 | J77: 124 | K77: Manejo eficiente y sustentable del agua | L77: Construcción de infraestructura para agua potable
A78: A00 | B78: DIRECCION DE DIVERSIDAD SEXUAL | C78: 02 | D78: 06 | E78: 08 | F78: 05 | G78: 02 | I78: A00 | J78: 172 | K78: Igualdad de trato y oportunidades para la mujer, el hombre y personas LGBTTTIQ+ | L78: Cultura de igualdad entre la mujer y el hombre; y población LGBTIQ+, para la prevención de la violencia de género
C79: 03 | D79: 01 | E79: 02 | F79: 03 | G79: 01 | I79: A00 | J79: 172 | K79: Inclusión económica para la igualdad de género | L79: Capacitación de la mujer para el trabajo
C80: 03 | D80: 01 | E80: 02 | F80: 03 | G80: 02 | I80: A00 | J80: 172 | L80: Proyectos productivos para el desarrollo de la mujer
A81: O00 | B81: DIRECCIÓN DE EDUCACIÓN | C81: 02 | D81: 05 | E81: 01 | F81: 01 | G81: 10 | I81: O00 | J81: 141 | K81: Educación básica | L81: Apoyo municipal a la educación básica
C82: 02 | D82: 05 | E82: 02 | F82: 01 | G82: 05 | I82: O00 | J82: 141 | K82: Educación media superior | L82: Apoyo municipal a la educación media superior
C83: 02 | D83: 05 | E83: 03 | F83: 01 | G83: 05 | I83: O00 | J83: 141 | K83: Educación superior | L83: Apoyo municipal a la educación superior
C84: 02 | D84: 05 | E84: 05 | F84: 01 | G84: 01 | I84: O00 | J84: 141 | K84: Educación para adultos | L84: Alfabetización y educación básica para adultos
C85: 02 | D85: 05 | E85: 05 | F85: 01 | G85: 02 | I85: O00 | J85: 141 | L85: Formación para el trabajo
A86: J00 | B86: DIRECCIÓN DE GOBIERNO | C86: 01 | D86: 02 | E86: 04 | F86: 01 | G86: 02 | I86: J00 | J86: 102 | K86: Derechos Humanos | L86: Protección y defensa de los derechos humanos
C87: 01 | D87: 03 | E87: 02 | F87: 01 | G87: 04 | I87: J00 | J87: 144 | K87: Democracia y pluralidad politica | L87: Capacitacion para el desarrollo de la cultura politica
C88: 02 | D88: 04 | E88: 04 | F88: 01 | G88: 02 | I88: J00 | J88: 111 | K88: Nuevas Organizaciones de la Sociedad | L88: Participacion Ciudadana
C89: 02 | D89: 06 | E89: 07 | F89: 01 | G89: 01 | I89: J00 | J89: 151 | K89: Pueblos Indígenas | L89: Preservación y revalorización de usos y costumbres de los pueblos indigenas
C90: 01 | D90: 08 | E90: 01 | F90: 01 | G90: 01 | I90: J00 | J90: 112 | K90: Protección jurídica de las personas | L90: Asesoría jurídica para los mexiquenses
A91: V00 | B91: DIRECCIÓN DEL INSTITUTO DE LA MUJER E IGUALDAD DE GÉNERO | C91: 02 | D91: 06 | E91: 08 | F91: 05 | G91: 01 | I91: V00 | J91: 152 | K91: Igualdad de trato y oportunidades para la mujer y el hombre | L91: Coordinación institucional para la igualdad de género
C92: 02 | D92: 06 | E92: 08 | F92: 05 | G92: 02 | I92: V00 | J92: 152 | L92: Cultura de igualdad entre la mujer y el hombre; y población LGBTIQ+, para la prevención de la violencia de género
C93: 02 | D93: 06 | E93: 08 | F93: 05 | G93: 03 | I93: V00 | J93: 152 | L93: Apoyo social para el empoderamiento y bienestar económico de la mujer
C94: 03 | D94: 01 | E94: 02 | F94: 03 | G94: 01 | I94: V00 | J94: 152 | K94: Inclusión económica para la igualdad de género | L94: Capacitación de la mujer para el trabajo
C95: 01 | D95: 07 | E95: 01 | F95: 01 | G95: 02 | I95: Q00 | J95: 152 | K95: Seguridad pública | L95: Tecnología, inteligencia e investigación para la prevención y combate al delito | M95: Este es nuevo en INMUJERES
A96: M00 | B96: DIRECCIÓN DE CONSEJERÍA JURÍDICA | C96: 01 | D96: 03 | E96: 05 | F96: 01 | G96: 04 | I96: M00 | J96: 155 | K96: Asistencia jurídica al ejecutivo | L96: Asesoría jurídica al ayuntamiento
C97: 01 | D97: 08 | E97: 01 | F97: 01 | G97: 01 | I97: M00 | J97: 112 | K97: Protección jurídica de las personas | L97: Asesoría jurídica para los mexiquenses
A98: H00 | B98: DIRECCIÓN DE TIANGUIS, MERCADOS Y VÍA PÚBLICA | C98: 02 | D98: 02 | E98: 06 | F98: 01 | G98: 06 | I98: H00 | J98: 147 | K98: Modernización de los servicios comunales | L98: Coordinación para servicios de administración y mantenimiento de mercados y centrales de abasto
A99: F01 | B99: MOVILIDAD Y TRANSPORTE | C99: 02 | D99: 02 | E99: 01 | F99: 01 | G99: 11 | I99: F01 | J99: 154 | K99: Infraestructura de espacios públicos | L99: Equipamiento de vialidades urbanas | M99: Dejan de utilizar 0202010106 Participación comunitaria para el mejoramiento urbano
C100: 01 | D100: 07 | E100: 01 | F100: 01 | G100: 08 | I100: F01 | J100: 154 | K100: Seguridad pública | L100: Mantenimiento de los dispositivos para el control de tránsito y educación Vial
C101: 03 | D101: 05 | E101: 01 | F101: 01 | G101: 11 | I101: F01 | J101: 154 | K101: Modernización de la Movilidad y el transporte terrestre | L101: Apoyo municipal a las políticas para el desarrollo del transporte
C102: 01 | D102: 05 | E102: 02 | F102: 06 | G102: 02 | I102: F01 | J102: 154 | K102: Consolidación de la administración pública para resultados | L102: Capacitación y profesinalización para el desarrollo de personal
...

Sheet GACETA
A1: PROYECTO | B1: NOMBRE PROYECTO | C1: CONAC
A2: 0102040101 | B2: Investigación, capacitación, promoción y divulgación de los derechos humanos | C2: E
A3: 0102040102 | B3: Protección y defensa de los derechos humanos | C3: E
A4: 0102040103 | B4: Desarrollo institucional para los derechos humanos | C4: E
A5: 0103010101 | B5: Relaciones públicas | C5: P
A6: 0103010103 | B6: Audiencia pública y consulta popular | C6: E
A7: 0103020104 | B7: Capacitación para el desarrollo de la cultura política | C7: E
A8: 0103030101 | B8: Conservación, restauración y difusión del patrimonio cultural | C8: E
A9: 0103040101 | B9: Fiscalización, control y evaluación interna de la gestión pública | C9: O
A10: 0103040102 | B10: Participación social en la formulación, seguimiento, control y evaluación | C10: P
A11: 0103040203 | B11: Declaración de situación patrimonial, de interés y constancia de la declaración fiscal de los servidores públicos | C11: O
A12: 0103040205 | B12: Investigación de faltas administrativas | C12: O
... A186: 0402010104 | B186: Transferencias del ayuntamiento a organismos municipales | C186: O

Sheet GACETA 1
A1: PROYECTO | B1: NOMBRE PROYECTO | C1: JUSTIFICACIÓN
A2: 0102040101 | B2: Investigación, capacitación, promoción y divulgación de los derechos humanos | C2: Comprende las actividades de investigación y docencia, como mecanismos para fortalecer la capacitación, promoción, difusión y divulgación entre la sociedad civil y las instituciones públicas que consoliden el conocimiento en derechos humanos y los servicios que se ofrecen en la materia.
A3: 0102040102 | B3: Protección y defensa de los derechos humanos | C3: Contempla las acciones encaminadas a atender oportuna y diligentemente los actos u omisiones de naturaleza administrativa que impliquen presuntas violaciones a los derechos humanos integrando el desarrollo de supervisiones, revisiones y visitas a centros e instituciones del sistema penitenciario, sector salud, justicia, localidades de alto y muy alto nivel de marginación y zonas de tránsito de migrantes, emitiendo, si fuere necesario las recomendaciones conducentes a una mejor protección de los derechos humanos y brindando orientación y asesoría a la población.
A4: 0102040103 | B4: Desarrollo institucional para los derechos humanos | C4: Considera acciones de carácter administrativo y de servicios para dar soporte a las acciones sustantivas de atención a presuntas violaciones a los derechos humanos, potenciando los recursos humanos, técnicos y financieros.
A5: 0103010101 | B5: Relaciones públicas | C5: Contiene las acciones dirigidas a establecer y mantener sistemas de comunicación directa para el despacho de los asuntos de responsabilidad de los presidentes municipales.
A6: 0103010103 | B6: Audiencia pública y consulta popular | C6: Considera las acciones que permiten garantizar el derecho de la ciudadanía a ser escuchada por las autoridades del ayuntamiento y las que se refieren a promover la solicitud de opiniones, sugerencias y demandas de la población para ser incorporadas en los planes y programas de gobierno.
A7: 0103020104 | B7: Capacitación para el desarrollo de la cultura política | C7: Considera las acciones que contribuyan en la consolidación de una cultura política, democrática, participativa y corresponsable a través de la capacitación en la materia, orientada principalmente a la educación media superior y superior con contenidos en los diversos sectores de la sociedad, la integración social, la solidaridad y la identidad mexiquense, coadyuvando a fortalecer la relación gobierno-sociedad y reconstruir el tejido social.
A8: 0103030101 | B8: Conservación, restauración y difusión del patrimonio cultural | C8: Engloba las actividades enfocadas a restaurar, conservar y mantener en óptimas condiciones de uso, el patrimonio histórico, artístico y cultural de la entidad, con la finalidad de difundirlo entre la población.
A9: 0103040101 | B9: Fiscalización, control y evaluación interna de la gestión pública | C9: Comprende las acciones de dirección para vigilar, fiscalizar, controlar y evaluar la gestión de los servidores públicos en la administración pública municipal y el cumplimiento de sus obligaciones derivadas de los convenios suscritos con los gobiernos federal, estatal y municipales, así como la inspección, vigilancia y evaluación de los órganos internos de control de las dependencias y entidades públicas municipales.
A10: 0103040102 | B10: Participación social en la formulación, seguimiento, control y evaluación interna de obras, programas y servicios públicos | C10: Comprende las acciones para promover la participación organizada de la ciudadanía en la formulación, seguimiento, control y evaluación de programas de la administración pública municipal y en particular en lo relativo a obras y servicios de mayor impacto, como apoyo al diseño de las políticas públicas; asimismo incluye las acciones relacionadas con las autoridades auxiliares municipales.
A11: 0103040201 | B11: Prevención, detección, disuasión, sanción y combate a la corrupción | C11: Incluye las acciones y procesos orientados al establecimiento y operación del Sistema Anticorrupción del Estado de México y Municipios, así como aquellas destinadas a instituir los principios, bases generales y procedimientos para la coordinación entre las autoridades del Estado de México y los municipios, con el objeto de fiscalizar y controlar los recursos públicos; promover la transparencia y rendición de cuentas; prevenir, investigar, resolver y en su caso, sancionar las faltas administrativas, hechos de corrupción y conflicto de intereses, en congruencia con el Sistema Estatal Anticorrupción.
A12: 0103040202 | B12: Responsabilidades administrativas | C12: Comprende el conjunto de acciones orientadas a procurar que el desempeño de los servidores públicos se apegue a los principios rectores y directrices de su actuación, así como a las acciones que permitan llevar a cabo la substanciación de procedimientos derivados de hechos irregulares y actos de corrupción de los servidores públicos, para constituir las responsabilidades administrativas y la resolución de estos por la autoridad competente.
... A192: 0404010102 | B192: Pasivos por contratación de créditos | C192: Integra las acciones que se realizan los ayuntamientos con el objeto de atender el pasivo de los créditos de corto plazo pagaderos en el mismo año, créditos para organismos descentralizados, vencimientos y refinanciamiento.

Sheet Hoja3
A2: 102040101 | B2: 102040101 | C2: =A2-B2 -> 0
A3: 102040102 | B3: 102040102 | C3: =A3-B3 -> 0
A4: 102040103 | B4: 102040103 | C4: =A4-B4 -> 0
A5: 103010101 | B5: 103010101 | C5: =A5-B5 -> 0
A6: 103010103 | B6: 103010103 | C6: =A6-B6 -> 0
A7: 103020104 | B7: 103020104 | C7: =A7-B7 -> 0
A8: 103030101 | B8: 103030101 | C8: =A8-B8 -> 0
A9: 103040101 | B9: 103040101 | C9: =A9-B9 -> 0
A10: 103040102 | B10: 103040102 | C10: =A10-B10 -> 0
A11: 103040201 | C11: =A11-B11 -> 103040201
A12: 103040202 | C12: =A12-B12 -> 103040202
A13: 103040203 | B13: 103040203 | C13: =A13-B13 -> 0
A14: 103040205 | B14: 103040205 | C14: =A14-B14 -> 0
A15: 103050104 | B15: 103050104 | C15: =A15-B15 -> 0
A16: 103080104 | B16: 103080104 | C16: =A16-B16 -> 0
A17: 103080107 | B17: 103080107 | C17: =A17-B17 -> 0
A18: 103090104 | B18: 103090104 | C18: =A18-B18 -> 0
A19: 10309020101 | B19: 103090201 | C19: =A19-B19 -> 10205929900
A20: 103090301 | B20: 103090301 | C20: =A20-B20 -> 0
A21: 104010103 | B21: 104010103 | C21: =A21-B21 -> 0
A22: 105020105 | B22: 105020105 | C22: =A22-B22 -> 0
A23: 105020201 | B23: 105020201 | C23: =A23-B23 -> 0
A24: 105020209 | B24: 105020209 | C24: =A24-B24 -> 0
... A40: 107010103 | B40: 107010103 | C40: =A40-B40 -> 0
A41: 107010105 | C41: =A41-B41 -> 107010105
A42: 107010108 | C42: =A42-B42 -> 107010108
A43: 107020101 | B43: 107020101 | C43: =A43-B43 -> 0
A44: 107020103 | C44: =A44-B44 -> 107020103
A45: 107020102 | B45: 107020102 | C45: =A45-B45 -> 0
B46: 107020103 | C46: =A46-B46 -> -107020103
A47: 107020104 | B47: 107020104 | C47: =A47-B47 -> 0
A48: 107020105 | B48: 107020105 | C48: =A48-B48 -> 0
A49: 107020106 | B49: 107020106 | C49: =A49-B49 -> 0
A50: 107040101 | B50: 107040101 | C50: =A50-B50 -> 0
A51: 108010101 | B51: 108010101 | C51: =A51-B51 -> 0
A52: 108010102 | B52: 108010102 | C52: =A52-B52 -> 0
A53: 108010201 | B53: 108010201 | C53: =A53-B53 -> 0
A54: 108010301 | B54: 108010301 | C54: =A54-B54 -> 0
A55: 108020101 | B55: 108020101 | C55: =A55-B55 -> 0
A56: 108030103 | B56: 108030103 | C56: =A56-B56 -> 0
A57: 108040101 | B57: 108040101 | C57: =A57-B57 -> 0
A58: 108050103 | B58: 108050103 | C58: =A58-B58 -> 0
... A191: 402010104 | B191: 402010104 | C191: =A191-B191 -> 0
A192: 404010101 | C192: =A192-B192 -> 404010101
A193: 404010102 | C193: =A193-B193 -> 404010102

Sheet GACETA 2
A1: 1111 | B1: 1111 | C1: =A1-B1 -> 0 | D1: Dietas. Asignación para el pago de remuneraciones a los CC. Diputados de la H. Legislatura Local, y en el caso de los municipios a los integrantes del H. Ayuntamiento
A2: 1121 | B2: 1121 | C2: =A2-B2 -> 0 | D2: Haberes. Asignaciones para remuneraciones al personal que desempeña sus servicios en el ejercicio, fuerza aérea y armada nacionales.
A3: 1131 | B3: 1131 | C3: =A3-B3 -> 0 | D3: Sueldo base. Remuneración al servidor público de base o de confianza que preste sus servicios al Poder Legislativo, Ejecutivo, Judicial o algún Organismo Autónomo o Descentralizado. Los montos que importen estas remuneraciones serán fijados de acuerdo con el Catálogo de Puestos del Gobierno Estatal y los tabuladores vigentes autorizados por la Secretaría o su equivalente, en el caso de los municipios se refiere a las remuneraciones al servidor público de base y no sindicalizado, que presta sus servicios en la Administración Pública Municipal, acorde con el marco jurídico.
A4: 1132 | B4: 1132 | C4: =A4-B4 -> 0 | D4: Otro sueldo magisterio. Remuneración que recibe el docente que cubre dos plazas, de conformidad con lo dispuesto en el Acuerdo que fija el Esquema de Compatibilidad en Horario y Funciones de los Servidores Públicos de los Sectores Central y Auxiliar del Poder Ejecutivo.
A5: 1133 | B5: 1133 | C5: =A5-B5 -> 0 | D5: Hora clase. Sueldo base para docentes que laboran como profesores horas clase, con base en el convenio laboral correspondiente
A6: 1134 | B6: 1134 | C6: =A6-B6 -> 0 | D6: Carrera magisterial. Percepción para docentes cuando cumplen los requisitos establecidos para el ingreso y promoción de carrera magisterial.
A7: 1135 | B7: 1135 | C7: =A7-B7 -> 0 | D7: Carrera docente. Percepción para docentes de educación media superior y superior, cuando cumplen los requisitos establecidos para el ingreso y promoción de carrera docente.
A8: 1141 | B8: 1141 | C8: =A8-B8 -> 0 | D8: Remuneraciones por adscripción laboral en el extranjero. Asignaciones destinadas a cubrir las remuneraciones del personal que labora en representaciones estatales y municipales en el extranjero. Incluye las variaciones del factor de ajuste: importancia relativa de la oficina de adscripción; costo de la vida en el lugar de adscripción y condiciones de dificultad de la vida en cada adscripción. Dichas remuneraciones son cubiertas exclusivamente al personal que labore en esas representaciones en el exterior.
A9: 1211 | B9: 1211 | C9: =A9-B9 -> 0 | D9: Honorarios asimilables al salario. Asignaciones destinadas para cubrir el pago por la prestación de servicios contratados con personas físicas, para la realización de trabajos determinados que correspondan a la especialidad.
A10: 1221 | B10: 1221 | C10: =A10-B10 -> 0 | D10: Sueldo por Interinato. Sueldo del personal que sustituye temporalmente a servidores públicos de carácter permanente, con permiso para ausentarse de sus funciones de acuerdo a la normatividad vigente, así como el Sueldo para el personal que sustituye temporalmente a docentes por estado de gravidez, con licencia prejubilatoria, becados o comisionados, o con permiso especial, de acuerdo a la normatividad establecida.
A11: 1222 | B11: 1222 | C11: =A11-B11 -> 0 | D11: Sueldos y salarios compactados al personal eventual. Sueldo que se otorga a profesionistas, técnicos, expertos o peritos contratados por obra o tiempo determinado, que invariablemente no podrá ser mayor a seis meses. No se podrá contratar personal bajo esta modalidad para realizar funciones administrativas, apoyo secretarial, chofer, mantenimiento general, limpieza y similares. La remuneración que se pague por concepto de contrato por obra o tiempo determinado, no podrá exceder a lo estipulado para una labor similar establecida en el Catálogo de Puestos y en el tabulador de sueldo vigente.
A12: 1223 | B12: 1223 | C12: =A12-B12 -> 0 | D12: Becas para médicos residentes. Percepción económica que de acuerdo al Sistema nacional de residencias médicas se asigna para formar a médicos en alguna especialidad, mismos que deben cubrir con los requerimientos establecidos en la norma 090 SSA1 1994 (Norma oficial mexicana para la organización y funcionamiento de residencias médicas y desarrollo); esta formación especializada se llevara a cabo en instituciones públicas del sector salud, establecidas en el estado.
... A163: 3371 | B163: 3371 | C163: =A163-B163 -> 0 | D163: Servicios de protección y seguridad. Asignaciones destinadas a la realización de programas, investigaciones, acciones y actividades en materia de seguridad pública y nacional, en cumplimiento de funciones y actividades en oficiales, cuya realización implique riesgo, urgencia y confidencialidad extrema. Incluye los recursos para la contratación temporal de personas y la adquisición de materiales y servicios necesarios para tales efectos. En ningún caso se podrán sufragar con cargo a esta partida, erogaciones previstas en otros capítulos, conceptos y partidas de este clasificador cuando corresponda a programas, investigaciones, acciones y actividades diferentes de los especiales sujetos a esta partida.
A164: 3381 | C164: =A164-B164 -> 3381
A165: 3391 | C165: =A165-B165 -> 3391
A166: 3411 | C166: =A166-B166 -> 3411 | D166: Servicios de vigilancia. Asignaciones para cubrir el pago de los servicios de vigilancia brindados por un prestador de servicios independiente, por concepto de vigilancia y protección de bienes muebles e inmuebles, destinados a oficinas administrativas
A167: 3421 | B167: 3381 | C167: =A167-B167 -> 40 | D167: e instalaciones operativas.
A168: 3431 | B168: 3391 | C168: =A168-B168 -> 40 | D168: Servicios profesionales. Asignaciones destinadas a cubrir el costo de los servicios profesionales por concepto de estudios e investigaciones de carácter socioeconómico, científico, jurídico, diseño de estrategias de mercadotecnia, análisis de mercado, entre otros.
A169: 3441 | C169: =A169-B169 -> 3441 | D169: Servicios bancarios y financieros. Asignaciones destinadas a cubrir el pago de servicios bancarios y financieros, tales como: comisiones, intereses por adeudos, descuentos e intereses devengados con motivo de la colocación de empréstitos, certificados, traslados de valores y otras obligaciones. Incluye los gastos por la realización de avalúo de bienes muebles e
A170: 3451 | B170: 3411 | C170: =A170-B170 -> 40 | D170: inmuebles o por justipreciación, se excluyen las comisiones por devolución de cheques.
A171: 3461 | B171: 3421 | C171: =A171-B171 -> 40 | D171: Servicios de cobranza, investigación crediticia y similar. Asignaciones destinadas a cubrir los gastos por servicios de cobranza, investigación crediticia y recopilación de información sobre solvencia financiera de personas o negocios.
A172: 3471 | B172: 3431 | C172: =A172-B172 -> 40 | D172: Gastos inherentes a la recaudación. Asignaciones destinadas a cubrir el pago de servicios financieros por situación y traslado de fondos del erario y otros gastos inherentes a la recaudación fiscal, incluida la guarda y custodia de fondos y valores.
A173: 3481 | C173: =A173-B173 -> 3481 | D173: Seguros de responsabilidad patrimonial y fianzas. Asignaciones destinadas a cubrir las primas con cargo al presupuesto autorizado de los entes públicos, por concepto de la contratación de seguro de responsabilidad patrimonial del Estado, que permita con la suma asegurada cubrir el monto equivalente a las indemnizaciones y que corresponderán a la reparación integral del daño y, en su caso, por el daño personal y moral, que se ocasionen como consecuencia de la actividad administrativa irregular del Estado. Excluye el monto de las erogaciones que resulten por insuficiencia de la suma asegurada contra el costo de la indemnización y, en su caso, los deducibles correspondientes. Estas erogaciones deberán cubrirse con cargo a la partida: Otros gastos por responsabilidades, de este clasificador.
A174: 3491 | C174: =A174-B174 -> 3491
A175: 3511 | C175: =A175-B175 -> 3511
A176: 3512 | B176: 3441 | C176: =A176-B176 -> 71
A177: 3521 | C177: =A177-B177 -> 3521 | D177: Seguros y fianzas. Asignaciones destinadas a cubrir las primas por concepto de seguros contra robos, incendios y demás riesgos o contingencias a que pueden estar sujetos los bienes muebles e inmuebles, incluidos los bienes informáticos y todo
A178: 3531 | B178: 3451 | C178: =A178-B178 -> 80 | D178: tipo de valores registrados en los activos. Así como para cubrir el importe de las fianzas de fidelidad de los servidores públicos que por sus funciones lo requieran. Incluye el pago de deducibles y coaseguros.
A179: 3532 | B179: 3461 | C179: =A179-B179 -> 71 | D179: Almacenaje, embalaje y envase. Asignaciones destinadas a cubrir el costo de los servicios de almacenamiento, embalaje, desembalaje, envase y desenvase de toda clase de objetos, artículos, materiales, mobiliario, entre otros.
A180: 3541 | B180: 3471 | C180: =A180-B180 -> 70 | D180: Fletes y maniobras. Asignaciones destinadas a cubrir el costo de traslado, maniobras, embarque y desembarque de animales, plantas, maquinaria y de toda clase de objetos, artículos, materiales, mobiliario, entre otros.
A181: 3551 | C181: =A181-B181 -> 3551 | D181: Comisiones por ventas. Asignaciones destinadas a cubrir el pago de comisiones a personas físicas, ya sean: profesionistas, técnico, expertos o peritos, así como a las personas morales, con las cuáles se tenga celebrado contrato respectivo, por los servicios de venta prestados a los entes públicos.
A182: 3561 | B182: 3481 | C182: =A182-B182 -> 80
A183: 3571 | C183: =A183-B183 -> 3571 | D183: Servicios financieros, bancarios y comerciales integrales. Otros servicios financieros, bancarios y comerciales no previstos en las demás partidas anteriores de este concepto. Incluye casetas telefónicas sin operar las redes alambicas, recepción de llamadas telefónicas y promoción por teléfono de bienes y servicios, de recepción de llamadas telefónicas en nombre de los
A184: 3581 | C184: =A184-B184 -> 3581 | D184: clientes. Excluye: cálculo de impuestos y preparación de formatos para la declaración de impuestos, al procesamiento de datos, a la operación de redes de telefonía tradicional, venta de productos por teléfono, y a los servicios de correo electrónico.
A185: 3591 | B185: 3491 | C185: =A185-B185 -> 100
A186: 3611 | C186: =A186-B186 -> 3611 | D186: Reparación y mantenimiento menor de inmuebles. Asignación para cubrir los gastos derivados de reparaciones y mantenimientos menores de edificios, locales, terrenos y predios propiedad del Estado y de los Municipios, así como de los inmuebles en arrendamiento destinados a cubrir la función o los servicios públicos. Estos gastos no implican una modificación estructural del inmueble ni aumentan significativamente su valor contable, y se consideran necesarios para la conservación operativa y funcional de los bienes. Incluye también los deducibles de seguros por daños a inmuebles y servicios específicos de conservación no capitalizables.
A187: 3612 | C187: =A187-B187 -> 3612
A188: 3613 | B188: 3511 | C188: =A188-B188 -> 102
A189: 3621 | C189: =A189-B189 -> 3621 | D189: Adaptación de locales, almacenes, bodegas y edificios. Asignación para cubrir el pago de la mano de obra y materiales para la adaptación de locales, terrenos y predios de propiedades oficiales, así como de los inmuebles en arrendamiento destinados a cubrir la función o los servicios públicos. Cuando la adaptación modifique la estructura original o aumente el valor del inmueble se deberá considerar como obra pública.
A190: 3631 | B190: 3512 | C190: =A190-B190 -> 119
A191: 3641 | C191: =A191-B191 -> 3641 | D191: Reparación, mantenimiento e instalación de mobiliario y equipo de oficina. Asignaciones destinadas a cubrir el costo de los servicios de mantenimiento, reparación e instalación de toda clase de mobiliario y equipo de administración tales como:
A192: 3651 | B192: 3521 | C192: =A192-B192 -> 130 | D192: escritorios, sillas, sillones, archiveros, máquinas de escribir, calculadoras, fotocopiadoras, entre otros.
A193: 3661 | C193: =A193-B193 -> 3661 | D193: Reparación, instalación y mantenimiento de bienes informáticos, microfilmación y tecnologías de la información. Asignaciones destinadas a cubrir el costo de los servicios que se contraten con terceros para el mantenimiento, reparación e instalación de bienes informáticos, microfilmación y tecnologías de la información, tales como: computadoras, impresoras, dispositivos de seguridad, reguladores, fuentes de potencia ininterrumpida, redes informáticas internas y sistemas de telecomunicaciones,
A194: 3691 | C194: =A194-B194 -> 3691 | D194: entre otros. Incluye el costo de las instalaciones menores especializadas.
A195: 3711 | B195: 3531 | C195: =A195-B195 -> 180
A196: 3721 | C196: =A196-B196 -> 3721
A197: 3731 | C197: =A197-B197 -> 3731
A198: 3741 | B198: 3532 | C198: =A198-B198 -> 209 | D198: Reparación y mantenimiento para equipo y redes de tele y radio transmisión. Asignaciones destinadas a cubrir el pago de mano de obra y materiales requeridos en la reparación y mantenimiento del equipo y líneas de tele y radio transmisión.
A199: 3751 | B199: 3541 | C199: =A199-B199 -> 210 | D199: Reparación, instalación y mantenimiento de equipo médico y de laboratorio. Asignaciones destinadas a cubrir el costo de los servicios de reparación, instalación, mantenimiento y conservación de equipo médico especializado y equipo de laboratorio, cuando se efectúen por cuenta de terceros. Incluye el costo de las instalaciones menores especializadas.
A200: 3752 | B200: 3551 | C200: =A200-B200 -> 201 | D200: Reparación y mantenimiento de vehículos terrestres, aéreos y lacustres. Asignación para cubrir el costo de la reparación y mantenimiento de vehículos oficiales.
A201: 3753 | B201: 3561 | C201: =A201-B201 -> 192 | D201: Reparación y mantenimiento de equipos de seguridad y defensa. Asignaciones destinadas a cubrir los gastos por servicios de reparación y mantenimiento del equipo de seguridad y defensa, tales como armas cortas, armas largas, equipo anti motín, así
A202: 3761 | C202: =A202-B202 -> 3761 | D202: como de equipos que se utilicen para la salvaguarda de la población.
A203: 3762 | C203: =A203-B203 -> 3762 | D203: Reparación, instalación y mantenimiento de maquinaria, equipo industrial y diverso. Asignaciones destinadas a cubrir el costo de los servicios de reparación, mantenimiento, instalación y conservación de la maquinaria, equipo industrial y equipos contra
A204: 3763 | B204: 3571 | C204: =A204-B204 -> 192 | D204: incendio, entre otros; así como: equipo topográfico, tractores, palas mecánicas, dragas, fertilizadoras, equipo especializado instalado en inmuebles, obras de arte, entre otros, cuando se efectúen por cuenta de terceros.
A205: 3771 | C205: =A205-B205 -> 3771 | D205: Servicios de lavandería, limpieza e higiene. Asignaciones destinadas a cubrir los gastos por servicios de: lavandería, limpieza, desinfección e higiene en los bienes muebles e inmuebles oficina propiedad o al cuidado de los entes públicos. Incluye los costos de recolección, traslado, tratamiento y disposición final de residuos y desechos tóxicos, limpieza de carreteras y
A206: 3781 | B206: 3581 | C206: =A206-B206 -> 200 | D206: caminos, entre otros.
A207: 3791 | B207: 3591 | C207: =A207-B207 -> 200 | D207: Servicios de fumigación. Asignaciones destinadas a cubrir los gastos por servicios de: fumigación y jardinería de los bienes muebles e inmuebles oficiales.
A208: 3811 | C208: =A208-B208 -> 3811 | D208: Gastos de publicidad y propaganda. Asignación para contratar servicios de publicidad y difusión en medios masivos de comunicación, que permitan dar a conocer el quehacer de la administración pública estatal, así como los bienes y servicios
A209: 3821 | B209: 3611 | C209: =A209-B209 -> 210 | D209: públicos que se prestan; publicación y difusión masiva a través de televisión abierta y restringida, radio, cine, prensa, encartes, espectaculares, para buses, Internet y medios electrónicos e impresos internacionales.
A210: 3822 | C210: =A210-B210 -> 3822 | D210: Publicaciones oficiales. Asignaciones destinadas a cubrir el costo de los servicios de publicación de documentos oficiales tales como: programas sectoriales, regionales y especiales, informes de labores, manuales de organización, de procedimientos y de servicios al público, decretos, acuerdos, convenios, oficios, circulares, programas de adquisiciones, instructivos, libros, revistas, folletos, boletines, posters, trípticos, edictos, informes, así como la información en materia de licitaciones públicas y
A211: 3831 | C211: =A211-B211 -> 3831 | D211: subastas para la adquisición o enajenación, bases y convocatorias.
A212: 3841 | B212: 3612 | C212: =A212-B212 -> 229
A213: 3851 | B213: 3613 | C213: =A213-B213 -> 238 | D213: Costos de estudios, producción y post-producción. Asignaciones destinadas a cubrir el costo de los estudios necesarios para el desarrollo de mensajes y diseño de conceptualización de los mismos, preproducción, producción, post-producción y copiado.
A214: 3911 | B214: 3621 | C214: =A214-B214 -> 290 | D214: Gastos de publicidad en materia comercial. Asignaciones destinadas a cubrir el costo de la publicidad y difusión comercial de bienes y servicios que generan un ingreso para las unidades ejecutoras de la administración pública.
A215: 3921 | B215: 3631 | C215: =A215-B215 -> 290 | D215: Servicios de creatividad, preproducción y producción de publicidad, excepto Internet. Asignaciones destinadas a cubrir los gastos por diseño y conceptualización de campañas de comunicación, preproducción, producción, post-producción y copiado.
A216: 3922 | B216: 3641 | C216: =A216-B216 -> 281 | D216: Servicios de fotografía. Asignación para cubrir el pago por servicios de revelado, impresión y reproducción fotográfica.
A217: 3931 | B217: 3651 | C217: =A217-B217 -> 280 | D217: Servicios de cine y grabación. Asignación para cubrir el pago por servicios de producción y grabaciones fílmicas.
A218: 3941 | B218: 3661 | C218: =A218-B218 -> 280 | D218: Servicios de creación y difusión de contenido a través de Internet. Asignaciones destinadas a cubrir el gasto por creación, difusión y transmisión de contenidos de interés general o específico a través de internet.
A219: 3942 | B219: 3691 | C219: =A219-B219 -> 251 | D219: Otros servicios de información. Asignaciones destinadas a cubrir el costo de la contratación de servicios profesionales con personas físicas o morales, por concepto de monitoreo de información en medios masivos de comunicación, de las actividades
A220: 3951 | C220: =A220-B220 -> 3951 | D220: de los entes públicos, que no se encuentren comprendidas en las demás partidas de este Capítulo.
A221: 3961 | B221: 3711 | C221: =A221-B221 -> 250 | D221: Transportación aérea. Asignaciones destinadas a cubrir los gastos por concepto de traslado de personal por vía aérea que utilices este medio de transporte en cumplimiento de sus funciones públicas. Incluye gastos por traslado de presos, reparto y
A222: 3971 | C222: =A222-B222 -> 3971 | D222: entrega de mensajería y excluye los pasajes por concepto de becas y arrendamiento de equipo de transporte.
A223: 3981 | B223: 3721 | C223: =A223-B223 -> 260 | D223: Gastos de traslado por vía terrestre. Asignación para cubrir el transporte en el país o en el extranjero por el traslado de personal por vía terrestre urbano y suburbano, interurbano y rural, taxis y ferroviario en cumplimiento de sus funciones públicas.
A224: 3982 | B224: 3731 | C224: =A224-B224 -> 251 | D224: Pasajes marítimos, lacustres y fluviales. Asignaciones destinadas a cubrir los gastos por concepto de traslado de personal por
A225: 3983 | C225: =A225-B225 -> 3983 | D225: vía marítima, lacustre y fluvial en cumplimiento de sus funciones públicas. Incluye gastos por traslado de presos reparto y entrega de mensajería y excluye los pasajes por concepto de becas y arrendamiento de equipo de transporte.
A226: 3991 | B226: 3741 | C226: =A226-B226 -> 250 | D226: Autotransporte. Asignaciones destinadas al autotransporte tanto de mercancías que no requieren de equipo especializado y que normalmente se transportan en camiones de caja o en contenedores, como de aquellos productos que por sus
A227: 3992 | C227: =A227-B227 -> 3992 | D227: características (líquidos, gases, etc.) requieren ser transportados en camiones con equipo especializado.
A228: 3993 | B228: 3751 | C228: =A228-B228 -> 242 | D228: Gastos de alimentación en territorio nacional. Asignación sujeta a comprobación de acuerdo a la normatividad en la materia, para cubrir la alimentación de los servidores públicos que por comisiones deban asistir a lugares distintos a los de su
A229: 3994 | C229: =A229-B229 -> 3994 | D229: adscripción.
A230: 3995 | B230: 3752 | C230: =A230-B230 -> 243 | D230: Gastos de hospedaje en territorio nacional. Asignación sujeta a comprobación de acuerdo a la normatividad en la materia, para cubrir el hospedaje de los servidores públicos que por comisiones deban asistir a lugares distintos a los de su adscripción.
A231: 3996 | B231: 3753 | C231: =A231-B231 -> 243 | D231: Gastos por arrendamiento de vehículos en territorio nacional. Asignación sujeta a comprobación de acuerdo a la normatividad en la materia, para cubrir el arrendamiento de vehículos para los servidores públicos que por comisiones deban hacer uso de estos servicios para asistir a lugares distintos a los de su adscripción.
A232: 3997 | C232: =A232-B232 -> 3997 | D232: Gastos de alimentación en el extranjero. Asignación sujeta a comprobación de acuerdo a la normatividad en la materia, para
A233: 3998 | B233: 3761 | C233: =A233-B233 -> 237 | D233: cubrir la alimentación de los servidores públicos que por comisiones deban asistir al extranjero para cumplir con funciones propias de su actividad.
A234: 4111 | C234: =A234-B234 -> 4111 | D234: Gastos de hospedaje en el extranjero. Asignación sujeta a comprobación de acuerdo a la normatividad en la materia, para
A235: 4121 | B235: 3762 | C235: =A235-B235 -> 359 | D235: cubrir el hospedaje de los servidores públicos que por comisiones deban asistir al extranjero para cumplir con funciones propias de su actividad.
A236: 4131 | B236: 3763 | C236: =A236-B236 -> 368 | D236: Gastos por arrendamiento de vehículos en el extranjero. Asignación sujeta a comprobación de acuerdo a la normatividad en la materia, para cubrir el arrendamiento de vehículos para los servidores públicos que por comisiones deban asistir al
A237: 4141 | C237: =A237-B237 -> 4141 | D237: extranjero para cumplir con funciones propias de su actividad.
A238: 4151 | C238: =A238-B238 -> 4151 | D238: Gastos de instalación y traslado de menaje. Asignaciones destinadas a cubrir los gastos que ocasione la instalación del personal civil o militar, diplomático y consular al servicio de los entes públicos, cuando en el desempeño de funciones oficiales
A239: 4161 | B239: 3771 | C239: =A239-B239 -> 390 | D239: dentro o fuera del país, se requiera su permanencia fuera de su residencia en forma transitoria o permanente, incluyendo, en su caso, el traslado de menaje de casa. Excluye los pagos de viáticos y pasajes.
A240: 4171 | C240: =A240-B240 -> 4171 | D240: Servicios integrales de traslado y viáticos. Asignaciones destinadas a cubrir las erogaciones que realicen los entes públicos por la contratación con personas físicas y morales de servicios diversos cuya desagregación no es realizable en forma específica para cada una de las partidas de gasto de este concepto, por tratarse de una combinación de servicios relacionados
A241: 4181 | B241: 3781 | C241: =A241-B241 -> 400 | D241: cuya prestación se estipula en forma integral y que en términos del costo total resulta en condiciones menos onerosas para los entes públicos.
A242: 4191 | B242: 3791 | C242: =A242-B242 -> 400 | D242: Otros servicios de traslado y hospedaje. Asignaciones destinadas a cubrir el pago de servicios básicos distintos de los señalados en las partidas de este concepto, tales como pensiones de estacionamiento, entre otros, requeridos en el
A243: 4211 | C243: =A243-B243 -> 4211 | D243: desempeño de funciones oficiales.
A244: 4221 | C244: =A244-B244 -> 4221 | D244: Gastos de ceremonial. Asignaciones destinadas a cubrir los servicios integrales que se contraten con motivo de organización y ejecución de recepciones de los titulares de los entes públicos al personal del Cuerpo Diplomático acreditado y personalidades nacionales o extranjeras residentes o de visita en el territorio nacional, así como para cubrir dichos gastos en eventos que se realicen en el extranjero; siempre y cuando que por tratarse de servicios integrales no puedan desagregarse en otras partidas de los capítulos 2000 Materiales y Suministros y 3000 Servicios Generales. Incluye bienes y servicios tales
A245: 4231 | C245: =A245-B245 -> 4231 | D245: como: organización y ejecución de recepciones, adornos, escenografía, entre otros.
A246: 4241 | B246: 3811 | C246: =A246-B246 -> 430
A247: 4242 | C247: =A247-B247 -> 4242 | D247: Gastos de ceremonias oficiales y de orden social. Asignaciones destinadas a cubrir los gastos que se originen con motivo de la celebración de actos conmemorativos y de orden social, tales como la realización de ceremonias patrióticas y oficiales,
A248: 4251 | B248: 3821 | C248: =A248-B248 -> 430 | D248: desfiles, adquisición de ofrendas florales y luctuosas, renta de sillas, lonas y sonido, entre otros, en los que participan el Titular del Ejecutivo Estatal o Municipal, funcionarios y servidores públicos.
A249: 4311 | B249: 3822 | C249: =A249-B249 -> 489 | D249: Espectáculos cívicos y culturales. Asignación para cubrir el desarrollo de espectáculos cívicos y culturales para fomentar la identidad entre la ciudadanía.
A250: 4321 | C250: =A250-B250 -> 4321 | D250: Congresos y convenciones. Asignaciones destinadas a cubrir el costo del servicio integral que se contrate con personas físicas o morales para la celebración de congresos, convenciones, seminarios, simposios y cualquier otro tipo de foro análogo o de características similares, que se organicen en cumplimiento de lo previsto en los programas o con motivo de las atribuciones propias, siempre y cuando no puedan desagregarse en otras partidas de los capítulos 2000 Materiales y Suministros y 3000
...

Sheet Hoja1
A2: 1111 | B2: 1111 | C2: =A2-B2 -> 0
A3: 1121 | B3: 1121 | C3: =A3-B3 -> 0
A4: 1131 | B4: 1131 | C4: =A4-B4 -> 0
A5: 1132 | B5: 1132 | C5: =A5-B5 -> 0
A6: 1133 | B6: 1133 | C6: =A6-B6 -> 0
A7: 1134 | B7: 1134 | C7: =A7-B7 -> 0
A8: 1135 | B8: 1135 | C8: =A8-B8 -> 0
A9: 1141 | B9: 1141 | C9: =A9-B9 -> 0
A10: 1211 | B10: 1211 | C10: =A10-B10 -> 0
A11: 1221 | B11: 1221 | C11: =A11-B11 -> 0
A12: 1222 | B12: 1222 | C12: =A12-B12 -> 0
A13: 1223 | B13: 1223 | C13: =A13-B13 -> 0
... A426: 7311 | B426: 7311 | C426: =A426-B426 -> 0
A427: 7321 | C427: =A427-B427 -> 7321
A428: 7331 | B428: 7331 | C428: =A428-B428 -> 0
A429: 7341 | B429: 7341 | C429: =A429-B429 -> 0
A430: 7351 | B430: 7351 | C430: =A430-B430 -> 0
A431: 7391 | B431: 7391 | C431: =A431-B431 -> 0
A432: 7392 | B432: 7392 | C432: =A432-B432 -> 0
A433: 7393 | B433: 7393 | C433: =A433-B433 -> 0
A434: 7411 | B434: 7411 | C434: =A434-B434 -> 0
A435: 7421 | B435: 7421 | C435: =A435-B435 -> 0
A436: 7431 | B436: 7431 | C436: =A436-B436 -> 0
A437: 7441 | B437: 7441 | C437: =A437-B437 -> 0
A438: 7451 | B438: 7451 | C438: =A438-B438 -> 0
A439: 7461 | B439: 7461 | C439: =A439-B439 -> 0
... A499: 9912 | B499: 9912 | C499: =A499-B499 -> 0

Sheet GACETA 3
A2: Clave | B2: Dependencia General | E2: Clave | F2: Dependencia Auxiliar
A3: A00 | B3: PRESIDENCIA | E3: 100 | F3: Secretaría Particular
A4: A01 | B4: Comunicación Social | E4: 101 | F4: Secretaría Técnica
A5: A02 | B5: Derechos Humanos | E5: 102 | F5: Derechos Humanos
A6: B00 | B6: SINDICATURAS | E6: 103 | F6: Comunicación Social
A7: B01 | B7: Sindicatura I | E7: 104 | F7: Seguridad Pública
A8: B02 | B8: Sindicatura II | E8: 105 | F8: Coordinación Municipal de Protección Civil
A9: C00 | B9: REGIDURIAS | E9: 106 | F9: Cuerpo de Bomberos
A10: C01 | B10: Regiduría I | E10: 107 | F10: Urbanismo y Vivienda
A11: C02 | B11: Regiduría II | E11: 108 | F11: Juzgados Cívicos
A12: C03 | B12: Regiduría III | E12: 109 | F12: Registro Civil
A13: C04 | B13: Regiduría IV | E13: 110 | F13: Acción Cívica
A14: C05 | B14: Regiduría V | E14: 111 | F14: Coordinación de Delegaciones
... A52: Z00 | B52: DIRECCIÓN DE ASUNTOS INDÍGENAS | E52: 149 | F52: Fomento Turístico
E53: 150 | F53: Cultura
E54: 151 | F54: Atención a los Pueblos Indígenas
E55: 152 | F55: Atención a la Mujer
E56: 153 | F56: Atención a la Salud
E57: 154 | F57: Vialidad y Transporte
E58: 155 | F58: Área Jurídica
E59: 156 | F59: Suministro de Agua Potable
E60: 157 | F60: Alcantarillado y saneamiento
E61: 158 | F61: Tránsito
E62: 159 | F62: Secretaría Técnica de Seguridad Pública
E63: 160 | F63: Prevención y Control Ambiental
E64: 161 | F64: Unidad Substanciadora y Resolutora
... E75: 172 | F75: Atención a la Población de la Diversidad Sexual

Sheet GACETA 4
B1: Descripción
A2: 110101 | B2: Ingresos Propios del Municipio
A3: 110201 | B3: Transferencias a Organismos Descentralizados Municipales
A4: 120101 | B4: Financiamiento de Instituciones Financieras
A5: 120102 | B5: Financiamiento de Proveedores
A6: 140101 | B6: Ingresos líquidos de Entidades Públicas Municipales
A7: 140102 | B7: Otros Ingresos en especie de Gestión de Entidades Públicas Municipales
A8: 140103 | B8: Ingresos por Adeudos de Ejercicios Fiscales Anteriores de Entidades Públicas Municipales
A9: 140104 | B9: Ingresos por disponibilidades Presupuestarias de Entidades Públicas Municipales
A10: 150101 | B10: Ramo 28: Participaciones de los Ingresos Federales
A11: 150102 | B11: Fondo de Estabilización de los Ingresos de las Entidades Federativas FEIEF
A12: 160101 | B12: Ingresos no etiquetados derivados del Sistema Estatal de Coordinación Hacendaria
A13: 170101 | B13: Ingresos recibidos del Sector Privado
... A43: 260103 | B43: Otros recursos Estatales etiquetados

Sheet Hoja4
A2: 110101 | B2: 110101 | C2: =A2-B2 -> 0
A3: 110201 | B3: 110201 | C3: =A3-B3 -> 0
A4: 120101 | B4: 120101 | C4: =A4-B4 -> 0
A5: 120102 | B5: 120102 | C5: =A5-B5 -> 0
A6: 140101 | B6: 140101 | C6: =A6-B6 -> 0
A7: 140102 | B7: 140102 | C7: =A7-B7 -> 0
A8: 140103 | B8: 140103 | C8: =A8-B8 -> 0
A9: 140104 | B9: 140104 | C9: =A9-B9 -> 0
A10: 150101 | B10: 150101 | C10: =A10-B10 -> 0
A11: 150102 | B11: 150102 | C11: =A11-B11 -> 0
A12: 160101 | B12: 160101 | C12: =A12-B12 -> 0
A13: 170101 | B13: 170101 | C13: =A13-B13 -> 0
... A39: 250218 | B39: 250218 | C39: =A39-B39 -> 0
A40: 250219 | C40: =A40-B40 -> 250219
A41: 260101 | B41: 260101 | C41: =A41-B41 -> 0
A42: 260102 | B42: 260102 | C42: =A42-B42 -> 0
A43: 260103 | B43: 260103 | C43: =A43-B43 -> 0
